Workbook

Sheet Resumo
A1: Resumo dos dois cenarios
A2: Posicao em 16/09/2026
A5: CENARIO 1 - Clientes suspensos com valores em aberto (inadimplencia)
A6: Faixa | B6: Contratos | C6: Divida da faixa | D6: Recuperado | E6: Em aberto
A7: Caixa confirmado | B7: =COUNTIF(Inadimplencia!$L$5:$L$30,$A7) -> 3 | C7: =SUMIF(Inadimplencia!$L$5:$L$30,$A7,Inadimplencia!$G$5:$G$30) -> 7655.52 | D7: =SUMIF(Inadimplencia!$L$5:$L$30,$A7,Inadimplencia!$M$5:$M$30) -> 7655.52 | E7: =SUMIF(Inadimplencia!$L$5:$L$30,$A7,Inadimplencia!$N$5:$N$30) -> 0
A8: Negociado em curso | B8: =COUNTIF(Inadimplencia!$L$5:$L$30,$A8) -> 4 | C8: =SUMIF(Inadimplencia!$L$5:$L$30,$A8,Inadimplencia!$G$5:$G$30) -> 34794.71 | D8: =SUMIF(Inadimplencia!$L$5:$L$30,$A8,Inadimplencia!$M$5:$M$30) -> 34794.71 | E8: =SUMIF(Inadimplencia!$L$5:$L$30,$A8,Inadimplencia!$N$5:$N$30) -> 0
A9: Pago em parte | B9: =COUNTIF(Inadimplencia!$L$5:$L$30,$A9) -> 1 | C9: =SUMIF(Inadimplencia!$L$5:$L$30,$A9,Inadimplencia!$G$5:$G$30) -> 5950 | D9: =SUMIF(Inadimplencia!$L$5:$L$30,$A9,Inadimplencia!$M$5:$M$30) -> 1700 | E9: =SUMIF(Inadimplencia!$L$5:$L$30,$A9,Inadimplencia!$N$5:$N$30) -> 4250
A10: Sem movimento | B10: =COUNTIF(Inadimplencia!$L$5:$L$30,$A10) -> 18 | C10: =SUMIF(Inadimplencia!$L$5:$L$30,$A10,Inadimplencia!$G$5:$G$30) -> 279880.03 | D10: =SUMIF(Inadimplencia!$L$5:$L$30,$A10,Inadimplencia!$M$5:$M$30) -> 0 | E10: =SUMIF(Inadimplencia!$L$5:$L$30,$A10,Inadimplencia!$N$5:$N$30) -> 279880.03
A11: Total do cenario 1 | B11: =SUM(B7:B10) -> 26 | C11: =SUM(C7:C10) -> 328280.26 | D11: =SUM(D7:D10) -> 44150.23 | E11: =SUM(E7:E10) -> 284130.03
A13: Composicao da divida | C13: Valor | D13: % do total
A14: Debito faturado (nota emitida, cobravel hoje) | C14: =SUM(Inadimplencia!$E$5:$E$30) -> 105157.81 | D14: =C14/$C$16 -> 0.32032937
A15: Valor represado (parcela segurada na suspensao) | C15: =SUM(Inadimplencia!$F$5:$F$30) -> 223122.45 | D15: =C15/$C$16 -> 0.67967063
A16: Divida total | C16: =C14+C15 -> 328280.26 | D16: =C16/$C$16 -> 1
A18: Contato com o cliente | B18: Contratos | C18: Divida | D18: % da divida
A19: Responde | B19: =COUNTIF(Inadimplencia!$K$5:$K$30,"Sim") -> 12 | C19: =SUMIF(Inadimplencia!$K$5:$K$30,"Sim",Inadimplencia!$G$5:$G$30) -> 107741.59 | D19: =C19/$C$21 -> 0.32820003
A20: Nao responde | B20: =COUNTIF(Inadimplencia!$K$5:$K$30,"Nao") -> 14 | C20: =SUMIF(Inadimplencia!$K$5:$K$30,"Nao",Inadimplencia!$G$5:$G$30) -> 220538.67 | D20: =C20/$C$21 -> 0.67179997
A21: Total | B21: =B19+B20 -> 26 | C21: =C19+C20 -> 328280.26 | D21: =C21/$C$21 -> 1
A25: CENARIO 2 - Clientes em churn
A26: Estagio do distrato | B26: Contratos | C26: Valor de contrato | D26: Recebido
A27: Aguardando pagamento da multa | B27: =COUNTIF(Churn!$G$5:$G$32,$A27) -> 4 | C27: =SUMIF(Churn!$G$5:$G$32,$A27,Churn!$E$5:$E$32) -> 11020 | D27: =SUMIF(Churn!$G$5:$G$32,$A27,Churn!$H$5:$H$32) -> 15000
A28: Em negociacao | B28: =COUNTIF(Churn!$G$5:$G$32,$A28) -> 4 | C28: =SUMIF(Churn!$G$5:$G$32,$A28,Churn!$E$5:$E$32) -> 8917.41 | D28: =SUMIF(Churn!$G$5:$G$32,$A28,Churn!$H$5:$H$32) -> 0
A29: Aguardando pagamento de boletos | B29: =COUNTIF(Churn!$G$5:$G$32,$A29) -> 6 | C29: =SUMIF(Churn!$G$5:$G$32,$A29,Churn!$E$5:$E$32) -> 7421.36 | D29: =SUMIF(Churn!$G$5:$G$32,$A29,Churn!$H$5:$H$32) -> 0
A30: Distrato em conclusao | B30: =COUNTIF(Churn!$G$5:$G$32,$A30) -> 7 | C30: =SUMIF(Churn!$G$5:$G$32,$A30,Churn!$E$5:$E$32) -> 5988.4 | D30: =SUMIF(Churn!$G$5:$G$32,$A30,Churn!$H$5:$H$32) -> 0
A31: Aguardando retorno do cliente sobre a multa | B31: =COUNTIF(Churn!$G$5:$G$32,$A31) -> 4 | C31: =SUMIF(Churn!$G$5:$G$32,$A31,Churn!$E$5:$E$32) -> 5525.55 | D31: =SUMIF(Churn!$G$5:$G$32,$A31,Churn!$H$5:$H$32) -> 0
A32: Aguardando assinatura do distrato | B32: =COUNTIF(Churn!$G$5:$G$32,$A32) -> 2 | C32: =SUMIF(Churn!$G$5:$G$32,$A32,Churn!$E$5:$E$32) -> 4455.84 | D32: =SUMIF(Churn!$G$5:$G$32,$A32,Churn!$H$5:$H$32) -> 0
A33: Acordo de pagamento em curso | B33: =COUNTIF(Churn!$G$5:$G$32,$A33) -> 1 | C33: =SUMIF(Churn!$G$5:$G$32,$A33,Churn!$E$5:$E$32) -> 700 | D33: =SUMIF(Churn!$G$5:$G$32,$A33,Churn!$H$5:$H$32) -> 0
A34: Total do cenario 2 | B34: =SUM(B27:B33) -> 28 | C34: =SUM(C27:C33) -> 44028.56 | D34: =SUM(D27:D33) -> 15000
A37: Os dois cenarios nao somam na mesma base. A inadimplencia tem divida apurada (faturado + represado); a aba Churn registra valor de contrato, e o unico valor recebido e caixa efetivo. Todos os totais sao formulas: ao alterar o detalhe, o resumo se atualiza.

Sheet Inadimplencia
A1: Clientes suspensos com valores em aberto
A2: Posicao em 16/09/2026 | 26 contratos | Divida total = debito faturado + valor represado
A4: Contrato | B4: Cliente | C4: Produto | D4: MRR | E4: Debito faturado | F4: Valor represado | G4: Divida total | H4: Pcs repres. | I4: Dias atraso | J4: Data suspensao | K4: Responde? | L4: Faixa | M4: Recuperado | N4: Em aberto | O4: Status cobranca | P4: Anotacao CS | Q4: O que foi negociado
A5: 30002744-5 | B5: PETRAS DE LIMA TELLES I.E 153.832.963 | C5: AGRIMANAGER ERP | D5: 4467.33 | E5: 0 | F5: 58075.29 | G5: =E5+F5 -> 58075.29 | H5: 13 | I5: 366 | J5: 45901 | K5: Nao | L5: Sem movimento | M5: 0 | N5: =G5-M5 -> 58075.29 | O5: Sem detalhe (importação) | P5: Sem retorno nas tentativas de contato com a cliente. | Q5: Parcelas faturadas regularizadas com a Averbach, tentando contato para negociação das parcelas represadas. Em 31/08/2026 vertical solicitou contato com cliente para negociação. Cliente parou de responder tentativas de contato. Parcelas represadas desde 09/2025. Não negativado.
A6: 30003232-5 | B6: ALZIR PIMENTEL AGUIAR NETO IE: 19.569.743-0 | C6: AGRIMANAGER ERP | D6: 8758.44 | E6: 0 | F6: 43792.2 | G6: =E6+F6 -> 43792.2 | H6: 5 | I6: 219 | J6: 46111 | K6: Nao | L6: Sem movimento | M6: 0 | N6: =G6-M6 -> 43792.2 | O6: Cumprindo Acordo; | P6: Sem retorno nas tentativas de contato com a cliente. | Q6: Inadimplente - Acordo em andamento com Averbach (10x). Sem previsão de negociação das parcelas represadas. Em 20/04/2026 vertical ficou ciente da negociação em andamento. Parcelas represadas - R$ 43.792,20 (05/2026 a 09/26) fora acordo
A7: 30003903-5 | B7: PEDRO HENRIQUE PINTO FADEL IE: 95045009-66 | C7: AGRIMANAGER ERP | D7: 3098.61 | E7: 0 | F7: 35736.48 | G7: =E7+F7 -> 35736.48 | H7: 8 | I7: 194 | J7: 46023 | K7: Sim | L7: Sem movimento | M7: 0 | N7: =G7-M7 -> 35736.48 | O7: Inadimplência | P7: Em negociação, cliente não concorda com o valor do débito. | Q7: Inadimplente - Enviado cobrança, sem retorno. Em 09/01/2026 solicitado de acordo da vertical para negativação. Em contato com a cliente no whatsapp, não concorda com o valor do débito pois tentou renegociar redução anteriormente. Parcelas represadas desde 02/2026. Não negativado.
A8: 30003178-5 | B8: TELLUS AGROPECUARIA LTDA | C8: AGRIMANAGER ERP | D8: 2202.97 | E8: 2067.47 | F8: 22029.7 | G8: =E8+F8 -> 24097.17 | H8: 10 | I8: 378 | J8: 37591 | K8: Nao | L8: Sem movimento | M8: 0 | N8: =G8-M8 -> 24097.17 | O8: Inadimplência | P8: Sem retorno nas tentativas de contato com a cliente. | Q8: Inadimplente - Sem previsão de pagamento. Em 14/11/2025 solicitado de acordo da vertical para negativação. 01/12/2025 liberado negativação pela vertical. *NFs 150640 / 152385 / 154397 em processo de cancelamento.* Verificar de acordo da Vertical
A9: 30006200-5 | B9: LUIZ MOREIRA ROCHA | C9: MY FARM ERP | D9: 2500 | E9: 20862.9 | F9: 0 | G9: =E9+F9 -> 20862.9 | H9: 0 | I9: 64 | J9: 46259 | K9: Sim | L9: Negociado em curso | M9: 20862.9 | N9: =G9-M9 -> 0 | O9: Inadimplência | P9: Pgto entrada realizado, restante será pago ainda hoje | Q9: Valor cheio fechado a vista via PIX e subido ao financeiro. Por motivo nao esclarecido para a operacao, foi ofertado parcelamento e o cliente pagou a primeira parcela. Em seguida procurou novamente a Amanda dizendo que queria pagar tudo; o restante foi subido para o cliente e aguardamos o comprovante.
A10: 30005824-5 | B10: CHRISTOPHER TERRENGUI IE 138736561 | C10: MY FARM ERP | D10: 10686.36 | E10: 14877.45 | F10: 1781.06 | G10: =E10+F10 -> 16658.51 | H10: 2 | I10: 406 | J10: 45901 | K10: Nao | L10: Sem movimento | M10: 0 | N10: =G10-M10 -> 16658.51 | O10: Inadimplência | P10: Sem retorno nas tentativas de contato com a cliente. | Q10: Inadimplente - Sem previsão de pagamento. Em 09/11/2025 solicitado informação quanto a implantação devido ao débito em aberto. Projeto com pendência, tem bloqueio para negativação junto ao Serasa. Verificar de acordo da Vertical
A11: 30006051-5 | B11: FYLLIPE CARVALHO FREITAS BARROS | C11: MY FARM ERP | D11: 902.5 | E11: 9610 | F11: 6317.5 | G11: =E11+F11 -> 15927.5 | H11: 7 | I11: 278 | J11: 46050 | K11: Nao | L11: Sem movimento | M11: 0 | N11: =G11-M11 -> 15927.5 | O11: Inadimplência | P11: Sem retorno do cliente nas tentativas de contato | Q11: Inadimplente - Sem previsão de pagamento. Em 28/01/2026 enviado solicitação para suspender plataforma. 17/02/2026 liberado negativação pela vertical. Sem retorno nas tentativas de contato. Verificar de acordo da Vertical
A12: 30005936-5 | B12: SILVANO ROGER DA SILVA | C12: MY FARM ERP | D12: 750 | E12: 9000 | F12: 6000 | G12: =E12+F12 -> 15000 | H12: 8 | I12: 333 | J12: 46054 | K12: Nao | L12: Sem movimento | M12: 0 | N12: =G12-M12 -> 15000 | O12: Inadimplência | P12: Sem retorno do cliente (3x) | Q12: Inadimplente - Sem previsão de pagamento. Em 26/12/2025 enviado solicitação para suspender plataforma. Solicitado bloqueio da plataforma em 26/12/2025. Verificar de acordo da Vertical
A13: 30006062-5 | B13: FALCON AGRICOLA LTDA | C13: MY FARM ERP | D13: 1580 | E13: 5959.02 | F13: 7900 | G13: =E13+F13 -> 13859.02 | H13: 5 | I13: 125 | J13: 46094 | K13: Sim | L13: Sem movimento | M13: 0 | N13: =G13-M13 -> 13859.02 | O13: Inadimplência | P13: Cliente solicitou cancelamento por email ontem. | Q13: Inadimplente - Sem previsão de pagamento. Em 13/03/2026 enviado solicitação para suspender plataforma. 19/03/2026 liberado negativação pela vertical. Reiterado Cobrança (e-mail-whatsapp).
A14: 30002424-5 | B14: MARCOS AURELIO SINOPOLI | C14: AGRIMANAGER ERP | D14: 3380.27 | E14: 0 | F14: 13521.08 | G14: =E14+F14 -> 13521.08 | H14: 4 | I14: 96 | J14: 46128 | K14: Nao | L14: Sem movimento | M14: 0 | N14: =G14-M14 -> 13521.08 | O14: Cumprindo Acordo; | P14: Sem retorno nas tentativas de contato com a cliente. | Q14: Acordo em andamento - Reativação ocorrerá após cumprimento total da renegociação. Em 20/04/2026 solicitado de acordo da vertical para negativação. Parcelas represadas - R$ 13.521,08 (06/2026 a 09/26) fora acordo
A15: 30001698-1 | B15: JOAO BATISTA CONSENTINI FILHO I.E.11.457.541-0 | C15: AGRIMANAGER ERP | D15: 4204.55 | E15: 0 | F15: 10688.86 | G15: =E15+F15 -> 10688.86 | H15: 2 | I15: 160 | J15: 46086 | K15: Nao | L15: Sem movimento | M15: 0 | N15: =G15-M15 -> 10688.86 | O15: Cumprindo Acordo; | P15: Sem retorno nas tentativas de contato com a cliente. | Q15: Acordo em andamento - Reativação ocorrerá após cumprimento total da renegociação. Em 09/07/2026 vertical solicitou retorno para negociação com cliente. Parcelas represadas - R$ 10.688,86 (08/26 e 09/26) fora acordo
A16: 30005234-5 | B16: VITOR MARCIO DUMONCEL E OUTROS IE: 13.890.735-8 | C16: AGRIMANAGER ERP | D16: 4876.6 | E16: 0 | F16: 9753.2 | G16: =E16+F16 -> 9753.2 | H16: 2 | I16: 145 | J16: 46034 | K16: Sim | L16: Negociado em curso | M16: 9753.2 | N16: =G16-M16 -> 0 | O16: Inadimplência - em negociação | P16: Pgto previsto dia 21/09 | Q16: Acordo em andamento - Reativação ocorrerá após cumprimento total da renegociação. Em 22/07/2025 solicitado informação quanto a implantação devido ao débito em aberto. Pagamento previsto para o dia 18/09. Parcelas represadas - R$ 9.753,20 (08/26 e 09/26) fora acordo
... A30: 30001840-5 | B30: MARCIA ANGELICA BARBOZA CORADINI IE 13898617-7 | C30: MY FARM ERP | D30: 118.46 | E30: 346.02 | F30: 355.38 | G30: =E30+F30 -> 701.4 | H30: 3 | I30: 127 | J30: 46176 | K30: Nao | L30: Sem movimento | M30: 0 | N30: =G30-M30 -> 701.4 | O30: Inadimplência | P30: Sem retorno nas tentativas de contato com a cliente. | Q30: Inadimplente - Sem previsão de pagamento. Em 30/06/2026 enviado solicitação para suspender plataforma. Em 02/01/2026 solicitamos de acordo para negativação, vertical ficou de tentar contato antes da negativação porém sem retorno, seguimos com a negativação. Reiterado Cobrança (e-mail-whatsapp).
B31: TOTAL | D31: =SUM(D5:D30) -> 59016.38 | E31: =SUM(E5:E30) -> 105157.81 | F31: =SUM(F5:F30) -> 223122.45 | G31: =SUM(G5:G30) -> 328280.26 | M31: =SUM(M5:M30) -> 44150.23 | N31: =SUM(N5:N30) -> 284130.03
A33: Legenda das faixas
A34: Caixa confirmado | B34: Dinheiro ja compensado. Inclui a parte faturada paga por Theodoro Ricardo de Andrade.
A35: Negociado em curso | B35: Valor fechado com o cliente, recebimento em andamento ou com data marcada.
A36: Pago em parte | B36: Pagou o debito faturado e recusou o valor represado. Contrato cancelado.
A37: Sem movimento | B37: Sem pagamento e sem acordo ate 16/09/2026.
A39: Fonte: Clientes Suspensos e Tratados por CS - Posicao em 16-09-2026.xlsx, aba Inadimplencia. As colunas Recuperado e Faixa foram atribuidas a partir da anotacao da CS e da posicao informada pela coordenacao em 16/09/2026, pois a base de origem nao possui coluna de valor pago.

Sheet Churn
A1: Clientes em churn
A2: Posicao em 16/09/2026 | 28 contratos | O valor em jogo e multa de distrato e boleto em aberto, nao mensalidade
A4: Contrato | B4: Cliente | C4: Produto | D4: Vertical | E4: Valor de contrato | F4: Substatus | G4: Estagio | H4: Recebido | I4: Houve recebimento? | J4: Acao de curadoria | K4: Observacao CS | L4: Resumo da anotacao
A5: 30005780-5 | B5: AGRO SANTA CLARA LTDA | C5: AGRIMANAGER ERP | D5: PRODUTORES AGRICOLAS | E5: 4594.51 | F5: RISCO CHURN | G5: Em negociacao | H5: 0 | I5: Nao | J5: Em Negociação | L5: CHURN - ASSINATURA DE DISTRATO Cliente solicitou o cancelamento do contrato (e-mail: natanael@7campos.com.br). Estamos aguardando retorno do CS
A6: 30006028-5 | B6: LUCIVAL PORTILHO ARANTES IE 29.474.545-9 | C6: AGRIMANAGER ERP | D6: PRODUTORES AGRICOLAS | E6: 4248.62 | F6: RISCO CHURN | G6: Aguardando pagamento da multa | H6: 15000 | I6: Sim | J6: Aguardando Pagamento Multa | K6: Cliente pagou R$ 15.000,00 em 16/09. O valor cobre debito em aberto e multa de distrato dos DOIS contratos desta inscricao estadual (30006028-5 e 30006243-5), que somam R$ 5.896,12 de valor de contrato. Lancado integralmente nesta linha para nao duplicar. | L6: CHURN - ASSINATURA DE DISTRATO CLIENTE SOLICITOU O CANCELAMENTO DO CONTRATO
A7: 30001494-1 | B7: PEDRO JOSE BERTUOL | C7: AGRIMANAGER ERP | D7: PRODUTORES AGRICOLAS | E7: 3927.73 | F7: RISCO CHURN | G7: Aguardando assinatura do distrato | H7: 0 | I7: Nao | J7: Aguardando Assinatura Distrato | L7: CHURN - ASSINATURA DE DISTRATO CLIENTE SOLICITOU O CANCELAMENTO DO CONTRATO
A8: 30003130-5 | B8: GEMIRO CARAFINI IE: 11.106.270-5 | C8: AGRIMANAGER ERP | D8: PRODUTORES AGRICOLAS | E8: 2581.48 | F8: RISCO CHURN | G8: Aguardando pagamento da multa | H8: 0 | I8: Nao | J8: Aguardando Pagamento Multa | L8: CHURN - ASSINATURA DE DISTRATO CLIENTE SOLICITOU CANCELAMENTO DO CONTRATO
A9: 30005811-5 | B9: AUGUSTO CESAR ANDRADE MAIA | C9: MY FARM ERP | D9: PRODUTORES AGRICOLAS | E9: 2542.4 | F9: RISCO CHURN | G9: Aguardando pagamento da multa | H9: 0 | I9: Nao | J9: Aguardando Pagamento Multa | L9: CHURN - ASSINATURA DE DISTRATO Cliente solicitou o cancelamento do c
A10: 30005366-5 | B10: ALEX ROBERTO DOS SANTOS ARRUDA IE: 13714988-3 | C10: MY FARM ERP | D10: PRODUTORES AGRICOLAS | E10: 2217.92 | F10: RISCO CHURN | G10: Aguardando pagamento de boletos | H10: 0 | I10: Nao | J10: Aguardando pagamento de boletos | L10: CHURN - ASSINATURA DE DISTRATO Cliente solicitou o cancelamento do contrato
A11: 30003665-5 | B11: TIAGO GODOY VILELA E OUTRO IE: 13.527.389-7 | C11: AGRIMANAGER ERP | D11: PRODUTORES AGRICOLAS | E11: 2144.87 | F11: RISCO CHURN | G11: Aguardando pagamento de boletos | H11: 0 | I11: Nao | J11: Aguardando pagamento de boletos | L11: CHURN - ASSINATURA DE DISTRATO CLIENTE SOLICITOU O CANCELAMENTO DO CONTRATO
A12: 30007127-5 | B12: AGRO ALIANCA LTDA | C12: MY FARM ERP | D12: PRODUTORES AGRICOLAS | E12: 1950 | F12: RISCO CHURN | G12: Em negociacao | H12: 0 | I12: Nao | J12: Em Negociação | L12: CHURN - ASSINATURA DE DISTRATO CLIENTE SOLICITOU CANCELAMENTO DO CONTRATO
A13: 30005213-5 | B13: FERNANDO LUNARDI E OUTROS IE: 13.554.998-1 | C13: AGRIMANAGER ERP | D13: PRODUTORES AGRICOLAS | E13: 1890.33 | F13: RISCO CHURN | G13: Aguardando retorno do cliente sobre a multa | H13: 0 | I13: Nao | J13: Aguardando retorno cliente Multa | L13: CHURN
A14: 30003425-5 | B14: FABIO GIOVANNI MARTINS CARRAPATEIRA IE: 28.801.052-3 | C14: AGRIMANAGER ERP | D14: PRODUTORES AGRICOLAS | E14: 1654.4 | F14: RISCO CHURN | G14: Aguardando retorno do cliente sobre a multa | H14: 0 | I14: Nao | J14: Aguardando retorno cliente Multa | L14: CHURN - ASSINATURA DE DISTRATO Cliente pagava por resgate. No momento de voltar a pagar pelo sistema, o cliente manifestou o desejo de cancelamento de contrato. Rodrigo Mendonça tratando do cancelamento. Suspenso até conclusão
A15: 30006243-5 | B15: LUCIVAL PORTILHO ARANTES IE 29.474.545-9 | C15: ALIARE CLOUD - PR | D15: PRODUTORES AGRICOLAS | E15: 1647.5 | F15: RISCO CHURN | G15: Aguardando pagamento da multa | H15: 0 | I15: Sim | J15: Aguardando Pagamento Multa | K15: Pagamento registrado no contrato 30006028-5, do mesmo cliente. Ver aquela linha. | L15: CHURN - ASSINATURA DE DISTRATO CLIENTE SOLICITOU CANCELAMENTO DO CONTRATO
A16: 30002284-5 | B16: JOSE DIAS DE MELO NETO - IE 11.377.955-0 | C16: AGRIMANAGER ERP | D16: PRODUTORES AGRICOLAS | E16: 1597.39 | F16: INADIMPLENCIA | G16: Distrato em conclusao | H16: 0 | I16: Nao | J16: Processo de Distrato | L16: Em processo de cancelamento.
A17: 30005737-5 | B17: ORDATA LTDA | C17: MY FARM ERP | D17: PRODUTORES AGRICOLAS | E17: 1422.9 | F17: RISCO CHURN | G17: Em negociacao | H17: 0 | I17: Nao | J17: Em Negociação | L17: CHURN
A18: 30004447-5 | B18: IVAN ALVES SILVA | C18: MY FARM ERP | D18: PRODUTORES AGRICOLAS | E18: 1202.27 | F18: INADIMPLENCIA | G18: Distrato em conclusao | H18: 0 | I18: Nao | J18: churn - Inadimplente desde 12/2025 - solicitação de cancelamento 06/2026 | L18: Em processo de cancelamento - Cliente não pagou a multa
A19: 30005572-5 | B19: LEANDRO GAI ANVERSA | C19: ALIARE CLOUD - PR | D19: PRODUTORES AGRICOLAS | E19: 1201.62 | F19: RISCO CHURN | G19: Aguardando pagamento de boletos | H19: 0 | I19: Nao | J19: Aguardando pagamento de boletos | L19: CHURN - ASSINATURA DE DISTRATO Cliente solicitou o cancelamento do contrato. Ticket 795460
A20: 30005742-5 | B20: GILIARDE RODRIGUES DA SILVA | C20: MY FARM ERP | D20: PRODUTORES AGRICOLAS | E20: 1200 | F20: RISCO CHURN | G20: Aguardando retorno do cliente sobre a multa | H20: 0 | I20: Nao | J20: Aguardando retorno cliente Multa | L20: CHURN
A21: 30005913-5 | B21: BEATRIZ COSTA FRANCO | C21: MY FARM ERP | D21: PRODUTORES AGRICOLAS | E21: 950 | F21: INADIMPLENCIA | G21: Em negociacao | H21: 0 | I21: Nao | J21: Churn, o valor foi negociado em 2x de R$ 1000 e foi repassado a cobrança para o time de contas a receber | L21: Em processo de cancelamento.
A22: 30004420-5 | B22: ALMIR DAL ROVERE IE: 00000005692121 | C22: MY FARM ERP | D22: PRODUTORES AGRICOLAS | E22: 924.66 | F22: EM NEGOCIACAO | G22: Distrato em conclusao | H22: 0 | I22: Nao | J22: Suspensão realizada pelo faturamento, após pesquisa cliente não quis renovar. | L22: CLIENTE NÃO QUIS RENOVAR O CONTRATO
A23: 30005970-5 | B23: VOLMIR ANTONIO FAVEIRO | I.E. 002638676.00-50 | C23: MY FARM ERP | D23: PRODUTORES AGRICOLAS | E23: 896 | F23: RISCO CHURN | G23: Aguardando pagamento de boletos | H23: 0 | I23: Nao | J23: Aguardando pagamento de boletos | L23: CHURN - ASSINATURA DE DISTRATO Cliente solicitou o cancelamento do contrato. E-mail: fazenda@agrosistemas.com.br
A24: 30005679-5 | B24: ELDON RICARDO BECKMAMM | C24: MY FARM ERP | D24: PRODUTORES AGRICOLAS | E24: 780.82 | F24: RISCO CHURN | G24: Aguardando retorno do cliente sobre a multa | H24: 0 | I24: Nao | J24: Aguardando retorno cliente Multa | L24: CHURN - ASSINATURA DE DISTRATO Cliente solicitou o cancelamento do contrato. E-mail: fazendasarandi.mtpa@gmail.com
A25: 30003080-5 | B25: LUCIANO JAYME GUIMARAES | C25: MY FARM ERP | D25: PRODUTORES AGRICOLAS | E25: 702.06 | F25: RISCO CHURN | G25: Distrato em conclusao | H25: 0 | I25: Nao | J25: Confirmar distrato e registrar lição de churn | L25: CHURN - ASSINATURA DE DISTRATO CLIENTE SOLICITOU O CANCELAMENTO DO CONTRATO. TICKET 800613
A26: 30007041-5 | B26: MARCO ANTONIO GIACON | C26: MY FARM ERP | D26: PRODUTORES AGRICOLAS | E26: 700 | F26: INADIMPLENCIA | G26: Acordo de pagamento em curso | H26: 0 | I26: Nao | J26: Acompanhar acordo de pagamento - Inadimplente desde 02/2026 - solicitação de cancelamento 06/2026-solicitou o cancelamento após cobrança | L26: Em processo de cancelamento.
A27: 30006190-5 | B27: JOAO MIGUEL GIONGO FREITAS | C27: MY FARM ERP | D27: PRODUTORES AGRICOLAS | E27: 590 | F27: INADIMPLENCIA | G27: Distrato em conclusao | H27: 0 | I27: Nao | J27: churn - Inadimplente desde 01/2026 - solicitação de cancelamento 07/2026 | L27: Em processo de cancelamento.
... A32: 30004487-5 | B32: GIZELLY SANTOS IE 28.852.854-9 | C32: MY FARM ERP | D32: PRODUTORES AGRICOLAS | E32: 410.95 | F32: RISCO CHURN | G32: Aguardando pagamento de boletos | H32: 0 | I32: Nao | J32: Aguardando pagamento de boletos | L32: CHURN - ASSINATURA DE DISTRATO cliente solicitou o cancelamento do contrato
B33: TOTAL | E33: =SUM(E5:E32) -> 44028.56 | H33: =SUM(H5:H32) -> 15000
A35: Fonte: Clientes Suspensos e Tratados por CS - Posicao em 16-09-2026.xlsx, aba Churn. A coluna Estagio agrupa os textos livres da Acao de Curadoria. O unico recebimento registrado no periodo foi o de Lucival Portilho Arantes, lancado integralmente no contrato 30006028-5.
