Workbook

Sheet Resumo
B2: Anotações:
B3: Dos 63 contratos suspensos R$ 113k:
B4: 36 Contratos estavam relacionados a Inadimplencia R$ 71.072;
B5: 22 Contratos em Churn R$ 38k;
B6: 5 Contratos 'Em Negociaçã' valor 4k;
B8: Detalhamento | Apenas Status Inadimplencia
B10: Status Geral | C10: # | D10: R$ | G10: Produto | H10: # | I10: R$ | J10: %
B11: {=_xlfn._xlws.SORT(_xlfn.UNIQUE(Inadimplencia!J4:J27),,1)} -> Carteira Cobrança | C11: =COUNTIF(Inadimplencia!$J$4:$J$27,B11) -> 20 | D11: =SUMIF(Inadimplencia!J:J,Resumo!B11,Inadimplencia!H:H) -> 53527.17 | G11: {=_xlfn.UNIQUE(Inadimplencia!N4:N27)} -> AGRIMANAGER ERP | H11: =COUNTIF(Inadimplencia!$N$4:$N$27,G11) -> 10 | I11: =SUMIF(Inadimplencia!$N$4:$N$27,G11,Inadimplencia!$H$4:$H$27) -> 35235.63 | J11: =I11/$I$13 -> 0.62788766
B12: Escritório AVERBACH | C12: =COUNTIF(Inadimplencia!$J$4:$J$27,B12) -> 4 | D12: =SUMIF(Inadimplencia!J:J,Resumo!B12,Inadimplencia!H:H) -> 2590.56 | G12: MY FARM ERP | H12: =COUNTIF(Inadimplencia!$N$4:$N$27,G12) -> 14 | I12: =SUMIF(Inadimplencia!$N$4:$N$27,G12,Inadimplencia!$H$4:$H$27) -> 20882.1 | J12: =I12/$I$13 -> 0.37211234
C13: =COUNTIF(Inadimplencia!$J$4:$J$27,B13) -> 0 | D13: =SUMIF(Inadimplencia!J:J,Resumo!B13,Inadimplencia!H:H) -> 0 | H13: =SUM(H11:H12) -> 24 | I13: =SUM(I11:I12) -> 56117.73
C14: =COUNTIF(Inadimplencia!$J$4:$J$27,B14) -> 0 | D14: =SUMIF(Inadimplencia!J:J,Resumo!B14,Inadimplencia!H:H) -> 0
C15: =COUNTIF(Inadimplencia!$J$4:$J$27,B15) -> 0 | D15: =SUMIF(Inadimplencia!J:J,Resumo!B15,Inadimplencia!H:H) -> 0
C16: =COUNTIF(Inadimplencia!$J$4:$J$27,B16) -> 0 | D16: =SUMIF(Inadimplencia!J:J,Resumo!B16,Inadimplencia!H:H) -> 0
C17: =SUM(C11:C16) -> 24 | D17: =SUM(D11:D16) -> 56117.73
B23: Reclassificação | C23: # | D23: R$ Total | E23: % | G23: AGRIMANAGER ERP | H23: MY FARM ERP
B24: Cumprindo Acordo | C24: 3 | D24: 16343 | E24: =D24/$D$30 -> 0.22995107 | F24: <> | G24: 16343 | H24: 0
B25: Migração AGM>My Farm | C25: 1 | D25: 1859.64 | E25: =D25/$D$30 -> 0.026165711 | F25: <> | G25: 1859.64 | H25: 0
B26: Churn | C26: 7 | D26: 7133 | E26: =D26/$D$30 -> 0.10036352 | F26: <> | G26: 1597 | H26: 5536
B27: Carteira CaR | Estável | C27: 2 | D27: 9344 | E27: =D27/$D$30 -> 0.13147298 | F27: <> | G27: 9344 | H27: 0
B28: Recuperado | C28: 2 | D28: 2884 | E28: =D28/$D$30 -> 0.040578774 | F28: <> | G28: 1199.89 | H28: 1684.11
B29: Em validação Dinamara | Vertical Acionada | C29: 21 | D29: 33508 | E29: =D29/$D$30 -> 0.47146794 | F29: <> | G29: 11779 | H29: 21729
C30: =SUM(C24:C29) -> 36 | D30: =SUM(D24:D29) -> 71071.64 | E30: =SUM(E24:E29) -> 1 | G30: =SUM(G24:G29) -> 42122.53 | H30: =SUM(H24:H29) -> 28949.11

Sheet Geral
C3: Inadimplencia | F3: Churn | I3: Em Negociação | L3: Total Geral
B4: Produto | C4: # | D4: Valor | F4: # | G4: Valor | I4: # | J4: Valor | L4: # | M4: Valor
B5: AGRIMANAGER ERP | C5: =COUNTIF(Inadimplencia!D:D,Geral!$B5) -> 10 | D5: =SUMIF(Inadimplencia!D:D,Geral!$B5,Inadimplencia!H:H) -> 35235.63 | F5: =COUNTIF(Churn!F:F,Geral!$B5) -> 8 | G5: =SUMIF(Churn!F:F,Geral!$B5,Churn!I:I) -> 22639.33 | I5: =COUNTIF(Em_Negociacao!E:E,Geral!$B5) -> 1 | J5: =SUMIF(Em_Negociacao!E:E,Geral!$B5,Em_Negociacao!H:H) -> 1859.64 | L5: =C5+F5+I5 -> 19 | M5: =D5+G5+J5 -> 59734.6
B6: MY FARM ERP | C6: =COUNTIF(Inadimplencia!D:D,Geral!$B6) -> 17 | D6: =SUMIF(Inadimplencia!D:D,Geral!$B6,Inadimplencia!H:H) -> 23780.75 | F6: =COUNTIF(Churn!F:F,Geral!$B6) -> 18 | G6: =SUMIF(Churn!F:F,Geral!$B6,Churn!I:I) -> 18540.11 | I6: =COUNTIF(Em_Negociacao!E:E,Geral!$B6) -> 9 | J6: =SUMIF(Em_Negociacao!E:E,Geral!$B6,Em_Negociacao!H:H) -> 11393.09 | L6: =C6+F6+I6 -> 44 | M6: =D6+G6+J6 -> 53713.95
B7: ALIARE CLOUD - PR | C7: =COUNTIF(Inadimplencia!D:D,Geral!$B7) -> 0 | D7: =SUMIF(Inadimplencia!D:D,Geral!$B7,Inadimplencia!H:H) -> 0 | F7: =COUNTIF(Churn!F:F,Geral!$B7) -> 2 | G7: =SUMIF(Churn!F:F,Geral!$B7,Churn!I:I) -> 2849.12 | I7: =COUNTIF(Em_Negociacao!E:E,Geral!$B7) -> 0 | J7: =SUMIF(Em_Negociacao!E:E,Geral!$B7,Em_Negociacao!H:H) -> 0 | L7: =C7+F7+I7 -> 2 | M7: =D7+G7+J7 -> 2849.12
B8: Geral | C8: =SUM(C5:C7) -> 27 | D8: =SUM(D5:D7) -> 59016.38 | F8: =SUM(F5:F7) -> 28 | G8: =SUM(G5:G7) -> 44028.56 | I8: =SUM(I5:I6) -> 10 | J8: =SUM(J5:J6) -> 13252.73 | L8: =SUM(L5:L7) -> 65 | M8: =SUM(M5:M7) -> 116297.67
B9: % | D9: =D8/$M$8 -> 0.50745969 | G9: =G8/$M$8 -> 0.37858506 | J9: =J8/$M$8 -> 0.11395525 | M9: =D9+G9+J9 -> 1

Sheet Inadimplencia
B2: =COUNTA(C4:C29) -> 26 | H2: =SUBTOTAL(9,H4:H1048576) -> 59016.38 | R2: =SUBTOTAL(9,R4:R1048576) -> 105157.81 | S2: =SUBTOTAL(9,S4:S1048576) -> 223122.45 | T2: =SUBTOTAL(9,T4:T1048576) -> 328280.26
B3: Contrato | C3: Cliente | D3: Produto | E3: OBS. CS | F3: Status Contrato | G3: SubStatusContrato | H3: R$ Contrato | I3: Obs Cobrança | J3: Estágio | K3: Status CaR | L3: Dinamara | M3: Observação Vertical | N3: Produto | O3: Perfil cliente | P3: Risco Financeiro | Q3: Dias de Atraso Atual | R3: (R$) Débito faturado | S3: (R$) Valor represado | T3: Total Dívida (R$) | U3: Qtde Pcs Represadas | V3: Data suspensão | W3: Telemetria | X3: Suporte Bloqueado | Y3: Conexão E-mail
B4: 30003232-5 | C4: ALZIR PIMENTEL AGUIAR NETO IE: 19.569.743-0 | D4: AGRIMANAGER ERP | E4: Reuniao 25/09 às 15:00 para tratar dos débitos. | F4: SUSPENSO | G4: INADIMPLENCIA | H4: 8758.44 | I4: Inadimplente - Acordo em andamento com Averbach (10x). Sem previsão de negociação das parcelas represadas. Em 20/04/2026 vertical ficou ciente da negociação em andamento. | J4: Carteira Cobrança | K4: Cumprindo Acordo; | L4: Parcelas represadas - R$ 43.792,20 (05/2026 a 09/26) fora acordo | N4: AGRIMANAGER ERP | O4: Recorrente em renegociações não cumpridas | P4: Risco Alto: Score 239. R$ 54,06 Milhões em anotações negativas , sendo R$ 38,96 milhões em instituições financeiras, Protesto ativo no valor de R$ 19,47 mil. | Q4: 219 | R4: 0 | S4: 43792.2 | T4: =R4+S4 -> 43792.2 | U4: 5 | V4: 46111 | Y4: Não propor Flexibilização 2027
B5: 30002424-5 | C5: MARCOS AURELIO SINOPOLI | D5: AGRIMANAGER ERP | E5: Acordo realizado com a cliente 18/09. | F5: SUSPENSO | G5: INADIMPLENCIA | H5: 3380.27 | I5: Acordo em andamento - Reativação ocorrerá após cumprimento total da renegociação. Em 20/04/2026 solicitado de acordo da vertical para negativação. | J5: Carteira Cobrança | K5: Cumprindo Acordo; | L5: Parcelas represadas - R$ 13.521,08 (06/2026 a 09/26) fora acordo | N5: AGRIMANAGER ERP | O5: Recorrente em renegociações não cumpridas | P5: Risco Alto: Score 280. R$ 14,06 Milhões em anotações negativas, sendo R$ 9,72 milhões em instituições financeiras, Protesto ativo no valor de R$ 6,75 milhões. 8 Ações judiciais, sendo 2 execuções. | Q5: 96 | R5: 0 | S5: 13521.08 | T5: =R5+S5 -> 13521.08 | U5: 4 | V5: 46128 | Y5: Não propor Flexibilização 2027
B6: 30001698-1 | C6: JOAO BATISTA CONSENTINI FILHO I.E.11.457.541-0 | D6: AGRIMANAGER ERP | F6: SUSPENSO | G6: INADIMPLENCIA | H6: 4204.55 | I6: Acordo em andamento - Reativação ocorrerá após cumprimento total da renegociação. Em 09/07/2026 vertical solicitou retorno para negociação com cliente. | J6: Carteira Cobrança | K6: Cumprindo Acordo; | L6: Parcelas represadas - R$ 10.688,86 (08/26 e 09/26) fora acordo | N6: AGRIMANAGER ERP | O6: Recorrente em renegociações não cumpridas | P6: Risco Alto: Score 314. R$ 389,33 Milhões em anotações negativas, sendo R$ 299,56 milhões em instituições financeiras, Protesto ativo no valor de R$ 5,78 milhões. 17 Ações judiciais, sendo 13 execuções. | Q6: 160 | R6: 0 | S6: 10688.86 | T6: =R6+S6 -> 10688.86 | U6: 2 | V6: 46086 | Y6: Não propor Flexibilização 2027
B7: 30005234-5 | C7: VITOR MARCIO DUMONCEL E OUTROS IE: 13.890.735-8 | D7: AGRIMANAGER ERP | E7: Acordo realizado, entrada de 10 k pago 23/09 | F7: SUSPENSO | G7: INADIMPLENCIA | H7: 4876.6 | I7: Acordo em andamento - Realizamos um novo acordo. Entrada – 23/09/2026: R$ 10.000,00 – PAGA E CONFIRMADA Parcela 1 – 25/10/2026: R$ 8.209,93 Parcela 2 – 25/11/2026: R$ 8.209,93 Parcela 3 – 25/12/2026: R$ 8.209,93 | J7: Carteira Cobrança | K7: Inadimplência - em negociação | L7: Parcelas represadas - R$ 9.753,20 (08/26 e 09/26) fora acordo | M7: Pagamento previsto para o dia 18/09. | N7: AGRIMANAGER ERP | O7: Primeira renegociação realizada | P7: Risco Alto: Score 330. R$ 28,75 Milhões em anotações negativas, sendo R$ 20,10 milhões em instituições financeiras, Protesto ativo no valor de R$ 1,83 milhões. 06 Ações judiciais, sendo 13 execuções. | Q7: 145 | R7: 0 | S7: =4876.6*2 -> 9753.2 | T7: =R7+S7 -> 9753.2 | U7: 2 | V7: 46034 | Y7: Não propor Flexibilização 2027
B8: 30002744-5 | C8: PETRAS DE LIMA TELLES I.E 153.832.963 | D8: AGRIMANAGER ERP | E8: Sem retorno nas tentativas de contato com a cliente. | F8: SUSPENSO | G8: INADIMPLENCIA | H8: 4467.33 | I8: Parcelas faturadas regularizadas com a Averbach, tentando contato para negociação das parcelas represadas. Em 31/08/2026 vertical solicitou contato com cliente para negociação. | J8: Carteira Cobrança | K8: Sem detalhe (importação) | L8: Parcelas represadas desde 09/2025. Não negativado. | M8: Cliente parou de responder tentativas de contato. | N8: AGRIMANAGER ERP | O8: Inadimplência recorrente, regularizou débito na Averbach | P8: Risco Alto: Score bloqueado. R$ 61,88 Milhões em anotações negativas, sendo R$ 51,77 milhões em instituições financeiras, Protesto ativo no valor de R$ 3,15 milhões. 08 Ações judiciais, sendo 7 execuções. | Q8: 366 | R8: 0 | S8: 58075.29 | T8: =R8+S8 -> 58075.29 | U8: 13 | V8: 45901 | Y8: Não propor Flexibilização 2027
B9: 30003903-5 | C9: PEDRO HENRIQUE PINTO FADEL IE: 95045009-66 | D9: AGRIMANAGER ERP | E9: Em negociação, enviei a seguinte proposta, está em análise pelo cliente. Ficaria da seguinte maneira: O débito hoje está em R$ 35.736,48 Parcelaríamos em 5x de R$ 3.573,64 que se encerram em Fevereiro, e ai o restante do pgto, ficaria para 30/03 do ano que vem. | F9: SUSPENSO | G9: INADIMPLENCIA | H9: 3098.61 | I9: Inadimplente - Enviado cobrança, sem retorno. Em 09/01/2026 solicitado de acordo da vertical para negativação. | J9: Carteira Cobrança | K9: Inadimplência | L9: Parcelas represadas desde 02/2026. Não negativado. | M9: Em contato com a cliente no whatsapp, não concorda com o valor do débito pois tentou renegociar redução anteriormente. | N9: AGRIMANAGER ERP | O9: Primeira renegociação cumprida na totalidade | P9: Risco Alto: Score bloqueado. R$ 89,29 Milhões em anotações negativas, sendo R$72,09 milhões em instituições financeiras, Protesto ativo no valor de R$ 3,98 milhões. 08 Ações judiciais (execuções). | Q9: 194 | R9: 0 | S9: 35736.48 | T9: =R9+S9 -> 35736.48 | U9: 8 | V9: 46023 | Y9: Não propor Flexibilização 2027
B10: 30006200-5 | C10: LUIZ MOREIRA ROCHA | D10: MY FARM ERP | E10: Pgto entrada realizado, negociado em 3x | F10: SUSPENSO | G10: INADIMPLENCIA | H10: 2500 | I10: Realizou acordo. Entrada + 2x. Entrada paga e confirmada | J10: Carteira Cobrança | K10: Inadimplência | L10: Reiterado Cobrança (e-mail-whatsapp). | M10: Cliente solicitou valores atualizados e dados para pgto, enviado valores com desconto porém não retornou mais. | N10: MY FARM ERP | O10: Inadimplência recorrente, pouco tempo em atraso | Q10: 64 | R10: 20862.9 | S10: 0 | T10: =R10+S10 -> 20862.9 | U10: 0 | V10: 46259 | Y10: Em negociação - Proposta para quitação a vista com 15% de desconto enviada.
B11: 30003342-5 | C11: NOVA FRONTEIRA AGROPECUARIA LTDA | D11: AGRIMANAGER ERP | E11: Sem retorno nas tentativas de contato com a cliente. | F11: SUSPENSO | G11: INADIMPLENCIA | H11: 1784.94 | I11: Inadimplente - Enviado cobrança, sem retorno. Em 02/07/2026 solicitado de acordo da vertical para negativação. | J11: Carteira Cobrança | K11: Inadimplência | L11: Reiterado Cobrança (e-mail-whatsapp). | M11: Em contato com a cliente no whatsapp. Sem sucesso nas tentativas de contato. | N11: AGRIMANAGER ERP | O11: Inadimplência recorrente | P11: Risco Médio: Score 285. Sem restrições negativas. Capital social de R$ 25. Empresa contituída em 2022. | Q11: 44 | R11: 4955.97 | S11: 0 | T11: =R11+S11 -> 4955.97 | U11: 0 | V11: 46259 | Y11: Flexibilizar para 2027, com entrada de 20%
B12: 30000710-5 | C12: PAULO MASSAYOSHI MIZOTE | D12: AGRIMANAGER ERP | E12: Pagou | F12: SUSPENSO | G12: INADIMPLENCIA | H12: 1261.92 | I12: Realizaram pagamento total | J12: Carteira Cobrança | K12: Inadimplência | L12: Reiterado Cobrança (e-mail-whatsapp). | N12: AGRIMANAGER ERP | O12: Primeira atraso | P12: Baixo Risco: Score 717. Sem restrições negativas. | Q12: 59 | R12: 2523.84 | S12: 0 | T12: =R12+S12 -> 2523.84 | U12: 0 | V12: 46259 | Y12: Em acordo de Pagamento Time CaR
B13: 30006069-5 | C13: PABLO RAFAEL SCNHEIDER | D13: AGRIMANAGER ERP | E13: Renegociação da forma de pgto - Cliente acordou semestralmente mas foi lançado como mensal. | F13: SUSPENSO | G13: INADIMPLENCIA | H13: 1200 | I13: Pagou os débitos, falta só ajustar a cobrança para semestral, aguardando retorno do cliente. | J13: Carteira Cobrança | K13: Inadimplência | L13: Reiterado Cobrança (e-mail-whatsapp). | M13: Em 27/08/2026 vertical solicitou retorno ao cliente para negociação. Cliente não concorda com a cobrança mensal da assinatura, pois foi negociado a cobrança semestral. | N13: AGRIMANAGER ERP | O13: Primeira atraso | P13: Baixo Risco: Score 821. Sem restrições negativas. | Q13: 53 | R13: 2400 | S13: 0 | T13: =R13+S13 -> 2400 | U13: 0 | V13: 46259 | Y13: Em acordo de Pagamento Time CaR
B14: 30006056-5 | C14: JUAREZ CARLOS SILVA FILHO | D14: MY FARM ERP | E14: Pago | F14: SUSPENSO | G14: INADIMPLENCIA | H14: 650 | J14: Carteira Cobrança | K14: Inadimplência | L14: Reiterado Cobrança (e-mail-whatsapp). | M14: Cliente realizou o pagamento. | N14: MY FARM ERP | O14: Inadimplência recorrente | Q14: 96 | R14: 2600 | S14: 0 | T14: =R14+S14 -> 2600 | U14: 0 | V14: 46259 | Y14: Realizou o pgto via pix 14/09
B15: 30007162-5 | C15: ANA PAULA BANDEIRA DE LIMA | D15: MY FARM ERP | E15: Pago | F15: SUSPENSO | G15: INADIMPLENCIA | H15: 565 | J15: Carteira Cobrança | K15: Inadimplência | L15: Reiterado Cobrança (e-mail-whatsapp). | M15: Cliente realizou o pagamento. | N15: MY FARM ERP | O15: No geral, pagamentos em dia. Pulo de parcela. | Q15: 100 | R15: 2531.68 | S15: 0 | T15: =R15+S15 -> 2531.68 | U15: 0 | V15: 46259 | Y15: Realizou o pgto via pix
B16: 30003568-5 | C16: HENRIQUE REGES DE CARVALHO | D16: MY FARM ERP | E16: Sem retorno do cliente. Débito está com escritório de cobrança também. | F16: SUSPENSO | G16: INADIMPLENCIA | H16: 491.6 | I16: Inadimplente - Enviado cobrança, sem retorno. Em 10/08/2026 enviado solicitação para suspender plataforma. | J16: Carteira Cobrança | K16: Inadimplência | L16: Reiterado Cobrança (e-mail-whatsapp). | M16: Solicitado bloqueio da plataforma em 10/08/2026. | N16: MY FARM ERP | O16: Inadimplência recorrente | Q16: 96 | R16: 1474.8 | S16: 491.6 | T16: =R16+S16 -> 1966.4 | U16: 1 | V16: 46204
B17: 30004027-5 | C17: JOAO EVERTON PAULINO RAMOS ALVES - IE 002448697.03-57 | D17: MY FARM ERP | E17: Pagou | F17: SUSPENSO | G17: INADIMPLENCIA | H17: 427.11 | J17: Carteira Cobrança | K17: Inadimplência | L17: Reiterado Cobrança (e-mail-whatsapp). | M17: Cliente aceitou proposta de 15% de desconto no débito. Previsão de pgto 18/09 | N17: MY FARM ERP | O17: Inadimplência recorrente | Q17: 105 | R17: 1381.31 | S17: 0 | T17: =R17+S17 -> 1381.31 | U17: 0 | V17: 46259 | Y17: Pgto previsto para dia 18/09
B18: 30005824-5 | C18: CHRISTOPHER TERRENGUI IE 138736561 | D18: MY FARM ERP | E18: Em contato com cliente, me questionou valor dos débitos, levantei planilha com as infos e enviei para que ele pudesse avaliar, ele parou de dar retorno após isso. | F18: SUSPENSO | G18: INADIMPLENCIA | H18: 10686.36 | I18: Inadimplente - Sem previsão de pagamento. Em 09/11/2025 solicitado informação quanto a implantação devido ao débito em aberto. | J18: Carteira Cobrança | K18: Inadimplência | L18: Verificar de acordo da Vertical | M18: Projeto com pendência, tem bloqueio para negativação junto ao Serasa. | N18: MY FARM ERP | O18: Inadimplência recorrente | Q18: 406 | R18: 14877.45 | S18: =890.53*2 -> 1781.06 | T18: =R18+S18 -> 16658.51 | U18: 2 | V18: 45901
B19: 30003178-5 | C19: TELLUS AGROPECUARIA LTDA | D19: AGRIMANAGER ERP | E19: SOLICITARAM O CANCELAMENTO - NÃO POSSUEM MAIS PARCELAS REPRESADAS A SEREM COBRADAS. | F19: SUSPENSO | G19: INADIMPLENCIA | H19: 2202.97 | I19: Inadimplente - Sem previsão de pagamento. Em 14/11/2025 solicitado de acordo da vertical para negativação. | J19: Carteira Cobrança | K19: Inadimplência | L19: Verificar de acordo da Vertical | M19: 01/12/2025 liberado negativação pela vertical. *NFs 150640 / 152385 / 154397 em processo de cancelamento.* | N19: AGRIMANAGER ERP | O19: No geral, pagamentos em dia | P19: Baixo Risco: Score 570. Protesto ativo no valor de R$ 2.757,44. | Q19: 378 | R19: 2067.47 | S19: 22029.7 | T19: =R19+S19 -> 24097.17 | U19: 10 | V19: 37591 | Y19: Flexibilizar para 2027, com entrada de 20%
B20: 30006062-5 | C20: FALCON AGRICOLA LTDA | D20: MY FARM ERP | E20: Cliente solicitou cancelamento por email. | F20: SUSPENSO | G20: INADIMPLENCIA | H20: 1580 | I20: Inadimplente - Sem previsão de pagamento. Em 13/03/2026 enviado solicitação para suspender plataforma. | J20: Carteira Cobrança | K20: Inadimplência | L20: Reiterado Cobrança (e-mail-whatsapp). | M20: 19/03/2026 liberado negativação pela vertical. | N20: MY FARM ERP | O20: Inadimplência recorrente | Q20: 125 | R20: 5959.02 | S20: 7900 | T20: =R20+S20 -> 13859.02 | U20: 5 | V20: 46094
B21: 30006051-5 | C21: FYLLIPE CARVALHO FREITAS BARROS | D21: MY FARM ERP | E21: Sem retorno do cliente nas tentativas de contato | F21: SUSPENSO | G21: INADIMPLENCIA | H21: 902.5 | I21: Inadimplente - Sem previsão de pagamento. Em 28/01/2026 enviado solicitação para suspender plataforma. | J21: Escritório AVERBACH | K21: Inadimplência | L21: Verificar de acordo da Vertical | M21: 17/02/2026 liberado negativação pela vertical. Sem retorno nas tentativas de contato. | N21: MY FARM ERP | O21: Sem parcelas pagas. | Q21: 278 | R21: 9610 | S21: 6317.5 | T21: =R21+S21 -> 15927.5 | U21: 7 | V21: 46050
B22: 30005717-5 | C22: THEODORO RICARDO DE ANDRADE | D22: MY FARM ERP | E22: Pgto integral das pendencias 16/09 [Não houve pagamento dos valores represados] Houve tentativa de negociação e retenção junto à cliente, com alinhamento com o Financeiro para avaliarmos alternativas para os valores represados, considerando que a base estava suspensa e que a cliente já vinha buscando, há algum tempo, uma solução junto à equipe de cobranças, sem sucesso. A dificuldade em conduzir a negociação, somada ao desgaste gerado pelas tentativas anteriores de regularização e à insatisfação da cliente com a cobrança de valores referentes ao período em que permaneceu com o acesso bloqueado, comprometeu a possibilidade de acordo. Mesmo com as condições especiais disponibilizadas, a cliente optou por realizar apenas o pagamento das pendências faturadas, não aceitou negociar os valores represados e, posteriormente, formalizou o cancelamento, informando que pretende tratar judicialmente os valores remanescentes. | F22: SUSPENSO | G22: INADIMPLENCIA | H22: 850 | I22: Inadimplente - Sem previsão de pagamento. Em 16/07/2026 vertical solicitou contato com cliente para negociação. | J22: Carteira Cobrança | K22: Inadimplência | L22: Reiterado Cobrança (e-mail-whatsapp). | M22: Em 13/01/2026 solicitamos bloqueio da plataforma e reiteramos em 14/01. Em 28/01/2026 solicitamos apoio a vertical quanto a informação de telefone para contato com cliente, porém sem retorno. Em 16/07/2026 solicitaram retorno ao cliente para negociação. | N22: MY FARM ERP | O22: Primeira atraso. Pulo de parcela. | Q22: 409 | R22: 1700 | S22: 4250 | T22: =R22+S22 -> 5950 | U22: 5 | V22: 46114
B23: 30005936-5 | C23: SILVANO ROGER DA SILVA | D23: MY FARM ERP | E23: Sem retorno do cliente (3x) | F23: SUSPENSO | G23: INADIMPLENCIA | H23: 750 | I23: Inadimplente - Sem previsão de pagamento. Em 26/12/2025 enviado solicitação para suspender plataforma. | J23: Escritório AVERBACH | K23: Inadimplência | L23: Verificar de acordo da Vertical | M23: Solicitado bloqueio da plataforma em 26/12/2025. | N23: MY FARM ERP | O23: Primeiro atraso. | Q23: 333 | R23: 9000 | S23: 6000 | T23: =R23+S23 -> 15000 | U23: 8 | V23: 46054
B24: 30005102-5 | C24: JOSE ROSA DOS SANTOS | D24: MY FARM ERP | E24: Em negociação | F24: SUSPENSO | G24: INADIMPLENCIA | H24: 565.06 | I24: Inadimplente - Sem previsão de pagamento. Em 11/11/2025 enviado solicitação para suspender plataforma. | J24: Escritório AVERBACH | K24: Inadimplência | L24: Verificar de acordo da Vertical | M24: Em 15/01/2026 solicitamos de acordo para negativação. | N24: MY FARM ERP | O24: Inadimplência recorrente. | Q24: 357 | R24: 6780.76 | S24: 565.1 | T24: =R24+S24 -> 7345.86 | U24: 1 | V24: 45931
B25: 30001886-5 | C25: RONI CESAR FERREIRA ALVES MACHADO | D25: MY FARM ERP | E25: Acredito que a empresa fechou, cliente vinculado ao grupo maroq que está em RJ pelo TJMT. | F25: SUSPENSO | G25: INADIMPLENCIA | H25: 423.01 | I25: Inadimplente - Sem previsão de pagamento. Em 17/07/2026 solicitado apoio a vertical quanto a novos telefones de contato. | J25: Carteira Cobrança | K25: Inadimplência | L25: Reiterado Cobrança (e-mail-whatsapp). | M25: Em 20/07/2026 solicitamos de acordo para negativação porém sem resposta. Tentando contato com cliente porém whatsapp business informa que estão fechados, e não atendem ligação. | N25: MY FARM ERP | O25: No geral, pagamentos em dia. Pulo de parcela. | Q25: 217 | R25: 1678.29 | S25: 0 | T25: =R25+S25 -> 1678.29 | U25: 0 | V25: 46225
B26: 30003885-5 | C26: MARCELO BENEDITO LARA | D26: MY FARM ERP | E26: Sem retorno do cliente (por email) | F26: SUSPENSO | G26: INADIMPLENCIA | H26: 373 | I26: Inadimplente - Sem previsão de pagamento. Em 29/07/2025 enviado solicitação para suspender plataforma. | J26: Escritório AVERBACH | K26: Inadimplência | L26: Verificar de acordo da Vertical | M26: Solicitado bloqueio da plataforma em 24/07/2025. Em 05/08/2025 liberado negativação pela vertical. | N26: MY FARM ERP | O26: Inadimplência recorrente. | Q26: 327 | R26: 2611 | S26: 1865 | T26: =R26+S26 -> 4476 | U26: 5 | V26: 45809
B27: 30001840-5 | C27: MARCIA ANGELICA BARBOZA CORADINI IE 13898617-7 | D27: MY FARM ERP | F27: SUSPENSO | G27: INADIMPLENCIA | H27: 118.46 | I27: Inadimplente - Sem previsão de pagamento. Em 30/06/2026 enviado solicitação para suspender plataforma. | J27: Carteira Cobrança | K27: Inadimplência | L27: Reiterado Cobrança (e-mail-whatsapp). | M27: Em 02/01/2026 solicitamos de acordo para negativação, vertical ficou de tentar contato antes da negativação porém sem retorno, seguimos com a negativação. | N27: MY FARM ERP | O27: Inadimplência recorrente | Q27: 127 | R27: 346.02 | S27: 355.38 | T27: =R27+S27 -> 701.4 | U27: 3 | V27: 46176
B28: 30007418-5 | C28: LUIZ ESPINDULA CARDOSO NETO | D28: MY FARM ERP | E28: Cliente solicitou churn para projetos e sumiu, já tentamos contato diversas vezes, foi repassado que ele precisa solicitar formalmente por email mas ainda não foi enviado o email. | F28: SUSPENSO | G28: INADIMPLENCIA | H28: 1500 | I28: Inadimplente - Enviado cobrança, sem retorno. | M28: O cliente solicitou cancelamento para o time de projetos (ainda estava em implantação), porém após isso deixou de responder tanto projetos, quanto CS, sem abertura para tentativa de reversão e ainda não formalizou o cancelamento. | N28: MY FARM ERP | O28: Primeiras parcelas em atraso. | Q28: 60 | R28: 9000 | S28: 0 | T28: =R28+S28 -> 9000 | U28: 0 | V28: 46261
B29: 30001803-5 | C29: MOACYR BRUNETTA | D29: MY FARM ERP | E29: Pgto realizado via pix dia 24/09. Valor integral | F29: SUSPENSO | G29: INADIMPLENCIA | H29: 1398.65 | N29: MY FARM ERP | O29: Primeiro atraso. | Q29: 37 | R29: 2797.3 | S29: 0 | T29: =R29+S29 -> 2797.3 | U29: 0 | V29: 46261
C30: Anderson Peixoto | D30: MY FARM ERP | E30: Pgto realizado. Cliente da central de cobrança

Sheet Churn
B3: =COUNTA(D5:D32) -> 28 | I3: =SUBTOTAL(9,I5:I32) -> 44028.56
B4: Vertical | C4: Cód. Contrato | D4: Cliente | E4: OBS CS | F4: Produto | G4: Situação | H4: Substatus (Motivo) | I4: Valor (R$) | J4: Categoria da Causa | K4: Resumo da Anotação | L4: Ação de Curadoria
B5: PRODUTORES AGRICOLAS | C5: 30005780-5 | D5: AGRO SANTA CLARA LTDA | F5: AGRIMANAGER ERP | G5: SUSPENSO | H5: RISCO CHURN | I5: 4594.51 | J5: Churn / distrato | K5: CHURN - ASSINATURA DE DISTRATO Cliente solicitou o cancelamento do contrato (e-mail: natanael@7campos.com.br). Estamos aguardando retorno do CS | L5: Em Negociação
B6: PRODUTORES AGRICOLAS | C6: 30006028-5 | D6: LUCIVAL PORTILHO ARANTES IE 29.474.545-9 | E6: Cliente pagou hoje dia 16/09 15mil reais. | F6: AGRIMANAGER ERP | G6: SUSPENSO | H6: RISCO CHURN | I6: 4248.62 | J6: Churn / distrato | K6: CHURN - ASSINATURA DE DISTRATO_x000D_ CLIENTE SOLICITOU O CANCELAMENTO DO CONTRATO | L6: Aguardando Pagamento Multa
B7: PRODUTORES AGRICOLAS | C7: 30001494-1 | D7: PEDRO JOSE BERTUOL | F7: AGRIMANAGER ERP | G7: SUSPENSO | H7: RISCO CHURN | I7: 3927.73 | J7: Churn / distrato | K7: CHURN - ASSINATURA DE DISTRATO_x000D_ CLIENTE SOLICITOU O CANCELAMENTO DO CONTRATO | L7: Aguardando Assinatura Distrato
B8: PRODUTORES AGRICOLAS | C8: 30003130-5 | D8: GEMIRO CARAFINI IE: 11.106.270-5 | F8: AGRIMANAGER ERP | G8: SUSPENSO | H8: RISCO CHURN | I8: 2581.48 | J8: Churn / distrato | K8: CHURN - ASSINATURA DE DISTRATO_x000D_ CLIENTE SOLICITOU CANCELAMENTO DO CONTRATO | L8: Aguardando Pagamento Multa
B9: PRODUTORES AGRICOLAS | C9: 30005811-5 | D9: AUGUSTO CESAR ANDRADE MAIA | F9: MY FARM ERP | G9: SUSPENSO | H9: RISCO CHURN | I9: 2542.4 | J9: Churn / distrato | K9: CHURN - ASSINATURA DE DISTRATO_x000D_ Cliente solicitou o cancelamento do c | L9: Aguardando Pagamento Multa
B10: PRODUTORES AGRICOLAS | C10: 30005366-5 | D10: ALEX ROBERTO DOS SANTOS ARRUDA IE: 13714988-3 | F10: MY FARM ERP | G10: SUSPENSO | H10: RISCO CHURN | I10: 2217.92 | J10: Churn / distrato | K10: CHURN - ASSINATURA DE DISTRATO_x000D_ Cliente solicitou o cancelamento do contrato | L10: Aguardando pagamento de boletos
B11: PRODUTORES AGRICOLAS | C11: 30003665-5 | D11: TIAGO GODOY VILELA E OUTRO IE: 13.527.389-7 | F11: AGRIMANAGER ERP | G11: SUSPENSO | H11: RISCO CHURN | I11: 2144.87 | J11: Churn / distrato | K11: CHURN - ASSINATURA DE DISTRATO_x000D_ CLIENTE SOLICITOU O CANCELAMENTO DO CONTRATO | L11: Aguardando pagamento de boletos
B12: PRODUTORES AGRICOLAS | C12: 30007127-5 | D12: AGRO ALIANCA LTDA | F12: MY FARM ERP | G12: SUSPENSO | H12: RISCO CHURN | I12: 1950 | J12: Churn / distrato | K12: CHURN - ASSINATURA DE DISTRATO_x000D_ CLIENTE SOLICITOU CANCELAMENTO DO CONTRATO | L12: Em Negociação
B13: PRODUTORES AGRICOLAS | C13: 30005213-5 | D13: FERNANDO LUNARDI E OUTROS IE: 13.554.998-1 | F13: AGRIMANAGER ERP | G13: SUSPENSO | H13: RISCO CHURN | I13: 1890.33 | J13: Churn / distrato | K13: CHURN | L13: Aguardando retorno cliente Multa
B14: PRODUTORES AGRICOLAS | C14: 30003425-5 | D14: FABIO GIOVANNI MARTINS CARRAPATEIRA IE: 28.801.052-3 | F14: AGRIMANAGER ERP | G14: SUSPENSO | H14: RISCO CHURN | I14: 1654.4 | J14: Churn / distrato | K14: CHURN - ASSINATURA DE DISTRATO_x000D_ Cliente pagava por resgate. No momento de voltar a pagar pelo sistema, o cliente manifestou o desejo de cancelamento de contrato. Rodrigo Mendonça tratando do cancelamento. Suspenso até conclusão | L14: Aguardando retorno cliente Multa
B15: PRODUTORES AGRICOLAS | C15: 30006243-5 | D15: LUCIVAL PORTILHO ARANTES IE 29.474.545-9 | F15: ALIARE CLOUD - PR | G15: SUSPENSO | H15: RISCO CHURN | I15: 1647.5 | J15: Churn / distrato | K15: CHURN - ASSINATURA DE DISTRATO_x000D_ CLIENTE SOLICITOU CANCELAMENTO DO CONTRATO | L15: Aguardando Pagamento Multa
B16: PRODUTORES AGRICOLAS | C16: 30005737-5 | D16: ORDATA LTDA | F16: MY FARM ERP | G16: SUSPENSO | H16: RISCO CHURN | I16: 1422.9 | J16: Churn / distrato | K16: CHURN | L16: Em Negociação
B17: PRODUTORES AGRICOLAS | C17: 30005572-5 | D17: LEANDRO GAI ANVERSA | F17: ALIARE CLOUD - PR | G17: SUSPENSO | H17: RISCO CHURN | I17: 1201.62 | J17: Churn / distrato | K17: CHURN - ASSINATURA DE DISTRATO Cliente solicitou o cancelamento do contrato. Ticket 795460 | L17: Aguardando pagamento de boletos
B18: PRODUTORES AGRICOLAS | C18: 30005742-5 | D18: GILIARDE RODRIGUES DA SILVA | F18: MY FARM ERP | G18: SUSPENSO | H18: RISCO CHURN | I18: 1200 | J18: Churn / distrato | K18: CHURN | L18: Aguardando retorno cliente Multa
... B32: PRODUTORES AGRICOLAS | C32: 30005162-5 | D32: VINICIUS DA SILVA SOARES | F32: MY FARM ERP | G32: SUSPENSO | H32: INADIMPLENCIA | I32: 422.4 | J32: Churn / distrato | K32: Em processo de cancelamento. | L32: Churn

Sheet Em_Negociacao
B2: =COUNTA(D4:D13) -> 10 | H2: =SUBTOTAL(9,H4:H13) -> 13252.73
B3: Vertical | C3: Cód. Contrato | D3: Cliente | E3: Produto | F3: Situação | G3: Substatus (Motivo) | H3: Valor (R$) | I3: Categoria da Causa | J3: Resumo da Anotação | K3: Ação Vertical
B4: PRODUTORES AGRICOLAS | C4: 30005923-5 | D4: COOPERATIVA AGROPECUARIA PRIMAVERA COAP | E4: MY FARM ERP | F4: SUSPENSO | G4: EM NEGOCIACAO | H4: 5946.19 | I4: Negociação / Retenção | J4: NEGOCIAÇÃO COMERCIAL_x000D_ CONTRATO SUSPENSO POR NEGOCIACAO COMERCIAL, TRATADO NO E-MAI: RENOVAÇÃO ANUAIS MYFARM 08/2026 COM A RAMONA | K4: Negociação e prazo de retomada
B5: PRODUTORES AGRICOLAS | C5: 30005114-5 | D5: LISEU JOSE SCHERER - IE.13.260.772-7 | E5: MY FARM ERP | F5: SUSPENSO | G5: EM NEGOCIACAO | H5: 936.91 | I5: Negociação / Retenção | J5: NEGOCIAÇÃO COMERCIAL_x000D_ CONTRATO SUSPENSO POR NEGOCIACAO COMERCIAL, TRATADO NO E-MAI: RENOVAÇÃO ANUAIS MYFARM 08/2026 COM A RAMONA | K5: Negociação e prazo de retomada
B6: PRODUTORES AGRICOLAS | C6: 30007333-5 | D6: KNAP SOLUCOES CONTABEIS LTDA | E6: MY FARM ERP | F6: SUSPENSO | G6: EM NEGOCIACAO | H6: 705.99 | I6: Negociação / Retenção | J6: NEGOCIAÇÃO DOCUMENTAL - CONTRATOS_x000D_ Esse contrato está sendo analisado pelo Jurídico, juntamente com o Angelo e o Julio. Trata-se do contrato utilizado pelo Jader (BPO) para atendimento de terceiros | K6: Respondido essa semana - Aguardando cliente pagar valores em aberto;
B7: PRODUTORES AGRICOLAS | C7: 30005113-5 | D7: DIEGO MORA MACENA | E7: MY FARM ERP | F7: SUSPENSO | G7: EM NEGOCIACAO | H7: 493.08 | I7: Negociação / Retenção | J7: NEGOCIAÇÃO COMERCIAL_x000D_ CONTRATO SUSPENSO POR NEGOCIACAO COMERCIAL, TRATADO NO E-MAI: RENOVAÇÃO ANUAIS MYFARM 08/2026 COM A RAMONA | K7: Negociação e prazo de retomada
B8: PRODUTORES AGRICOLAS | C8: 30005886-5 | D8: WALDYRENE BARROS SILVA | E8: MY FARM ERP | F8: SUSPENSO | G8: EM NEGOCIACAO | H8: 419.25 | I8: Negociação / Retenção | J8: NEGOCIAÇÃO COMERCIAL Segue informação do Sucesso do Cliente: A cliente informa que não está conseguindo acompanhar a implantação no momento, mas não deseja efetuar o cancelamento. Entrará em um projeto pessoal e momentaneamente precisará parar a implantação do sistema._x | K8: Status correto - Suspenso - Pendencias de Projeto | Atualizar Status
B9: PRODUTORES AGRICOLAS | C9: 30002312-5 | D9: ADRIANA CRISTINA GUIZELINI | E9: MY FARM ERP | F9: SUSPENSO | G9: EM NEGOCIACAO | H9: 408.28 | I9: Negociação / Retenção | J9: NEGOCIAÇÃO COMERCIAL_x000D_ CONTRATO SUSPENSO POR NEGOCIACAO COMERCIAL, TRATADO NO E-MAI: RENOVAÇÃO ANUAIS MYFARM 08/2026 COM A RAMONA | K9: Negociação e prazo de retomada
B10: PRODUTORES AGRICOLAS | C10: 30003798-5 | D10: JOSE WILIAN BAHDUR | E10: MY FARM ERP | F10: SUSPENSO | G10: EM NEGOCIACAO | H10: 312.52 | I10: Negociação / Retenção | J10: NEGOCIAÇÃO COMERCIAL Em troca de e-mails com o comercial myfarm, o cliente não está utilizando o sistema. irão entrar em contato para verificação juntamente ao cliente | K10: Suspensão realizada pelo faturamento, aguardando retorno da negociação comercial
B11: PRODUTORES AGRICOLAS | C11: 30005762-5 | D11: WILLIAM CARDOSO DOS SANTOS | E11: MY FARM ERP | F11: SUSPENSO | G11: RISCO CHURN | H11: 500 | I11: Negociação / Retenção | J11: CHURN - ASSINATURA DE DISTRATO_x000D_ Cliente solicitou o cancelamento do contrato, está sendo tratado no ticket: 724692 (Amanda Cristina) | K11: Aguardando Retorno do CS
B12: PRODUTORES AGRICOLAS | C12: 30004481-5 | D12: AGROPECUARIA ALVORADA LTDA | E12: AGRIMANAGER ERP | F12: SUSPENSO | G12: INADIMPLENCIA | H12: 1859.64 | I12: Negociação / Retenção | J12: Em processo de cancelamento - Aguardando pagamento da entrada do acordo/distrato. Em 23/06/2025 solicitado de acordo da vertical para negativação. | K12: Migração AGM Myfarm | Aguardando pagamento da negociação referente ao distrato
B13: PRODUTORES AGRICOLAS | C13: 30007136-5 | D13: FERNANDO VIEIRA PERES | E13: MY FARM ERP | F13: SUSPENSO | G13: INADIMPLENCIA | H13: 1670.87 | I13: Negociação / Retenção | J13: Em processo de cancelamento. | K13: Acionar cobrança e definir reativar x churn - Inadimplente desde 05/2026 - solicitação de cancelamento 08/2026
