Workbook

Sheet Resumo
B1: Posição da cobrança dos contratos suspensos
B2: Aliare · Operações Produtor Rural
B3: Data da posição | C3: 46290
B5: Receita mensal recuperada em setembro
B6: MRR recuperado (R$ por mês) | C6: =Recuperado!H23 -> 25101.44 | D6: Contratos anuais divididos por 12.
B7: Da carteira de cobrança | C7: =SUMIFS(Recuperado!$H$5:$H$22,Recuperado!$E$5:$E$22,"Carteira de cobrança") -> 21210.26
B8: Extra, fora das planilhas de cobrança | C8: =SUMIFS(Recuperado!$H$5:$H$22,Recuperado!$E$5:$E$22,"Extra") -> 3891.18 | D8: Linhas em roxo na aba Recuperado.
B9: Em 12 meses | C9: =C6*12 -> 301217.28
B10: Contratos reativados | C10: =COUNTIF(Recuperado!$H$5:$H$22,">0") -> 15
B11: Seguem ativos hoje | C11: =COUNTIF(Recuperado!$K$5:$K$22,"Ativo") -> 12
B13: Dívida dos contratos negociados
B14: Dívida cobrada | C14: =Recuperado!L23 -> 113295.07
B15: Recuperado (em caixa mais a receber) | C15: =Recuperado!P23 -> 86807.87 | D15: =IF(C14=0,"",C15/C14) -> 0.76621048
B16: Em caixa | C16: =Recuperado!M23 -> 34053.18
B17: A receber em acordo | C17: =Recuperado!N23 -> 52754.69 | D17: Calendário na aba A receber, até 30/03/2027.
B18: Não recuperado | C18: =Recuperado!O23 -> 26487.2 | D18: Detalhe na aba Não recuperado.
B20: Ainda em cobrança ou em encerramento
B21: Em aberto na carteira interna | C21: ='Em aberto'!G10 -> 153248.8 | D21: =COUNTA('Em aberto'!A5:A9)&" contratos" -> 5 contratos
B22: No escritório de cobrança | C22: =Escritório!G12 -> 57599.67 | D22: =COUNT(Escritório!G5:G11)&" contratos em cobrança e 1 quitado" -> 6 contratos em cobrança e 1 quitado
B23: Churn: receita mensal em cancelamento | C23: =Churn!G39 -> 49937.64 | D23: =Churn!C39&" contratos de "&COUNTA(Churn!A5:A38)&" clientes" -> 35 contratos de 34 clientes
B24: Churn: débitos a acertar no encerramento | C24: =Churn!J39 -> 37249.31
B25: Churn: valor já recebido | C25: =Churn!K39 -> 15000
B26: Negociação comercial: mensalidade suspensa | C26: ='Negociação comercial'!E12 -> 8516.23
B28: Como ler
B29: MRR recuperado: mensalidade que voltou a ser faturada depois da reativação. Contrato anual entra dividido por 12.
B30: Represado: meses não faturados durante a suspensão. Débito faturado: mensalidades faturadas e não pagas.
B31: Extra: contrato recuperado pela central de cobrança que não estava nas planilhas de cobrança do financeiro e do CS.
B32: Cada cliente aparece em uma única aba. Valores em reais.
B33: Fontes: planilha de inadimplência do financeiro, relatório de inadimplentes do CS e recuperação mensal da central de cobrança, posição de 25/09/2026.

Sheet Recuperado
A1: Contratos recuperados em setembro de 2026
A2: Dívida negociada e receita mensal que voltou a ser faturada. Linhas em roxo: recuperados pela central fora das planilhas de cobrança (extra).
A4: Cliente | B4: Contrato | C4: Produto | D4: Situação | E4: Origem | F4: Periodicidade | G4: Valor no cadastro (R$) | H4: MRR recuperado (R$ por mês) | I4: Data da reativação | J4: Dias na central | K4: Situação hoje | L4: Dívida cobrada (R$) | M4: Em caixa (R$) | N4: A receber em acordo (R$) | O4: Não recuperado (R$) | P4: Dívida recuperada (R$) | Q4: Como foi negociado
A5: Luiz Moreira Rocha | B5: 30006200 | C5: myFarm | D5: Acordo em parcelas | E5: Carteira de cobrança | F5: Mensal | G5: 5000 | H5: =IF(G5="","",IF(F5="Anual",ROUND(G5/12,2),G5)) -> 5000 | I5: 46287 | J5: 3 | K5: De volta à central: parcelas do acordo em aberto | L5: 20862.9 | M5: 6258.78 | N5: 14603.82 | O5: 0.3 | P5: =IF(L5="","",M5+N5) -> 20862.6 | Q5: O cliente recebeu proposta de quitação à vista com 15% de desconto e optou pelo parcelamento em três vezes, sem desconto: entrada de R$ 6.258,78, paga e confirmada, e duas parcelas de R$ 7.301,91 em 14/10 e 14/11.
A6: Vitor Marcio Dumoncel e outros | B6: 30005234 | C6: AgriManager | D6: Acordo em parcelas | E6: Carteira de cobrança | F6: Mensal | G6: 4876.6 | H6: =IF(G6="","",IF(F6="Anual",ROUND(G6/12,2),G6)) -> 4876.6 | I6: 46289 | J6: 33 | K6: Ativo | L6: 34629.79 | M6: 10000 | N6: 24629.79 | O6: 0 | P6: =IF(L6="","",M6+N6) -> 34629.79 | Q6: O cliente já tinha um acordo em andamento. As duas parcelas represadas, que ficavam fora dele, foram somadas ao saldo desse acordo e consolidadas em um novo acordo, sem desconto: entrada de R$ 10.000,00, paga e confirmada em 23/09, e três parcelas de R$ 8.209,93 com vencimento em 25/10, 25/11 e 25/12.
A7: Marcos Aurelio Sinopoli | B7: 30002424 | C7: AgriManager | D7: Acordo no Plano Safra | E7: Carteira de cobrança | F7: Mensal | G7: 3529.65 | H7: =IF(G7="","",IF(F7="Anual",ROUND(G7/12,2),G7)) -> 3529.65 | I7: 46287 | J7: 24 | K7: Ativo | L7: 13521.08 | M7: 0 | N7: 13521.08 | O7: 0 | P7: =IF(L7="","",M7+N7) -> 13521.08 | Q7: O débito faturado já estava em acordo e segue sendo cumprido. As quatro parcelas represadas, de junho a setembro, ficavam fora desse acordo. Em 18/09 foi fechado o acordo delas no Plano Safra: o cliente segue pagando as mensalidades e o acordo anterior, e o represado de R$ 13.521,08 vence em 30/03/2027.
A8: Agropecuária Mano Velho Ltda | B8: 30004920 | C8: AgriManager | D8: Reativado | E8: Extra | F8: Mensal | G8: 2230.23 | H8: =IF(G8="","",IF(F8="Anual",ROUND(G8/12,2),G8)) -> 2230.23 | I8: 46269 | J8: 7 | K8: Ativo | P8: =IF(L8="","",M8+N8) | Q8: Entrou na central em 27/08 por estar suspenso. O contato por WhatsApp foi feito no mesmo dia, e o contrato voltou a ativo em 04/09.
A9: Anderson Peixoto Cordeiro | B9: 30003505 | C9: myFarm | D9: Reativado | E9: Carteira de cobrança | F9: Mensal | G9: 1457.26 | H9: =IF(G9="","",IF(F9="Anual",ROUND(G9/12,2),G9)) -> 1457.26 | I9: 46287 | J9: 25 | K9: De volta à central: vencimento em 16/10/2026 | P9: =IF(L9="","",M9+N9) | Q9: Cliente adimplente: segundo o financeiro, o próximo vencimento é só em 16/10/2026. Reativado pela central em 22/09.
A10: Agropecuária Alvorada Ltda | B10: 30007726 | C10: myFarm | D10: Reativado | E10: Carteira de cobrança | F10: Mensal | G10: 1400 | H10: =IF(G10="","",IF(F10="Anual",ROUND(G10/12,2),G10)) -> 1400 | I10: 46269 | J10: 73 | K10: Ativo | P10: =IF(L10="","",M10+N10) | Q10: Cliente migrou do AgriManager para o myFarm e estava em período de teste desde julho. O pagamento foi tratado direto com o financeiro, e o contrato myFarm voltou a ativo em 04/09. O contrato AgriManager anterior, 30004481, segue em distrato.
A11: Moacyr Brunetta | B11: 30001803 | C11: myFarm | D11: Quitado | E11: Carteira de cobrança | F11: Mensal | G11: 1398.65 | H11: =IF(G11="","",IF(F11="Anual",ROUND(G11/12,2),G11)) -> 1398.65 | I11: 46289 | J11: 26 | K11: De volta à central desde 25/09/2026 | L11: 2797.3 | M11: 2797.3 | N11: 0 | O11: 0 | P11: =IF(L11="","",M11+N11) -> 2797.3 | Q11: Pagamento integral do débito via pix em 24/09, sem desconto.
A12: Pablo Rafael Scnheider | B12: 30006069 | C12: AgriManager | D12: Quitado | E12: Carteira de cobrança | F12: Mensal | G12: 1200 | H12: =IF(G12="","",IF(F12="Anual",ROUND(G12/12,2),G12)) -> 1200 | I12: 46283 | J12: 22 | K12: Ativo | L12: 2400 | M12: 2400 | N12: 0 | O12: 0 | P12: =IF(L12="","",M12+N12) -> 2400 | Q12: O cliente havia combinado cobrança semestral, mas a assinatura foi faturada mensalmente, o que gerou o atraso. Pagou o débito integral, e o ajuste da cobrança para semestral está em andamento.
A13: Sandro Sia e Outros | B13: 30007323 | C13: myFarm | D13: Reativado | E13: Extra | F13: Mensal | G13: 847.18 | H13: =IF(G13="","",IF(F13="Anual",ROUND(G13/12,2),G13)) -> 847.18 | I13: 46269 | J13: 23 | K13: Ativo | P13: =IF(L13="","",M13+N13) | Q13: Cliente em implantação que não estava recebendo os boletos; o time de projetos já acompanhava o caso. Entrou na central em 11/08 e voltou a ativo em 04/09.
A14: Knap Soluções Contábeis Ltda | B14: 30007333 | C14: myFarm | D14: Reativado | E14: Carteira de cobrança | F14: Mensal | G14: 705.99 | H14: =IF(G14="","",IF(F14="Anual",ROUND(G14/12,2),G14)) -> 705.99 | I14: 46280 | J14: 34 | K14: Ativo | P14: =IF(L14="","",M14+N14) | Q14: Contrato em análise contratual. A coordenação de operações fez a cobrança por WhatsApp em 28/08, e o cliente foi reativado pela central em 15/09.
A15: Neimar Walker | B15: 30002492 | C15: myFarm | D15: Reativado | E15: Extra | F15: Anual | G15: 8000 | H15: =IF(G15="","",IF(F15="Anual",ROUND(G15/12,2),G15)) -> 666.67 | I15: 46269 | J15: 23 | K15: Ativo | P15: =IF(L15="","",M15+N15) | Q15: Contrato anual de R$ 8.000,00, suspenso no momento da renovação. Entrou na central em 11/08, recebeu contato do comercial para renovar e voltou a ativo em 04/09.
A16: Juarez Carlos Silva Filho | B16: 30006056 | C16: myFarm | D16: Quitado | E16: Carteira de cobrança | F16: Mensal | G16: 650 | H16: =IF(G16="","",IF(F16="Anual",ROUND(G16/12,2),G16)) -> 650 | I16: 46283 | J16: 22 | K16: Ativo | L16: 2600 | M16: 2600 | N16: 0 | O16: 0 | P16: =IF(L16="","",M16+N16) -> 2600 | Q16: Pagamento integral do débito via pix em 14/09, sem desconto.
A17: Ana Paula Bandeira de Lima | B17: 30007162 | C17: myFarm | D17: Quitado | E17: Carteira de cobrança | F17: Mensal | G17: 565 | H17: =IF(G17="","",IF(F17="Anual",ROUND(G17/12,2),G17)) -> 565 | I17: 46276 | J17: 15 | K17: Ativo | L17: 2531.68 | M17: 2531.68 | N17: 0 | O17: 0 | P17: =IF(L17="","",M17+N17) -> 2531.68 | Q17: Pagamento integral do débito via pix, sem desconto.
A18: João Everton Paulino Ramos Alves | B18: 30004027 | C18: myFarm | D18: Quitado com desconto | E18: Carteira de cobrança | F18: Mensal | G18: 427.11 | H18: =IF(G18="","",IF(F18="Anual",ROUND(G18/12,2),G18)) -> 427.11 | I18: 46283 | J18: 22 | K18: Ativo | L18: 1381.31 | M18: 1174.11 | N18: 0 | O18: 207.2 | P18: =IF(L18="","",M18+N18) -> 1174.11 | Q18: O cliente aceitou a proposta de 15% de desconto para pagamento à vista e quitou R$ 1.174,11.
A19: Bruno Marques Guidi | B19: 30004903 | C19: myFarm | D19: Reativado | E19: Extra | F19: Anual | G19: 1765.17 | H19: =IF(G19="","",IF(F19="Anual",ROUND(G19/12,2),G19)) -> 147.1 | I19: 46269 | J19: 6 | K19: Ativo | P19: =IF(L19="","",M19+N19) | Q19: Contrato anual de R$ 1.765,17. Entrou na central em 28/08 e voltou a ativo em 04/09, sem necessidade de contato.
A20: Tellus Agropecuaria Ltda | B20: 30003178 | C20: AgriManager | D20: Pagou o faturado e cancelou | E20: Carteira de cobrança | H20: =IF(G20="","",IF(F20="Anual",ROUND(G20/12,2),G20)) | K20: Contrato cancelado | L20: 24097.17 | M20: 2067.47 | N20: 0 | O20: 22029.7 | P20: =IF(L20="","",M20+N20) -> 2067.47 | Q20: O cliente pagou o débito faturado de R$ 2.067,47 e não aceitou negociar as dez parcelas represadas. Solicitou o cancelamento do contrato, e as notas referentes ao período represado estão em processo de cancelamento.
A21: Theodoro Ricardo de Andrade | B21: 30005717 | C21: myFarm | D21: Pagou o faturado e cancelou | E21: Carteira de cobrança | H21: =IF(G21="","",IF(F21="Anual",ROUND(G21/12,2),G21)) | K21: Contrato cancelado | L21: 5950 | M21: 1700 | N21: 0 | O21: 4250 | P21: =IF(L21="","",M21+N21) -> 1700 | Q21: O cliente pagou integralmente o débito faturado em 16/09. Mesmo com condições especiais para o valor represado, alinhadas com o financeiro, não aceitou negociar a cobrança referente ao período em que esteve com o acesso bloqueado. Formalizou o cancelamento e informou que pretende tratar o valor restante judicialmente.
A22: Paulo Massayoshi Mizote | B22: 30000710 | C22: AgriManager | D22: Quitado | E22: Carteira de cobrança | H22: =IF(G22="","",IF(F22="Anual",ROUND(G22/12,2),G22)) | K22: Não consta na central | L22: 2523.84 | M22: 2523.84 | N22: 0 | O22: 0 | P22: =IF(L22="","",M22+N22) -> 2523.84 | Q22: Pagamento total do débito, correspondente a duas mensalidades, sem desconto.
A23: Total | H23: =SUBTOTAL(9,H5:H22) -> 25101.44 | L23: =SUBTOTAL(9,L5:L22) -> 113295.07 | M23: =SUBTOTAL(9,M5:M22) -> 34053.18 | N23: =SUBTOTAL(9,N5:N22) -> 52754.69 | O23: =SUBTOTAL(9,O5:O22) -> 26487.2 | P23: =SUBTOTAL(9,P5:P22) -> 86807.87

Sheet A receber
A1: Calendário do valor a receber em acordo
A2: Parcelas dos acordos fechados, por data de vencimento.
A4: Vencimento | B4: Cliente | C4: Contrato | D4: Parcela | E4: Valor (R$) | F4: Modalidade | G4: Observação
A5: 46309 | B5: Luiz Moreira Rocha | C5: 30006200 | D5: Parcela 1 de 2 | E5: 7301.91 | F5: Parcelamento | G5: Entrada de R$ 6.258,78 paga.
A6: 46320 | B6: Vitor Marcio Dumoncel e outros | C6: 30005234 | D6: Parcela 1 de 3 | E6: 8209.93 | F6: Parcelamento | G6: Entrada de R$ 10.000,00 paga em 23/09/2026.
A7: 46340 | B7: Luiz Moreira Rocha | C7: 30006200 | D7: Parcela 2 de 2 | E7: 7301.91 | F7: Parcelamento | G7: Entrada de R$ 6.258,78 paga.
A8: 46351 | B8: Vitor Marcio Dumoncel e outros | C8: 30005234 | D8: Parcela 2 de 3 | E8: 8209.93 | F8: Parcelamento | G8: Entrada de R$ 10.000,00 paga em 23/09/2026.
A9: 46381 | B9: Vitor Marcio Dumoncel e outros | C9: 30005234 | D9: Parcela 3 de 3 | E9: 8209.93 | F9: Parcelamento | G9: Entrada de R$ 10.000,00 paga em 23/09/2026.
A10: 46476 | B10: Marcos Aurelio Sinopoli | C10: 30002424 | D10: Represado no Plano Safra | E10: 13521.08 | F10: Plano Safra | G10: O cliente segue pagando as mensalidades e o acordo anterior.
A11: Total a receber | E11: =SUBTOTAL(9,E5:E10) -> 52754.69

Sheet Não recuperado
A1: Valores que não voltam nos contratos negociados
A2: Parte da dívida cobrada que ficou de fora do pagamento ou do acordo.
A4: Cliente | B4: Contrato | C4: Produto | D4: Motivo | E4: Valor (R$) | F4: Observação
A5: Tellus Agropecuaria Ltda | B5: 30003178 | C5: AgriManager | D5: Represado baixado com o cancelamento | E5: 22029.7 | F5: Pagou o faturado de R$ 2.067,47 e pediu cancelamento. As notas das dez parcelas represadas estão em cancelamento.
A6: Theodoro Ricardo de Andrade | B6: 30005717 | C6: myFarm | D6: Represado recusado pelo cliente | E6: 4250 | F6: Pagou o faturado de R$ 1.700,00 em 16/09/2026, recusou as cinco parcelas represadas e formalizou o cancelamento. Informou que vai discutir o valor na Justiça.
A7: João Everton Paulino Ramos Alves | B7: 30004027 | C7: myFarm | D7: Desconto de 15% à vista | E7: 207.2 | F7: Quitou R$ 1.174,11 à vista sobre o débito de R$ 1.381,31.
A8: Luiz Moreira Rocha | B8: 30006200 | C8: myFarm | D8: Arredondamento do acordo | E8: 0.3 | F8: Acordo de R$ 20.862,60 sobre o débito de R$ 20.862,90.
A9: Total não recuperado | E9: =SUBTOTAL(9,E5:E8) -> 26487.2

Sheet Em aberto
A1: Inadimplência em aberto na carteira interna
A2: Contratos sem acordo em 25/09/2026. Quase toda a dívida é represada.
A4: Cliente | B4: Contrato | C4: Produto | D4: Mensalidade (R$) | E4: Débito faturado (R$) | F4: Valor represado (R$) | G4: Dívida total (R$) | H4: Dívida com juros, planilha do CS (R$) | I4: Situação | J4: Plano Safra | K4: Observação | L4: Próximo passo
A5: Petras de Lima Telles | B5: 30002744 | C5: AgriManager | D5: 4467.33 | E5: 0 | F5: 58075.29 | G5: =E5+F5 -> 58075.29 | H5: 58088.29 | I5: Sem retorno do cliente | J5: Candidato | K5: Parcelas faturadas já regularizadas com o escritório de cobrança. Restam 13 parcelas represadas desde 09/2025, R$ 58.075,29, com 366 dias de atraso, e o cliente parou de responder. Risco alto: R$ 61,88 milhões em anotações negativas e 8 ações judiciais; não negativado. | L5: Área de negócio retomar contato para negociar o represado, conforme pedido de 31/08/2026. Financeiro recomenda não propor flexibilização 2027.
A6: Alzir Pimentel Aguiar Neto | B6: 30003232 | C6: AgriManager | D6: 8758.44 | E6: 0 | F6: 43792.2 | G6: =E6+F6 -> 43792.2 | H6: 43792.2 | I6: Reunião marcada em 25/09 | J6: Candidato | K6: Cumpre acordo antigo de 10 parcelas, mas 5 mensalidades represadas de 05/2026 a 09/2026, R$ 43.792,20, ficaram fora do acordo. Atraso de 219 dias, suspenso desde 30/03/2026. Risco alto: R$ 54,06 milhões em anotações negativas e histórico de renegociações não cumpridas. | L6: Registrar o resultado da reunião de 25/09 às 15h e fechar proposta para o represado sem flexibilização para 2027, conforme recomendação do financeiro.
A7: Pedro Henrique Pinto Fadel | B7: 30003903 | C7: AgriManager | D7: 3098.61 | E7: 0 | F7: 35736.48 | G7: =E7+F7 -> 35736.48 | H7: 35736.48 | I7: Proposta em análise | J7: Proposta enviada, em análise | K7: Dívida de R$ 35.736,48 em 8 parcelas represadas desde 02/2026, 194 dias de atraso, sem negativação; o cliente alega dificuldade financeira e contesta o valor, pois já havia pedido redução da mensalidade, e reduziu licenças em julho. Proposta em análise pelo cliente: 5 parcelas de R$ 3.573,64 até fevereiro e saldo de R$ 17.868,28 em 30/03/2027. Risco alto: R$ 89,29 milhões em anotações negativas e 8 execuções judiciais. | L7: Obter a resposta do cliente à proposta e alinhar com o financeiro, que recomenda não flexibilizar para 2027, antes de fechar o acordo.
A8: Joao Batista Consentini Filho | B8: 30001698 | C8: AgriManager | D8: 4204.55 | E8: 0 | F8: 10688.86 | G8: =E8+F8 -> 10688.86 | H8: 11020.56 | I8: Represado fora do acordo | K8: Acordo de renegociação em cumprimento, com reativação prevista só após quitação total. As parcelas de 08/2026 e 09/2026, R$ 10.688,86, estão represadas fora do acordo. Cliente recorrente em renegociações não cumpridas, risco alto: 17 ações judiciais e R$ 389,33 milhões em anotações negativas. | L8: Cobrança negociar a inclusão dos R$ 10.688,86 represados, retorno pedido pela área de negócio em 09/07/2026. Financeiro recomenda não propor flexibilização 2027.
A9: Nova Fronteira Agropecuária Ltda | B9: 30003342 | C9: AgriManager | D9: 1784.94 | E9: 4955.97 | F9: 0 | G9: =E9+F9 -> 4955.97 | H9: 4955.97 | I9: Sem retorno do cliente | J9: Indicado pelo financeiro, entrada de 20% | K9: Dívida de R$ 4.955,97 em mensalidades faturadas, 44 dias de atraso, suspenso desde 25/08/2026. Cobrança reiterada por email e mensagem, sem retorno. Em 02/07/2026 a cobrança pediu aval para negativação; inadimplência recorrente. | L9: Decidir a negativação pedida em 02/07/2026 e oferecer flexibilização para 2027 com entrada de 20%, R$ 991,19, conforme recomendação do financeiro.
A10: Total | D10: =SUBTOTAL(9,D5:D9) -> 22313.87 | E10: =SUBTOTAL(9,E5:E9) -> 4955.97 | F10: =SUBTOTAL(9,F5:F9) -> 148292.83 | G10: =SUBTOTAL(9,G5:G9) -> 153248.8 | H10: =SUBTOTAL(9,H5:H9) -> 153593.5

Sheet Escritório
A1: Dívidas no escritório de cobrança terceirizado
A2: Todos myFarm; nenhum pediu cancelamento. Confirmado: as duas planilhas registram o escritório. A confirmar: a planilha do CS indica o escritório e a do financeiro ainda registra a carteira interna.
A4: Cliente | B4: Contrato | C4: Produto | D4: Situação no escritório | E4: Débito faturado (R$) | F4: Valor represado (R$) | G4: Dívida total (R$) | H4: Dívida com juros, planilha do CS (R$) | I4: Observação | J4: Próximo passo
A5: Fyllipe Carvalho Freitas Barros | B5: 30006051 | C5: myFarm | D5: Confirmado nas duas planilhas | E5: 9610 | F5: 6317.5 | G5: =IF(AND(E5="",F5=""),"",E5+F5) -> 15927.5 | H5: 15927.5 | I5: Dívida de R$ 15.927,50 entregue ao escritório de cobrança terceirizado: R$ 9.610,00 faturados e R$ 6.317,50 represados em 7 parcelas. Nenhuma parcela paga, 278 dias de atraso, plataforma suspensa em 28/01/2026 e negativação liberada em 17/02/2026. Cliente sem retorno nas tentativas de contato. | J5: Cobrança validar com o escritório a situação do caso e se existe acordo em andamento, conforme anotação do financeiro.
A6: Silvano Roger da Silva | B6: 30005936 | C6: myFarm | D6: Confirmado nas duas planilhas | E6: 9000 | F6: 6000 | G6: =IF(AND(E6="",F6=""),"",E6+F6) -> 15000 | H6: 15000 | I6: Dívida de R$ 15.000,00 (R$ 9.000,00 faturado e R$ 6.000,00 represado em 8 parcelas), com 333 dias de atraso. Cliente sem retorno após 3 contatos; bloqueio da plataforma solicitado em 26/12/2025. Dívida entregue ao escritório de cobrança. | J6: Financeiro validar com o escritório o andamento da cobrança e trazer posição atualizada.
A7: José Rosa dos Santos | B7: 30005102 | C7: myFarm | D7: Confirmado nas duas planilhas | E7: 6780.76 | F7: 565.1 | G7: =IF(AND(E7="",F7=""),"",E7+F7) -> 7345.86 | H7: 7345.86 | I7: Dívida de R$ 7.345,86 com 357 dias de atraso, entregue ao escritório de cobrança terceirizado. Suspenso desde 01/10/2025, sem previsão de pagamento e com histórico de inadimplência recorrente. Em 15/01/2026 foi pedido aval para negativação. | J7: Validar com o escritório a situação da cobrança e obter o aval da vertical para negativação.
A8: Christopher Terrengui | B8: 30005824 | C8: myFarm | D8: A confirmar com o financeiro | E8: 14877.45 | F8: 1781.06 | G8: =IF(AND(E8="",F8=""),"",E8+F8) -> 16658.51 | H8: 16777.85 | I8: Dívida de R$ 16.658,51 sem juros (R$ 14.877,45 faturado e R$ 1.781,06 represado), com 406 dias de atraso. Cliente questionou os valores, recebeu planilha detalhada e parou de responder. CS indica envio ao escritório de cobrança. | J8: Financeiro confirmar se a dívida já está com o escritório e resolver a pendência de projeto que impede a negativação.
A9: Henrique Reges de Carvalho | B9: 30003568 | C9: myFarm | D9: A confirmar com o financeiro | E9: 1474.8 | F9: 491.6 | G9: =IF(AND(E9="",F9=""),"",E9+F9) -> 1966.4 | H9: 2458 | I9: Dívida de R$ 1.966,40 (R$ 1.474,80 faturado e R$ 491,60 represado), R$ 2.458,00 com juros, 96 dias de atraso. Sem retorno do cliente; bloqueio da plataforma pedido em 10/08/2026. CS informa que o débito está com o escritório de cobrança terceirizado. | J9: Confirmar com o financeiro se o débito foi entregue ao escritório terceirizado e atualizar o estágio na planilha.
A10: Marcia Angelica Barboza Coradini | B10: 30001840 | C10: myFarm | D10: A confirmar com o financeiro | E10: 346.02 | F10: 355.38 | G10: =IF(AND(E10="",F10=""),"",E10+F10) -> 701.4 | H10: 701.4 | I10: Inadimplência recorrente, 127 dias de atraso e sem previsão de pagamento. Negativação feita após o cliente não retornar ao contato; suspensão da plataforma pedida em 30/06/2026. Dívida de R$ 701,40, sendo R$ 346,02 faturados e R$ 355,38 represados. | J10: Financeiro confirmar se a dívida foi entregue ao escritório de cobrança e atualizar o estágio na planilha.
A11: Marcelo Benedito Lara | B11: 30003885 | C11: myFarm | D11: Quitado pelo escritório | G11: =IF(AND(E11="",F11=""),"",E11+F11) | I11: Dívida registrada de R$ 4476,00 quitada integralmente; valor pago não informado. CS informa que os débitos foram quitados integralmente (linha marcada como paga). A dívida registrada no financeiro era de R$ 4.476,00, com 327 dias de atraso e suspensão desde 01/06/2025. Próxima etapa é a renovação. | J11: Financeiro confirmar a baixa do pagamento, retirar do escritório terceirizado e baixar a negativação, se houver; CS conduzir a renovação para reativar o contrato.
A12: Total em cobrança no escritório | E12: =SUBTOTAL(9,E5:E11) -> 42089.03 | F12: =SUBTOTAL(9,F5:F11) -> 15510.64 | G12: =SUBTOTAL(9,G5:G11) -> 57599.67 | H12: =SUBTOTAL(9,H5:H11) -> 58210.61

Sheet Churn
A1: Contratos em churn: cancelamento pedido ou em distrato
A2: Cada cliente em uma linha. Tellus e Theodoro, que pagaram o faturado antes de cancelar, estão na aba Recuperado.
A4: Cliente | B4: Contrato | C4: Nº de contratos | D4: Produto | E4: Etapa do encerramento | F4: Situação | G4: Receita mensal (R$) | H4: Pedido de cancelamento | I4: Dias desde o pedido | J4: Débito a acertar (R$) | K4: Valor recebido (R$) | L4: Observação | M4: Próximo passo
A5: Lucival Portilho Arantes | B5: 30006028 e 30006243 | C5: 2 | D5: AgriManager e Aliare Cloud | E5: Pagamento ou acordo feito | F5: Pago, aguardando distrato | G5: 5896.12 | H5: 46165 | I5: =IF(ISNUMBER(H5),Resumo!$C$3-H5,"") -> 125 | K5: 15000 | L5: Dois contratos: AgriManager, com mensalidade de R$ 4.248,62, e Aliare Cloud, com R$ 1.647,50. O cliente pediu cancelamento por email em 23/05/2026 e pagou R$ 15.000,00 em 16/09/2026 referentes aos débitos. O distrato do AgriManager aguarda emissão, e o do Aliare Cloud aguarda o pagamento da multa. | M5: Financeiro confirmar se o pagamento quitou débitos e multas dos dois contratos; contratos emitir os dois distratos.
A6: Agro Santa Clara Ltda | B6: 30005780 | C6: 1 | D6: AgriManager | E6: Multa em discussão com o cliente | F6: Aguardando retorno de contratos | G6: 4594.51 | H6: 46195 | I6: =IF(ISNUMBER(H6),Resumo!$C$3-H6,"") -> 95 | L6: Cliente pediu cancelamento por email em 22/06/2026, alegando descumprimento do acordo pela empresa, e pede isenção da multa. Mensalidade de R$ 4.594,51. | M6: Contratos decidir sobre o pedido de isenção da multa; CS formalizar o distrato com o cliente e dar retorno ao financeiro.
A7: Pedro Jose Bertuol | B7: 30001494 | C7: 1 | D7: AgriManager | E7: Distrato em assinatura | F7: Aguardando assinatura do distrato | G7: 3927.73 | H7: 46113 | I7: =IF(ISNUMBER(H7),Resumo!$C$3-H7,"") -> 177 | L7: Cliente pediu cancelamento por email em 01/04/2026, há quase seis meses. O CS parou na etapa de retenção e o financeiro registra o contrato aguardando assinatura do distrato. Receita mensal perdida de R$ 3.927,73. | M7: CS encerrar a tentativa de retenção e contratos colher a assinatura do distrato.
A8: Gemiro Carafini | B8: 30003130 | C8: 1 | D8: AgriManager | E8: Aguardando pagamento da multa | F8: Aguardando pagamento da multa | G8: 2581.48 | I8: =IF(ISNUMBER(H8),Resumo!$C$3-H8,"") | L8: Cliente pediu cancelamento e o distrato aguarda o pagamento da multa de cancelamento. Mensalidade de R$ 2.581,48. | M8: Financeiro cobrar a multa de cancelamento para concluir o distrato.
A9: Augusto Cesar Andrade Maia | B9: 30005811 | C9: 1 | D9: myFarm | E9: Aguardando pagamento da multa | F9: Aguardando pagamento da multa | G9: 2542.4 | H9: 46120 | I9: =IF(ISNUMBER(H9),Resumo!$C$3-H9,"") -> 170 | J9: 12712 | L9: Cliente pediu cancelamento por email em 08/04/2026, citando falhas e inconsistências recorrentes no sistema. Débito de R$ 12.712,00 com juros. Distrato aguarda pagamento da multa. | M9: Cobrança acompanhar o pagamento da multa e do débito para liberar o distrato.
A10: Alex Roberto dos Santos Arruda | B10: 30005366 | C10: 1 | D10: myFarm | E10: Aguardando pagamento de boletos | F10: Aguardando pagamento dos boletos | G10: 2217.92 | I10: =IF(ISNUMBER(H10),Resumo!$C$3-H10,"") | L10: Cliente pediu o cancelamento e o distrato está em assinatura. Pendente o pagamento dos boletos em aberto. Mensalidade perdida de R$ 2.217,92. | M10: Cobrar os boletos em aberto e concluir o distrato para baixa do contrato.
A11: Tiago Godoy Vilela e Outro | B11: 30003665 | C11: 1 | D11: AgriManager | E11: Aguardando pagamento de boletos | F11: Aguardando pagamento de boletos | G11: 2144.87 | I11: =IF(ISNUMBER(H11),Resumo!$C$3-H11,"") | L11: Cliente pediu o cancelamento do contrato; distrato em andamento. Aguarda pagamento de boletos em aberto para concluir. Mensalidade perdida de R$ 2.144,87; data do pedido e valor dos boletos não informados. | M11: Acompanhar o pagamento dos boletos e, com a quitação, colher a assinatura do distrato.
A12: Agro Alianca Ltda | B12: 30007127 | C12: 1 | D12: myFarm | E12: Aguardando retorno de contratos | F12: Aguardando retorno de contratos | G12: 1950 | H12: 46170 | I12: =IF(ISNUMBER(H12),Resumo!$C$3-H12,"") -> 120 | L12: Cliente pediu cancelamento por email, alegando inconsistências e falhas recorrentes no sistema. Distrato em assinatura, aguardando retorno de contratos. Mensalidade de R$ 1.950,00. | M12: Contratos dar retorno ao cliente sobre o distrato; comercial avaliar se a negociação registrada pelo financeiro ainda permite reversão.
A13: Fernando Lunardi e Outros | B13: 30005213 | C13: 1 | D13: AgriManager | E13: Multa em discussão com o cliente | F13: Cliente recusa pagar multa | G13: 1890.33 | H13: 45940 | I13: =IF(ISNUMBER(H13),Resumo!$C$3-H13,"") -> 350 | L13: Cliente pediu o cancelamento e reforçou o pedido várias vezes. Contrato segue suspenso porque o cliente se recusa a pagar a multa contratual. Mensalidade perdida de R$ 1.890,33. | M13: Definir se a multa será flexibilizada para fechar o distrato ou cobrada por via formal.
A14: Fernando Vieira Peres | B14: 30007136 | C14: 1 | D14: myFarm | E14: Aguardando retorno de contratos | F14: Aguardando retorno de contratos | G14: 1670.87 | H14: 46248 | I14: =IF(ISNUMBER(H14),Resumo!$C$3-H14,"") -> 42 | L14: Cliente pediu cancelamento por email em 14/08/2026, ainda em implantação; a tentativa de reversão não teve sucesso. Ordens de serviço e saldo restante foram enviados a contratos, sem retorno até agora. Inadimplente desde maio de 2026, sem valor de dívida nas planilhas; mensalidade perdida de R$ 1.670,87. | M14: Contratos retornar com o cálculo do saldo e das ordens de serviço; financeiro e CS fechar a decisão entre reativar e encerrar e acionar a cobrança.
A15: Fabio Giovanni Martins Carrapateira | B15: 30003425 | C15: 1 | D15: AgriManager | E15: Multa em discussão com o cliente | F15: Aguardando retorno sobre multa | G15: 1654.4 | H15: 45992 | I15: =IF(ISNUMBER(H15),Resumo!$C$3-H15,"") -> 298 | L15: Cliente encerrou as atividades e pediu cancelamento em 12/2025, sem renovar a assinatura. Pagava por resgate e, ao voltar a pagar pelo sistema, optou por sair. Distrato em andamento, aguardando retorno do cliente sobre a multa; mensalidade perdida de R$ 1.654,40. | M15: Cobrar retorno do cliente sobre a multa rescisória e colher a assinatura do distrato.
A16: Jose Dias de Melo Neto | B16: 30002284 | C16: 1 | D16: AgriManager | E16: Distrato em assinatura | F16: Distrato em andamento | G16: 1597.39 | I16: =IF(ISNUMBER(H16),Resumo!$C$3-H16,"") | L16: Contrato em processo de cancelamento, com distrato em andamento no financeiro. Receita mensal perdida de R$ 1.597,39. Sem data do pedido registrada. | M16: Contratos concluir o distrato e CS registrar data e motivo do pedido.
A17: Falcon Agricola Ltda | B17: 30006062 | C17: 1 | D17: myFarm | E17: Aguardando retorno de contratos | F17: Aguardando retorno de contratos | G17: 1580 | H17: 46280 | I17: =IF(ISNUMBER(H17),Resumo!$C$3-H17,"") -> 10 | J17: 13859.02 | L17: Cliente pediu cancelamento por email em 15/09/2026, alegando que não usa o sistema há muito tempo, e pediu revisão dos débitos. Dívida de R$ 13.859,02 na carteira interna: R$ 5.959,02 faturados e R$ 7.900,00 represados em 5 parcelas, 125 dias de atraso. Suspenso desde 13/03/2026, negativação liberada em 19/03/2026, histórico de inadimplência recorrente. | M17: Contratos retornar sobre o distrato e a revisão dos débitos pedida pelo cliente; cobrança definir o valor final a cobrar no encerramento.
A18: Luiz Espindula Cardoso Neto | B18: 30007418 | C18: 1 | D18: myFarm | E18: Aguardando retorno de contratos | F18: Aguardando retorno de contratos | G18: 1500 | H18: 46287 | I18: =IF(ISNUMBER(H18),Resumo!$C$3-H18,"") -> 3 | J18: 9000 | L18: Cliente pediu cancelamento ao time de projetos ainda em implantação e deixou de responder; formalizou por email em 22/09/2026, alegando dificuldade de uso, erros e limitações do sistema. Dívida de R$ 9.000,00 em mensalidades faturadas, sem represado, 60 dias de atraso nas primeiras parcelas. Suspenso desde 27/08/2026. | M18: Contratos responder ao pedido formal e fechar o distrato; cobrança incluir os R$ 9.000,00 faturados no acerto do encerramento.
A19: Ordata Ltda | B19: 30005737 | C19: 1 | D19: myFarm | E19: Distrato em assinatura | F19: Distrato em negociação | G19: 1422.9 | I19: =IF(ISNUMBER(H19),Resumo!$C$3-H19,"") | L19: Contrato em cancelamento nas duas planilhas, com distrato em negociação. Mensalidade perdida de R$ 1.422,90. Sem data do pedido e sem débito registrado. | M19: CS registrar data e motivo do pedido e concluir a negociação do distrato.
A20: Ivan Alves Silva | B20: 30004447 | C20: 1 | D20: myFarm | E20: Aguardando pagamento da multa | F20: Aguardando pagamento da multa | G20: 1202.27 | H20: 46174 | I20: =IF(ISNUMBER(H20),Resumo!$C$3-H20,"") -> 116 | L20: Inadimplente desde 12/2025, pediu cancelamento em 06/2026 e não pagou a multa. Distrato parado à espera do pagamento. Mensalidade de R$ 1.202,27. | M20: Definir com o financeiro o valor da multa e dos débitos desde 12/2025 e cobrar para concluir o distrato; sem pagamento, avaliar envio ao escritório de cobrança.
A21: Leandro Gai Anversa | B21: 30005572 | C21: 1 | D21: Aliare Cloud | E21: Aguardando pagamento de boletos | F21: Aguardando pagamento dos boletos | G21: 1201.62 | I21: =IF(ISNUMBER(H21),Resumo!$C$3-H21,"") | L21: Cliente pediu o cancelamento pelo chamado 795460 e o distrato está em assinatura. Pendente o pagamento dos boletos em aberto. Mensalidade de R$ 1.201,62. | M21: Cobrar os boletos em aberto e concluir o distrato.
A22: Giliarde Rodrigues da Silva | B22: 30005742 | C22: 1 | D22: myFarm | E22: Multa em discussão com o cliente | F22: Aguardando retorno sobre multa | G22: 1200 | I22: =IF(ISNUMBER(H22),Resumo!$C$3-H22,"") | L22: Cliente pediu cancelamento; o financeiro aguarda retorno do cliente sobre a multa rescisória. Mensalidade perdida de R$ 1.200,00. Sem data do pedido registrada. | M22: CS cobrar retorno do cliente sobre a multa e fechar o distrato.
A23: Beatriz Costa Franco | B23: 30005913 | C23: 1 | D23: myFarm | E23: Pagamento ou acordo feito | F23: Acordo de débito em cobrança | G23: 950 | I23: =IF(ISNUMBER(H23),Resumo!$C$3-H23,"") | L23: Cliente em processo de cancelamento. Débito negociado em 2 parcelas de R$ 1.000,00 e repassado ao contas a receber. Mensalidade de R$ 950,00. | M23: Contas a receber acompanhar o pagamento das 2 parcelas; contratos emitir o distrato após a quitação.
A24: Almir Dal Rovere | B24: 30004420 | C24: 1 | D24: myFarm | E24: Sem etapa registrada | F24: Encerramento por não renovação | G24: 924.66 | I24: =IF(ISNUMBER(H24),Resumo!$C$3-H24,"") | L24: Após pesquisa, o cliente decidiu não renovar o contrato e o faturamento suspendeu. Mensalidade perdida de R$ 924,66. Sem data do pedido e sem débito informado. | M24: Formalizar o encerramento por não renovação e atualizar o substatus no sistema para cancelamento.
A25: Volmir Antonio Faveiro | B25: 30005970 | C25: 1 | D25: myFarm | E25: Aguardando pagamento de boletos | F25: Aguardando pagamento de boletos | G25: 896 | I25: =IF(ISNUMBER(H25),Resumo!$C$3-H25,"") | L25: Cliente pediu cancelamento; distrato em fase de assinatura. Encerramento depende do pagamento dos boletos em aberto. Mensalidade de R$ 896,00. | M25: Cobrança acompanhar o pagamento dos boletos; contratos concluir o distrato.
A26: Eldon Ricardo Beckmamm | B26: 30005679 | C26: 1 | D26: myFarm | E26: Multa em discussão com o cliente | F26: Aguardando retorno sobre multa | G26: 780.82 | I26: =IF(ISNUMBER(H26),Resumo!$C$3-H26,"") | L26: Cliente pediu o cancelamento e o distrato está em assinatura. Aguardando retorno do cliente sobre o pagamento da multa contratual. Mensalidade perdida de R$ 780,82. | M26: Cobrar retorno do cliente sobre a multa e fechar o distrato.
A27: Luciano Jayme Guimaraes | B27: 30003080 | C27: 1 | D27: myFarm | E27: Distrato em assinatura | F27: Aguardando confirmação do distrato | G27: 702.06 | I27: =IF(ISNUMBER(H27),Resumo!$C$3-H27,"") | L27: Cliente pediu cancelamento pelo chamado 800613 e o distrato está em fase de assinatura. Receita mensal perdida de R$ 702,06. | M27: Contratos confirmar a assinatura do distrato e CS registrar o motivo do cancelamento.
A28: Marco Antonio Giacon | B28: 30007041 | C28: 1 | D28: myFarm | E28: Pagamento ou acordo feito | F28: Acordo de pagamento em acompanhamento | G28: 700 | H28: 06/2026 | I28: =IF(ISNUMBER(H28),Resumo!$C$3-H28,"") | L28: Inadimplente desde fevereiro de 2026, pediu cancelamento em junho de 2026, depois de ser cobrado. Existe acordo de pagamento em acompanhamento. Mensalidade perdida de R$ 700,00; valor da dívida não informado. | M28: Cobrança acompanhar o cumprimento do acordo; contratos concluir o distrato ao fim do acordo.
A29: Joao Miguel Giongo Freitas | B29: 30006190 | C29: 1 | D29: myFarm | E29: Sem etapa registrada | F29: Cancelamento em andamento | G29: 590 | H29: 07/2026 | I29: =IF(ISNUMBER(H29),Resumo!$C$3-H29,"") | L29: Inadimplente desde janeiro de 2026, pediu cancelamento em julho de 2026 e o processo está em andamento. Mensalidade perdida de R$ 590,00. Valor da dívida não informado nas planilhas. | M29: Contratos formalizar o distrato; cobrança levantar o débito acumulado desde janeiro de 2026 para cobrar no encerramento.
A30: Claudio Moizes Decares | B30: 30006175 | C30: 1 | D30: myFarm | E30: Aguardando pagamento de boletos | F30: Aguardando pagamento dos boletos | G30: 550 | I30: =IF(ISNUMBER(H30),Resumo!$C$3-H30,"") | L30: Cliente pediu o cancelamento do contrato e o distrato está em assinatura. Mensalidade perdida de R$ 550,00. O encerramento depende do pagamento dos boletos em aberto, cujo valor não consta nas planilhas. | M30: Cobrança acompanhar o pagamento dos boletos; contratos concluir a assinatura do distrato após a quitação.
A31: Geraldo Roberto Mossignato | B31: 30003756 | C31: 1 | D31: myFarm | E31: Pagamento ou acordo feito | F31: Aguardando comprovante de pagamento | G31: 549.62 | H31: 46262 | I31: =IF(ISNUMBER(H31),Resumo!$C$3-H31,"") -> 28 | L31: Cliente pediu cancelamento em 28/08/2026. O valor em aberto e a chave PIX foram enviados ao cliente, que ainda não mandou o comprovante. Mensalidade de R$ 549,62. | M31: Cobrar o comprovante do PIX, confirmar o pagamento com o financeiro e formalizar o distrato.
A32: José Valdir Martins Vieira | B32: 30004798 | C32: 1 | D32: myFarm | E32: Distrato em assinatura | F32: Aguardando assinatura do distrato | G32: 528.11 | I32: =IF(ISNUMBER(H32),Resumo!$C$3-H32,"") | L32: Cliente pediu o cancelamento. Distrato enviado e aguardando assinatura do cliente. Mensalidade perdida de R$ 528,11. | M32: Cobrar a assinatura do distrato e encerrar o contrato.
A33: William Cardoso dos Santos | B33: 30005762 | C33: 1 | D33: myFarm | E33: Distrato em assinatura | F33: Aguardando retorno do CS | G33: 500 | I33: =IF(ISNUMBER(H33),Resumo!$C$3-H33,"") | L33: Cliente pediu cancelamento, tratado em chamado de atendimento. Distrato em fase de assinatura, financeiro aguarda retorno do CS. Mensalidade de R$ 500,00. | M33: CS dar retorno ao financeiro e concluir a assinatura do distrato.
A34: Roni Cesar Ferreira Alves Machado | B34: 30001886 | C34: 1 | D34: myFarm | E34: Sem etapa registrada | F34: Empresa fechada, sem contato | G34: 423.01 | I34: =IF(ISNUMBER(H34),Resumo!$C$3-H34,"") | J34: 1678.29 | L34: CS lista o contrato como cancelamento: empresa fechada, ligada a grupo em recuperação judicial, sem sucesso nas tentativas de contato. Financeiro mantém cobrança de R$ 1.678,29 faturados, com 217 dias de atraso e aval para negativação pedido em 20/07/2026 sem resposta. | M34: Contratos formalizar o encerramento; jurídico avaliar habilitação do crédito de R$ 1.678,29 na recuperação judicial.
A35: Vinicius da Silva Soares | B35: 30005162 | C35: 1 | D35: myFarm | E35: Sem etapa registrada | F35: Cancelamento em andamento | G35: 422.4 | I35: =IF(ISNUMBER(H35),Resumo!$C$3-H35,"") | L35: Cliente em processo de cancelamento, suspenso por inadimplência. Não há registro da etapa do distrato nem do valor em aberto. Mensalidade perdida de R$ 422,40. | M35: Confirmar a etapa do distrato e levantar se há débito a cobrar antes da baixa.
A36: Gizelly Santos | B36: 30004487 | C36: 1 | D36: myFarm | E36: Aguardando pagamento de boletos | F36: Aguardando pagamento dos boletos | G36: 410.95 | I36: =IF(ISNUMBER(H36),Resumo!$C$3-H36,"") | L36: Cliente pediu o cancelamento e o distrato está em assinatura. Pendente o pagamento dos boletos em aberto para encerrar. Mensalidade perdida de R$ 410,95. | M36: Cobrar os boletos em aberto e concluir a assinatura do distrato para baixa do contrato.
A37: Marino Bortolas Neto | B37: 30002073 | C37: 1 | D37: myFarm | E37: Sem etapa registrada | F37: Cancelamento sem etapa registrada | G37: 235.2 | I37: =IF(ISNUMBER(H37),Resumo!$C$3-H37,"") | L37: CS lista o contrato na aba de cancelamentos, com receita mensal perdida de R$ 235,20. Não há data do pedido, observação nem etapa do distrato registradas. | M37: CS registrar data do pedido e etapa do distrato; financeiro incluir o contrato na base de cancelamentos.
A38: Nativa Agricultura Sustentável Ltda | B38: 30003714 | C38: 1 | D38: AgriManager | E38: Sem etapa registrada | F38: Sem registro de etapa | I38: =IF(ISNUMBER(H38),Resumo!$C$3-H38,"") | L38: Consta como cancelamento no relatório do CS, com mensalidade perdida zerada. Não há anotação de etapa, data do pedido nem débito. | M38: CS registrar a data do pedido e a etapa do distrato, e confirmar com o financeiro se há débito ou multa pendente.
A39: Total | C39: =SUBTOTAL(9,C5:C38) -> 35 | G39: =SUBTOTAL(9,G5:G38) -> 49937.64 | J39: =SUBTOTAL(9,J5:J38) -> 37249.31 | K39: =SUBTOTAL(9,K5:K38) -> 15000

Sheet Negociação comercial
A1: Suspensos sem cobrança de dívida
A2: Renovação anual do myFarm, pendência de projeto ou análise contratual. O último contrato foi cedido e sai da lista de suspensos.
A4: Cliente | B4: Contrato | C4: Produto | D4: Motivo da suspensão | E4: Mensalidade (R$) | F4: Observação | G4: Próximo passo
A5: Cooperativa Agropecuária Primavera (COAP) | B5: 30005923 | C5: myFarm | D5: Renovação em negociação | E5: 5946.19 | F5: Contrato suspenso durante a renovação anual de 08/2026, com orientação de não cobrar. O cliente segue em atendimento, com demanda de produto levada ao desenvolvimento em 24/09/2026. | G5: Comercial concluir a renovação e alinhar com o CS a baixa do registro de cancelamento.
A6: Liseu José Scherer | B6: 30005114 | C6: myFarm | D6: Renovação em negociação | E6: 936.91 | F6: Contrato suspenso por negociação comercial na rodada de renovações anuais do myFarm de 08/2026. Sem débito informado. Mensalidade de R$ 936,91. | G6: Comercial concluir a renovação e definir prazo de retomada do acesso.
A7: Diego Mora Macena | B7: 30005113 | C7: myFarm | D7: Renovação em negociação | E7: 493.08 | F7: Contrato suspenso porque o cliente não renovou. O cliente informou que cotou outros ERPs e o comercial tenta reter na rodada de renovações anuais do myFarm de 08/2026. Mensalidade de R$ 493,08. | G7: Comercial apresentar proposta de renovação e definir prazo de retomada. Risco de perda para concorrente.
A8: Waldyrene Barros Silva | B8: 30005886 | C8: myFarm | D8: Implantação pausada pela cliente | E8: 419.25 | F8: Cliente pausou a implantação por um projeto pessoal e informou que não deseja cancelar. Contrato suspenso por pendência de projeto. Mensalidade de R$ 419,25. | G8: CS confirmar com a cliente a permanência, definir data de retomada da implantação e ajustar o status no sistema.
A9: Adriana Cristina Guizelini | B9: 30002312 | C9: myFarm | D9: Renovação sem retorno do cliente | E9: 408.28 | F9: Suspenso por negociação da renovação anual myFarm de 08/2026. Cliente não responde WhatsApp, email nem ligação. Sem dívida registrada; mensalidade de R$ 408,28. | G9: Comercial definir prazo de retomada da renovação; sem retorno, avaliar tratamento como cancelamento.
A10: José Wilian Bahdur | B10: 30003798 | C10: myFarm | D10: Aguardando retorno do comercial | E10: 312.52 | F10: Contrato de 2024 sem projeto aberto e sem uso do sistema. Suspenso pelo faturamento, aguardando a negociação do comercial. CS informa que o cliente nunca respondeu contatos nem cobranças e que o telefone cadastrado provavelmente mudou; mensalidade de R$ 312,52. | G10: Comercial confirmar se há contato ativo com o cliente; sem retorno, avaliar o encerramento do contrato.
A11: Rogerio Ezequiel Ferrari | B11: 30002988 | C11: AgriManager | D11: Contrato cedido a outro titular | F11: Contrato cedido a outro titular, que segue no contrato 30007586. Sem débito registrado. | G11: Contratos encerrar este contrato, que sai da lista de suspensos, e confirmar o contrato 30007586 ativo.
A12: Total | E12: =SUBTOTAL(9,E5:E11) -> 8516.23

Sheet Plano Safra
A1: Plano Safra: o que ficou para 30/03/2027
A2: Um acordo fechado e uma proposta em análise; os demais são candidatos.
A4: Como funciona
A5: 1. O cliente assina termo de confissão de dívida e o boleto vence em 30/03/2027, quando o produtor de grãos já recebeu pela colheita da soja.
A6: 2. A data fica antes de 30/04, quando vence a maior parte das compras de insumos: a Aliare recebe antes dos outros credores.
A7: 3. O represado e as mensalidades de outubro a dezembro podem entrar no mesmo boleto.
A8: 4. A mensalidade volta a ser faturada no mês seguinte ao acordo, e o contrato é reativado.
A9: 5. Pede entrada ou parcela intermediária antes da virada do ano, e justificativa de plantio.
A11: Cliente | B11: Contrato | C11: Situação | D11: Valor envolvido (R$) | E11: Vencimento | F11: Condição | G11: Observação
A12: Marcos Aurelio Sinopoli | B12: 30002424 | C12: Acordo fechado em 18/09/2026 | D12: 13521.08 | E12: 46476 | F12: Represado de junho a setembro de 2026 em pagamento único | G12: O cliente segue pagando as mensalidades e o acordo anterior.
A13: Pedro Henrique Pinto Fadel | B13: 30003903 | C13: Proposta enviada, em análise | D13: 35736.48 | E13: 46476 | F13: 5 parcelas de R$ 3.573,64 até fevereiro e saldo de R$ 17.868,28 em 30/03/2027 | G13: O cliente alega dificuldade financeira e contesta o valor.
A14: Alzir Pimentel Aguiar Neto | B14: 30003232 | C14: Candidato | D14: 43792.2 | F14: Represado fora do acordo de 10 parcelas feito com o escritório | G14: Reunião em 25/09/2026 às 15h para tratar dos débitos.
A15: Petras de Lima Telles | B15: 30002744 | C15: Candidato | D15: 58075.29 | F15: 13 parcelas represadas desde 09/2025 | G15: Cliente sem retorno.
A16: Nova Fronteira Agropecuária Ltda | B16: 30003342 | C16: Indicado pelo financeiro | D16: 4955.97 | F16: Flexibilização para 2027 com entrada de 20% | G16: Cliente sem retorno.
