Workbook

Sheet Consolidado
A1: CONSOLIDADO DE CHURN E DOWNSELL — 1 linha por cliente x produto
A2: Filtro: STATUS = Churn ou Downsell. Agrupamento: Cliente (col. A original) x Novo_Produto (col. G original). Valores: soma COM SINAL da coluna Variacao (col. D original) — ver aba Notas.
A4: Cliente | B4: Cód. Cliente | C4: Contrato(s) | D4: Produto | E4: Status | F4: Competência(s) | G4: Qtd. linhas origem | H4: Variação total (R$) | I4: Perda (R$ positivo) | J4: % da perda total | K4: Considera no Churn? | L4: Procede? | M4: Trato por CSM? | N4: Motivo do Cancelamento | O4: Motivo do Cancelamento (categoria)
A5: SERIOS AGROPECUARIA LTDA | B5: 30008363 | C5: 30001083 | D5: Agrimanager ERP | E5: Downsell | F5: fev/26; mai/26 | G5: 3 | H5: =SUMIFS(Base_Tratada!$H:$H,Base_Tratada!$A:$A,$A5,Base_Tratada!$G:$G,$D5) -> -16573.14 | I5: =-H5 -> 16573.14 | J5: =IFERROR(I5/$I$67,0) -> 0.15266014 | K5: Sim | L5: Sim | M5: Sim | N5: Troca de ERP | O5: Troca de ERP
A6: CLODOVEU FRANCIOSI IE 133535746 | B6: 30006916 | C6: 30001424 | D6: Agrimanager ERP | E6: Downsell | F6: jun/26 | G6: 1 | H6: =SUMIFS(Base_Tratada!$H:$H,Base_Tratada!$A:$A,$A6,Base_Tratada!$G:$G,$D6) -> -13701.65 | I6: =-H6 -> 13701.65 | J6: =IFERROR(I6/$I$67,0) -> 0.12620999 | K6: Sim | L6: Sim | M6: Sim | N6: Querem eduzir as licenças porque estava “em processo de migração de ERP”. Por isso, solicitou permanecer com apenas 1 licença de cada módulo ativo, além do cancelamento completo do módulo de Recursos Humanos. | O6: troca de ERP
A7: SERRA BONITA SEMENTES S.A. | B7: 30005436 | C7: 30000899 | D7: Agrimanager ERP | E7: Downsell | F7: fev/26; mai/26 | G7: 2 | H7: =SUMIFS(Base_Tratada!$H:$H,Base_Tratada!$A:$A,$A7,Base_Tratada!$G:$G,$D7) -> -6532.98 | I7: =-H7 -> 6532.98 | J7: =IFERROR(I7/$I$67,0) -> 0.06017723 | K7: Sim | L7: Sim | M7: Sim | N7: Venda da empresa | O7: Venda da empresa
A8: LEONARDO LUIZ OSS | B8: 30016958 | C8: 30005248 | D8: My Farm ERP | E8: Downsell | F8: mai/26 | G8: 1 | H8: =SUMIFS(Base_Tratada!$H:$H,Base_Tratada!$A:$A,$A8,Base_Tratada!$G:$G,$D8) -> -4195.79 | I8: =-H8 -> 4195.79 | J8: =IFERROR(I8/$I$67,0) -> 0.038648675 | L8: Sim | M8: Sim | N8: Cancelamento do serviço de BPO | O8: Decisão estratégica / internalização
A9: 3SB PRODUTOS AGRICOLAS S.A. | B9: 30007727 | C9: 30000677 | D9: Agrimanager ERP | E9: Churn | F9: fev/26 | G9: 5 | H9: =SUMIFS(Base_Tratada!$H:$H,Base_Tratada!$A:$A,$A9,Base_Tratada!$G:$G,$D9) -> -4170.46 | I9: =-H9 -> 4170.46 | J9: =IFERROR(I9/$I$67,0) -> 0.038415352 | K9: Sim | L9: Sim | M9: Sim | N9: Cancelamento parcial: falta de integração com outros sistemas, falta de recursos no produto, mudança nas necessidades do cliente e problemas de suporte | O9: Falta de flexibilidade e automação do AGM.
A10: BRUNO SANCHES TORO | B10: 30015024 | C10: 30004006 | D10: Agrimanager ERP | E10: Churn | F10: jun/26 | G10: 3 | H10: =SUMIFS(Base_Tratada!$H:$H,Base_Tratada!$A:$A,$A10,Base_Tratada!$G:$G,$D10) -> -4010.69 | I10: =-H10 -> 4010.69 | J10: =IFERROR(I10/$I$67,0) -> 0.036943663 | K10: Sim | L10: Sim | M10: Sim | N10: Problemas financeiros | O10: Gap funcional / limitação do produto
A11: CLAUDIO AUGUSTO DINIZ - I.E. 13.235.367-9 | B11: 30009772 | C11: 30001556 | D11: Agrimanager ERP | E11: Churn | F11: mai/26 | G11: 2 | H11: =SUMIFS(Base_Tratada!$H:$H,Base_Tratada!$A:$A,$A11,Base_Tratada!$G:$G,$D11) -> -3408.4 | I11: =-H11 -> 3408.4 | J11: =IFERROR(I11/$I$67,0) -> 0.03139579 | K11: Sim | L11: Sim | M11: Sim | N11: Uso restrito a emissão de nota, tornando a operação inviável | O11: Baixa adoção / não uso
A12: RICARDO SILVA ROCHA IE: 11.196.197-1 | B12: 30013024 | C12: 30003254 | D12: Agrimanager ERP | E12: Churn | F12: fev/26 | G12: 2 | H12: =SUMIFS(Base_Tratada!$H:$H,Base_Tratada!$A:$A,$A12,Base_Tratada!$G:$G,$D12) -> -3117.15 | I12: =-H12 -> 3117.15 | J12: =IFERROR(I12/$I$67,0) -> 0.028712999 | L12: Não | M12: Sim | N12: Migração interna para My Farm (Primavera) — receita retida na Aliare | O12: Migração interna de ERP
A13: NATALINO BIGOLIN IE:13.606.182-6 | B13: 30006687 | C13: 30004170 | D13: Aliare Cloud - PR | E13: Churn | F13: mai/26 | G13: 1 | H13: =SUMIFS(Base_Tratada!$H:$H,Base_Tratada!$A:$A,$A13,Base_Tratada!$G:$G,$D13) -> -3046.65 | I13: =-H13 -> 3046.65 | J13: =IFERROR(I13/$I$67,0) -> 0.028063603 | K13: Sim | L13: Sim | M13: Sim | N13: Sem acesso ao banco de dados | O13: Gap funcional / limitação do produto
A14: LUIS HENRIQUE PAZINI E OUTRO - IE - 133440532 | B14: 30018439 | C14: 30006041 | D14: My Farm ERP | E14: Churn | F14: mai/26 | G14: 1 | H14: =SUMIFS(Base_Tratada!$H:$H,Base_Tratada!$A:$A,$A14,Base_Tratada!$G:$G,$D14) -> -2775.55 | I14: =-H14 -> 2775.55 | J14: =IFERROR(I14/$I$67,0) -> 0.02556642 | K14: Sim | L14: Sim | M14: Sim | N14: Não informado pelo cliente, solicitação de cancelamento sem justificativa porém foi encontrados informações sobre insatisfação sobre instabilidade do sistema. | O14: Instabilidade myFarm.
A15: ZORZETTO ASSES. E CONSULTORIA AGRONOMICA LTDA. | B15: 30010916 | C15: 30002254 | D15: Agrimanager ERP | E15: Churn | F15: jun/26 | G15: 2 | H15: =SUMIFS(Base_Tratada!$H:$H,Base_Tratada!$A:$A,$A15,Base_Tratada!$G:$G,$D15) -> -2243.46 | I15: =-H15 -> 2243.46 | J15: =IFERROR(I15/$I$67,0) -> 0.02066518 | K15: Sim | L15: Sim | M15: Sim (outra vertical) | N15: Não informado — tratado pelo CS de Distribuidor Rural | O15: Troca de ERP
A16: OCTAVIANO RAYMUNDO CAMARGO SILVA IE:212.059.354.118 | B16: 30016194 | C16: 30004772 | D16: Agrimanager ERP | E16: Churn | F16: jun/26 | G16: 1 | H16: =SUMIFS(Base_Tratada!$H:$H,Base_Tratada!$A:$A,$A16,Base_Tratada!$G:$G,$D16) -> -2150.61 | I16: =-H16 -> 2150.61 | J16: =IFERROR(I16/$I$67,0) -> 0.019809911 | K16: Sim | L16: Sim | M16: Sim | N16: Falta de mão de obra para operar o sistema | O16: Falta de mão de obra / estrutura
A17: VALQUIRIA MARCELINO FERREIRA ABREU IE: 13.429.008-9 | B17: 30016155 | C17: 30004756 | D17: Agrimanager ERP | E17: Churn | F17: mai/26 | G17: 1 | H17: =SUMIFS(Base_Tratada!$H:$H,Base_Tratada!$A:$A,$A17,Base_Tratada!$G:$G,$D17) -> -2110.81 | I17: =-H17 -> 2110.81 | J17: =IFERROR(I17/$I$67,0) -> 0.019443301 | K17: Sim | L17: Sim | M17: Não localizado | N17: Não informado — sem histórico de tratativas | O17: Troca de ERP
A18: CLODOVEU FRANCIOSI IE 133535746 | B18: 30006916 | C18: 30001424 | D18: Agrimanager Algodoeira | E18: Churn | F18: mar/26 | G18: 1 | H18: =SUMIFS(Base_Tratada!$H:$H,Base_Tratada!$A:$A,$A18,Base_Tratada!$G:$G,$D18) -> -1926.9898 | I18: =-H18 -> 1926.9898 | J18: =IFERROR(I18/$I$67,0) -> 0.017750078 | K18: Sim | L18: Sim | M18: Sim | N18: Troca de ERP | O18: Troca de ERP
A19: SEMENTES TRES PINHEIROS SEEDS LTDA | B19: 30010348 | C19: 30004593 | D19: Aliare Cloud - PR | E19: Churn | F19: jan/26 | G19: 1 | H19: =SUMIFS(Base_Tratada!$H:$H,Base_Tratada!$A:$A,$A19,Base_Tratada!$G:$G,$D19) -> -1875.06 | I19: =-H19 -> 1875.06 | J19: =IFERROR(I19/$I$67,0) -> 0.017271738 | K19: Sim | L19: Sim | M19: Não | N19: Não informado | O19: Troca de ERP
A20: MARCONDES AGROPECUARIA LTDA | B20: 30010824 | C20: 30001946 | D20: Vistra BI - PR | E20: Downsell | F20: fev/26 | G20: 1 | H20: =SUMIFS(Base_Tratada!$H:$H,Base_Tratada!$A:$A,$A20,Base_Tratada!$G:$G,$D20) -> -1865.58 | I20: =-H20 -> 1865.58 | J20: =IFERROR(I20/$I$67,0) -> 0.017184414 | K20: Sim | L20: Não | M20: Não | N20: Contrato permanece ativo cliente pagando 1.810,39 | O20: Não encontrou valor na solução
A21: CAPIVARY AGROPASTORIL LTDA | B21: 30010978 | C21: 30002051 | D21: Agrimanager ERP | E21: Downsell | F21: jan/26 | G21: 1 | H21: =SUMIFS(Base_Tratada!$H:$H,Base_Tratada!$A:$A,$A21,Base_Tratada!$G:$G,$D21) -> -1657.47 | I21: =-H21 -> 1657.47 | J21: =IFERROR(I21/$I$67,0) -> 0.015267451 | K21: Sim | L21: Sim | M21: Sim | N21: Terceirizou ADM e financeiro para a contabilidade, inicialmente permaneceriam com um usuário, por fim optaram por realizar o cancelamento | O21: Baixa adoção / não uso / falta de mão obra
A22: CARLOS ALBERTO MORESCO | B22: 20000027 | C22: 30001343 | D22: Vistra BI - PR | E22: Churn | F22: fev/26 | G22: 1 | H22: =SUMIFS(Base_Tratada!$H:$H,Base_Tratada!$A:$A,$A22,Base_Tratada!$G:$G,$D22) -> -1655.56 | I22: =-H22 -> 1655.56 | J22: =IFERROR(I22/$I$67,0) -> 0.015249858 | K22: Sim | L22: Sim | M22: Sim | N22: Restrições financeiras | O22: problemas financeiros
A23: BRUNO SANCHES TORO | B23: 30015024 | C23: 30004006 | D23: Aliare Cloud - PR | E23: Churn | F23: jun/26 | G23: 3 | H23: =SUMIFS(Base_Tratada!$H:$H,Base_Tratada!$A:$A,$A23,Base_Tratada!$G:$G,$D23) -> -1650.36 | I23: =-H23 -> 1650.36 | J23: =IFERROR(I23/$I$67,0) -> 0.015201959 | K23: Sim | L23: Sim | M23: Sim | N23: Problemas financeiros | O23: problemas financeiros
A24: OSVALDO HANISCH - I.E. 057.547.903 | B24: 10002290 | C24: 30001671 | D24: Agrimanager ERP | E24: Downsell | F24: jun/26 | G24: 1 | H24: =SUMIFS(Base_Tratada!$H:$H,Base_Tratada!$A:$A,$A24,Base_Tratada!$G:$G,$D24) -> -1484.86 | I24: =-H24 -> 1484.86 | J24: =IFERROR(I24/$I$67,0) -> 0.013677489 | L24: Sim | M24: Sim | N24: Reestruturação no quadro de colaboradores | O24: Falta de mão de obra / estrutura
A25: AGRO 100 COMERCIO DE PRODUTOS AGRICOLAS LTDA - EM RECUPERACAO | B25: 10001146 | C25: 10000135 | D25: Agrimanager ERP | E25: Churn | F25: mar/26 | G25: 1 | H25: =SUMIFS(Base_Tratada!$H:$H,Base_Tratada!$A:$A,$A25,Base_Tratada!$G:$G,$D25) -> -1375.16 | I25: =-H25 -> 1375.16 | J25: =IFERROR(I25/$I$67,0) -> 0.012667009 | L25: Sem informação | M25: Não | N25: Sem informação | O25: Sem relatório de churn
A26: FERNANDO CAVALHEIRO MACHADO I.E.29.439.136-3 | B26: 30008736 | C26: 30005481 | D26: Vistra BI - PR | E26: Downsell | F26: fev/26 | G26: 1 | H26: =SUMIFS(Base_Tratada!$H:$H,Base_Tratada!$A:$A,$A26,Base_Tratada!$G:$G,$D26) -> -1352.1 | I26: =-H26 -> 1352.1 | J26: =IFERROR(I26/$I$67,0) -> 0.012454597 | L26: Não | M26: Não | N26: Provável inadimplência, sem tratativa de churn localizada | O26: Sem relatório de churn
A27: MARIO PINTO DA SILVA | B27: 30020666 | C27: 30007174 | D27: My Farm ERP | E27: Churn | F27: jun/26 | G27: 1 | H27: =SUMIFS(Base_Tratada!$H:$H,Base_Tratada!$A:$A,$A27,Base_Tratada!$G:$G,$D27) -> -1327.99 | I27: =-H27 -> 1327.99 | J27: =IFERROR(I27/$I$67,0) -> 0.012232512 | K27: Sim | L27: Sim | M27: Sim | N27: Gap funcional: cliente de pecuária, My Farm não atendeu | O27: Gap funcional / limitação do produto
A28: FLAVIO FAEDO IE 11.508.239-5 | B28: 130 | C28: 30002569 | D28: My Farm ERP | E28: Churn | F28: fev/26 | G28: 1 | H28: =SUMIFS(Base_Tratada!$H:$H,Base_Tratada!$A:$A,$A28,Base_Tratada!$G:$G,$D28) -> -1201.82 | I28: =-H28 -> 1201.82 | J28: =IFERROR(I28/$I$67,0) -> 0.011070323 | K28: Sim | L28: Sim | M28: Sim | N28: Troca de ERP | O28: Falta de engajamento e recursos do produto
A29: ACASSIO TELES DE CASTRO | B29: 30017239 | C29: 30005439 | D29: My Farm ERP | E29: Churn | F29: jan/26 | G29: 1 | H29: =SUMIFS(Base_Tratada!$H:$H,Base_Tratada!$A:$A,$A29,Base_Tratada!$G:$G,$D29) -> -1200 | I29: =-H29 -> 1200 | J29: =IFERROR(I29/$I$67,0) -> 0.011053558 | K29: Sim | L29: Sim | M29: Sim | N29: Falta de mão de obra para operar o sistema | O29: Falta de mão de obra / estrutura
A30: S EPP AGRICOLA LTDA | B30: 30015247 | C30: 30001307 | D30: Vistra BI - PR | E30: Downsell | F30: fev/26 | G30: 1 | H30: =SUMIFS(Base_Tratada!$H:$H,Base_Tratada!$A:$A,$A30,Base_Tratada!$G:$G,$D30) -> -1178.13 | I30: =-H30 -> 1178.13 | J30: =IFERROR(I30/$I$67,0) -> 0.010852107 | L30: Não | M30: Não | N30: Ajuste financeiro pelo time de contratos | O30: Reajuste financeiro contratual
A31: ANDRE LUIZ COELHO GUILHERME | B31: 30016960 | C31: 30005242 | D31: My Farm ERP | E31: Churn | F31: mai/26 | G31: 1 | H31: =SUMIFS(Base_Tratada!$H:$H,Base_Tratada!$A:$A,$A31,Base_Tratada!$G:$G,$D31) -> -1073.29 | I31: =-H31 -> 1073.29 | J31: =IFERROR(I31/$I$67,0) -> 0.0098863947 | K31: Sim | L31: Sim | M31: Sim | N31: Falta de mão de obra para operar o sistema | O31: Falta de mão de obra / estrutura
A32: PEDRO ALCEU BACH | B32: 30019380 | C32: 30006286 | D32: My Farm ERP | E32: Churn | F32: jun/26 | G32: 1 | H32: =SUMIFS(Base_Tratada!$H:$H,Base_Tratada!$A:$A,$A32,Base_Tratada!$G:$G,$D32) -> -1070 | I32: =-H32 -> 1070 | J32: =IFERROR(I32/$I$67,0) -> 0.0098560895 | K32: Sim | L32: Sim | M32: Sim | N32: Cliente alega que o sistema não atende as demandas | O32: Recursos do produto
A33: THIAGO DE ALMEIDA | B33: 30011397 | C33: 30002281 | D33: My Farm ERP | E33: Churn | F33: jun/26 | G33: 1 | H33: =SUMIFS(Base_Tratada!$H:$H,Base_Tratada!$A:$A,$A33,Base_Tratada!$G:$G,$D33) -> -1067.58 | I33: =-H33 -> 1067.58 | J33: =IFERROR(I33/$I$67,0) -> 0.0098337982 | K33: Sim | L33: Sim (ressalva) | M33: Sem informação | N33: Solicitado pelo cliente em 08/2025 — baixa registrada em jun/26 | O33: Falta de mão de obra / estrutura
A34: LUCAS BOLOGNINI STRACCI | B34: 30016543 | C34: 30001182 | D34: Agrimanager ERP | E34: Churn | F34: jun/26 | G34: 9 | H34: =SUMIFS(Base_Tratada!$H:$H,Base_Tratada!$A:$A,$A34,Base_Tratada!$G:$G,$D34) -> -1040.32 | I34: =-H34 -> 1040.32 | J34: =IFERROR(I34/$I$67,0) -> 0.0095826982 | K34: Sim | L34: Sim | M34: Sim | N34: Cliente solicitou em 09/2025 - baixa registrada em 06/2026 | O34: Troca de ERP
A35: ROQUE CASSOL | B35: 30017104 | C35: 30005345 | D35: My Farm ERP | E35: Churn | F35: fev/26 | G35: 1 | H35: =SUMIFS(Base_Tratada!$H:$H,Base_Tratada!$A:$A,$A35,Base_Tratada!$G:$G,$D35) -> -1010.94 | I35: =-H35 -> 1010.94 | J35: =IFERROR(I35/$I$67,0) -> 0.0093120702 | K35: Sim | L35: Sim | M35: Sim | N35: Uso restrito a emissão de nota; passou para a contabilidade | O35: Migração para solução própria ou contábil
A36: FABIANO BERGOLI ZAMBERLAN IE:120114927-1 | B36: 30017436 | C36: 30005541 | D36: My Farm ERP | E36: Churn | F36: jun/26 | G36: 1 | H36: =SUMIFS(Base_Tratada!$H:$H,Base_Tratada!$A:$A,$A36,Base_Tratada!$G:$G,$D36) -> -963.73 | I36: =-H36 -> 963.73 | J36: =IFERROR(I36/$I$67,0) -> 0.0088772048 | K36: Sim | L36: Sim | M36: Sim | N36: Desengajado e usava planilhas no paralelo | O36: Falta de mão de obra / estrutura
A37: PAULO RICARDO SANTIN | B37: 30017209 | C37: 30005426 | D37: My Farm ERP | E37: Churn | F37: jun/26 | G37: 1 | H37: =SUMIFS(Base_Tratada!$H:$H,Base_Tratada!$A:$A,$A37,Base_Tratada!$G:$G,$D37) -> -937.62 | I37: =-H37 -> 937.62 | J37: =IFERROR(I37/$I$67,0) -> 0.0086366978 | K37: Sim | L37: Sim | M37: Sim | N37: Nunca usou o sistema | O37: Baixa adoção / não uso
A38: DONA EMA AGROPECUARIA E INDUSTRIAL LTDA | B38: 30013184 | C38: 30000891 | D38: Agrimanager ERP | E38: Downsell | F38: fev/26 | G38: 1 | H38: =SUMIFS(Base_Tratada!$H:$H,Base_Tratada!$A:$A,$A38,Base_Tratada!$G:$G,$D38) -> -884.96 | I38: =-H38 -> 884.96 | J38: =IFERROR(I38/$I$67,0) -> 0.0081516308 | L38: Sim | M38: Não | N38: Redução feita atravez de ticket 698079 | O38: Sem informação
A39: EDUARDO ZORZI - I.E. 13.322.258-6 | B39: 30010781 | C39: 30001903 | D39: Vistra BI - PR | E39: Downsell | F39: fev/26 | G39: 1 | H39: =SUMIFS(Base_Tratada!$H:$H,Base_Tratada!$A:$A,$A39,Base_Tratada!$G:$G,$D39) -> -865.52 | I39: =-H39 -> 865.52 | J39: =IFERROR(I39/$I$67,0) -> 0.0079725632 | L39: Sim | M39: Sim | N39: Não estavam utilizando | O39: Baixa adoção / não uso
A40: ADEMIR JOSE COMPARIM IE-28.523.221-5 | B40: 30012242 | C40: 30002927 | D40: My Farm ERP | E40: Churn | F40: jan/26 | G40: 1 | H40: =SUMIFS(Base_Tratada!$H:$H,Base_Tratada!$A:$A,$A40,Base_Tratada!$G:$G,$D40) -> -840.51 | I40: =-H40 -> 840.51 | J40: =IFERROR(I40/$I$67,0) -> 0.0077421886 | K40: Sim | L40: Sim | M40: Sim | N40: Não localizado historico CS, apenas informação do time de contratos de que recebeu a demanda do CS | O40: Falta de mão de obra / estrutura
A41: EVANDRO VILELA BARROS IE 11.331.859-6 | B41: 30014925 | C41: 30003941 | D41: My Farm ERP | E41: Churn | F41: mai/26 | G41: 1 | H41: =SUMIFS(Base_Tratada!$H:$H,Base_Tratada!$A:$A,$A41,Base_Tratada!$G:$G,$D41) -> -827.41 | I41: =-H41 -> 827.41 | J41: =IFERROR(I41/$I$67,0) -> 0.0076215206 | K41: Sim | L41: Sim | M41: Sim | N41: Falta de mão de obra para operar o sistema | O41: Troca de ERP
A42: TANIA POTRICH DE ROCCO E OUTROS IE 13.234.919-1 | B42: 30017565 | C42: 30005685 | D42: Vistra BI - PR | E42: Downsell | F42: fev/26 | G42: 1 | H42: =SUMIFS(Base_Tratada!$H:$H,Base_Tratada!$A:$A,$A42,Base_Tratada!$G:$G,$D42) -> -810.33 | I42: =-H42 -> 810.33 | J42: =IFERROR(I42/$I$67,0) -> 0.0074641916 | L42: Não | M42: Não | N42: Ajuste financeiro pelo time de contratos | O42: Reajuste financeiro contratual
A43: RODRIGO KONAGESKI I.E.13.252.476-7 | B43: 30011301 | C43: 30002242 | D43: Vistra BI - PR | E43: Churn | F43: fev/26 | G43: 1 | H43: =SUMIFS(Base_Tratada!$H:$H,Base_Tratada!$A:$A,$A43,Base_Tratada!$G:$G,$D43) -> -777.26 | I43: =-H43 -> 777.26 | J43: =IFERROR(I43/$I$67,0) -> 0.007159574 | K43: Sim | L43: Sim | M43: Sim | N43: Decisão interna cliente, devido informações lançadas erradas no erp. | O43: Falta de mão de obra / estrutura
A44: VALDIR FREIER IE 00132823500 | B44: 30011963 | C44: 30002645 | D44: My Farm ERP | E44: Churn | F44: jun/26 | G44: 1 | H44: =SUMIFS(Base_Tratada!$H:$H,Base_Tratada!$A:$A,$A44,Base_Tratada!$G:$G,$D44) -> -772.9 | I44: =-H44 -> 772.9 | J44: =IFERROR(I44/$I$67,0) -> 0.0071194127 | K44: Sim | L44: Sim (ressalva) | M44: Sim | N44: Cancelamento ocorrido em set/2025 — baixa registrada em jun/26. Não há uma causa formal registrada para o cancelamento do MyFarm; o histórico mostra sinais de risco e tentativa de retenção, mas não documenta a justificativa dada pelo cliente. | O44: Inadimplência
A45: WAGNER EDUARDO BALDIN PEREIRA | B45: 30017869 | C45: 30005764 | D45: My Farm ERP | E45: Churn | F45: jun/26 | G45: 1 | H45: =SUMIFS(Base_Tratada!$H:$H,Base_Tratada!$A:$A,$A45,Base_Tratada!$G:$G,$D45) -> -644.79 | I45: =-H45 -> 644.79 | J45: =IFERROR(I45/$I$67,0) -> 0.0059393532 | K45: Sim | L45: Sim | M45: Sim | N45: Arrendou a propriedade | O45: Encerramento de atividades
A46: GUILHERME DE ARAUJO PREDIGER | C46: 30007398 | D46: My Farm ERP | E46: Churn | F46: jun/26 | G46: 1 | H46: =SUMIFS(Base_Tratada!$H:$H,Base_Tratada!$A:$A,$A46,Base_Tratada!$G:$G,$D46) -> -621.26 | I46: =-H46 -> 621.26 | J46: =IFERROR(I46/$I$67,0) -> 0.0057226114 | K46: Sim | L46: Sim | M46: Não | N46: Cliente revogou a contratação antes de chegar ao CS | O46: Gap funcional / limitação do produto
A47: RENTAX AGROSOLUCOES E SERVICOS ADMINISTRATIVOS LTDA | B47: 30016676 | C47: 30005063 | D47: My Farm ERP | E47: Churn | F47: jan/26 | G47: 2 | H47: =SUMIFS(Base_Tratada!$H:$H,Base_Tratada!$A:$A,$A47,Base_Tratada!$G:$G,$D47) -> -620.27 | I47: =-H47 -> 620.27 | J47: =IFERROR(I47/$I$67,0) -> 0.0057134922 | K47: Sim | L47: Sim | M47: Sim | N47: Encerramento das atividades da empresa | O47: Encerramento de atividades
A48: PAULO EMILIO PALUDO - IE 13.345.834-2 | B48: 30014318 | C48: 30003760 | D48: My Farm ERP | E48: Churn | F48: mai/26 | G48: 1 | H48: =SUMIFS(Base_Tratada!$H:$H,Base_Tratada!$A:$A,$A48,Base_Tratada!$G:$G,$D48) -> -607.37417 | I48: =-H48 -> 607.37417 | J48: =IFERROR(I48/$I$67,0) -> 0.0055947048 | K48: Sim | L48: Sim | M48: Sim | N48: Não informado | O48: Gap funcional / limitação do produto
A49: CARLOS FERNANDO DA SILVEIRA BUENO | B49: 30017285 | C49: 30005453 | D49: My Farm ERP | E49: Churn | F49: jan/26 | G49: 1 | H49: =SUMIFS(Base_Tratada!$H:$H,Base_Tratada!$A:$A,$A49,Base_Tratada!$G:$G,$D49) -> -583.33 | I49: =-H49 -> 583.33 | J49: =IFERROR(I49/$I$67,0) -> 0.0053732268 | K49: Sim | L49: Sim | M49: Sim | N49: Não localizado historico CS, apenas informação do time de contratos de que recebeu a demanda do CS | O49: Sem informações
A50: MARCELO ANDRE KONAGESKI | B50: 30008217 | C50: 30001240 | D50: Agrimanager ERP | E50: Downsell | F50: mai/26 | G50: 1 | H50: =SUMIFS(Base_Tratada!$H:$H,Base_Tratada!$A:$A,$A50,Base_Tratada!$G:$G,$D50) -> -580.08 | I50: =-H50 -> 580.08 | J50: =IFERROR(I50/$I$67,0) -> 0.0053432901 | L50: Sim | M50: Sim | N50: Redução de colaboradores | O50: Redução de colaboradores
A51: MATEUS EDUARDO GONCALVES VIANA | B51: 30005462 | C51: 30000900 | D51: Agrimanager ERP | E51: Downsell | F51: mar/26 | G51: 1 | H51: =SUMIFS(Base_Tratada!$H:$H,Base_Tratada!$A:$A,$A51,Base_Tratada!$G:$G,$D51) -> -561.54 | I51: =-H51 -> 561.54 | J51: =IFERROR(I51/$I$67,0) -> 0.0051725126 | L51: Sim | M51: Sim | N51: Redução de colaboradores | O51: Redução de colaboradores
A52: MBB AGRO LTDA | B52: 30016791 | C52: 30005763 | D52: Vistra BI - PR | E52: Churn | F52: fev/26 | G52: 1 | H52: =SUMIFS(Base_Tratada!$H:$H,Base_Tratada!$A:$A,$A52,Base_Tratada!$G:$G,$D52) -> -517.19 | I52: =-H52 -> 517.19 | J52: =IFERROR(I52/$I$67,0) -> 0.0047639915 | L52: A validar | M52: Não | N52: Cliente segue utilizando o BI — evento a confirmar | O52: Contrato Ativo
A53: CORNELIO ADRIANO SANDERS E OUTROS | B53: 20000043 | C53: 30000717 | D53: Agrimanager ERP | E53: Downsell | F53: jun/26 | G53: 1 | H53: =SUMIFS(Base_Tratada!$H:$H,Base_Tratada!$A:$A,$A53,Base_Tratada!$G:$G,$D53) -> -514.72 | I53: =-H53 -> 514.72 | J53: =IFERROR(I53/$I$67,0) -> 0.0047412396 | L53: Sim | M53: Sim | N53: Redução feita atravez de ticket 770439, sem justificativa. | O53: Sen informação
A54: ELIANA GASPARINI TESTA IE 111876893 | B54: 30018091 | C54: 30005902 | D54: My Farm ERP | E54: Churn | F54: fev/26 | G54: 1 | H54: =SUMIFS(Base_Tratada!$H:$H,Base_Tratada!$A:$A,$A54,Base_Tratada!$G:$G,$D54) -> -480 | I54: =-H54 -> 480 | J54: =IFERROR(I54/$I$67,0) -> 0.0044214233 | K54: Sim | L54: Sim | M54: Sim | N54: Gap funcional: My Farm não atende leilão de animais | O54: Gap funcional / limitação do produto
A55: JORGE AUGUSTO BARRAGANA BRAZEIRO | B55: 30016118 | C55: 30004747 | D55: Vistra BI - PR | E55: Churn | F55: mar/26 | G55: 3 | H55: =SUMIFS(Base_Tratada!$H:$H,Base_Tratada!$A:$A,$A55,Base_Tratada!$G:$G,$D55) -> -447.72 | I55: =-H55 -> 447.72 | J55: =IFERROR(I55/$I$67,0) -> 0.0041240826 | L55: Não | M55: Não | N55: Cliente Simer | O55: Vertical Distribuição
A56: MARCOS CESAR JORDAO | B56: 30004467 | C56: 30000770 | D56: Agrimanager Autorize | E56: Downsell | F56: jun/26 | G56: 1 | H56: =SUMIFS(Base_Tratada!$H:$H,Base_Tratada!$A:$A,$A56,Base_Tratada!$G:$G,$D56) -> -407.24 | I56: =-H56 -> 407.24 | J56: =IFERROR(I56/$I$67,0) -> 0.0037512092 | L56: Não | M56: Sim | N56: Erro de venda/faturamento (venda errada) | O56: Erro de venda
A57: GERALDO AUGUSTO MARTINS TEIXEIRA IE 37260520019 | B57: 30015743 | C57: 30005853 | D57: My Farm ERP | E57: Churn | F57: mar/26 | G57: 1 | H57: =SUMIFS(Base_Tratada!$H:$H,Base_Tratada!$A:$A,$A57,Base_Tratada!$G:$G,$D57) -> -320 | I57: =-H57 -> 320 | J57: =IFERROR(I57/$I$67,0) -> 0.0029476156 | K57: Sim | L57: Sim | M57: Sim | N57: Migrou para software específico de produção de leite e bovinos | O57: Gap funcional / limitação do produto
A58: LEINNER LIMA BORGES IE 11.468.592-4 | B58: 30012511 | C58: 30003044 | D58: My Farm ERP | E58: Churn | F58: fev/26 | G58: 1 | H58: =SUMIFS(Base_Tratada!$H:$H,Base_Tratada!$A:$A,$A58,Base_Tratada!$G:$G,$D58) -> -302.91 | I58: =-H58 -> 302.91 | J58: =IFERROR(I58/$I$67,0) -> 0.0027901945 | K58: Sim | L58: Sim (ressalva) | M58: Sim | N58: Lentidão/performance do My Farm — cancelamento originado em 2025 | O58: Instabilidade myFarm.
A59: LEANDRO CAIAFFA ORCAY | B59: 30016337 | C59: 30004869 | D59: My Farm ERP | E59: Downsell | F59: mai/26 | G59: 2 | H59: =SUMIFS(Base_Tratada!$H:$H,Base_Tratada!$A:$A,$A59,Base_Tratada!$G:$G,$D59) -> -213.03 | I59: =-H59 -> 213.03 | J59: =IFERROR(I59/$I$67,0) -> 0.0019622829 | L59: Sim | M59: Sim | N59: Cliente renovou baseado no valor sem INPC | O59: Renovação errada
A60: ANTONIO MIGUEL WEBER DOS SANTOS I.E. 13.294.586-0 | B60: 30010080 | C60: 30001646 | D60: Agrimanager Autorize | E60: Churn | F60: abr/26 | G60: 1 | H60: =SUMIFS(Base_Tratada!$H:$H,Base_Tratada!$A:$A,$A60,Base_Tratada!$G:$G,$D60) -> -157.28 | I60: =-H60 -> 157.28 | J60: =IFERROR(I60/$I$67,0) -> 0.001448753 | L60: A validar | M60: Sim (outro produto) | N60: Divergência de produto: tratativa registrada foi do Clover, não do Autorize | O60: Sem relatório de churn
A61: MARCOS JOSE MELOZZI E OUTROS-I.E.13.576.600-1 | B61: 30010335 | C61: 30001726 | D61: Agrimanager Autorize | E61: Downsell | F61: jun/26 | G61: 1 | H61: =SUMIFS(Base_Tratada!$H:$H,Base_Tratada!$A:$A,$A61,Base_Tratada!$G:$G,$D61) -> -151.45 | I61: =-H61 -> 151.45 | J61: =IFERROR(I61/$I$67,0) -> 0.0013950512 | L61: Não | M61: Sim | N61: Autorize permanece ativo | O61: Contrato ativo
A62: EDIANA EDITH BOERI IE: 126447373 | B62: 30013092 | C62: 30003274 | D62: My Farm ERP | E62: Downsell | F62: mai/26 | G62: 1 | H62: =SUMIFS(Base_Tratada!$H:$H,Base_Tratada!$A:$A,$A62,Base_Tratada!$G:$G,$D62) -> -65.3 | I62: =-H62 -> 65.3 | J62: =IFERROR(I62/$I$67,0) -> 0.0006014978 | L62: Sim | M62: Não | N62: Cliente ativa, inclusive é a cliente que tenta pagar desde Fevereiro sem realizarmos a cobrança. Não localizado tratativas que indiquem essa redução de R$ 65,30 no contrato da cliente. | O62: Sem relatório de churn
A63: BRUNO RODRIGUES CAPPELLESSO | B63: 30011293 | C63: 30002239 | D63: My Farm ERP | E63: Downsell | F63: jan/26 | G63: 1 | H63: =SUMIFS(Base_Tratada!$H:$H,Base_Tratada!$A:$A,$A63,Base_Tratada!$G:$G,$D63) -> -36.051667 | I63: =-H63 -> 36.051667 | J63: =IFERROR(I63/$I$67,0) -> 0.00033208267 | L63: Não | M63: Não | N63: Ajuste financeiro pelo time de contratos | O63: Reajuste financeiro contratual
A64: ADRIANO XAVIER PIVETTA E OUTROS I.E 13.438.585-3 | B64: 30011394 | C64: 30002303 | D64: Agrimanager Autorize | E64: Downsell | F64: mar/26 | G64: 1 | H64: =SUMIFS(Base_Tratada!$H:$H,Base_Tratada!$A:$A,$A64,Base_Tratada!$G:$G,$D64) -> 0 | I64: =-H64 -> 0 | J64: =IFERROR(I64/$I$67,0) -> 0 | L64: Sem impacto (R$ 0,00) | M64: Sem informação | N64: Downsell de Agrimanager Autorize sem variação de MRR. Evento registrado na base de origem, sem reflexo financeiro. | O64: Sem impacto financeiro
A65: LUCAS BOLOGNINI STRACCI | B65: 30016543 | C65: 30001182 | D65: Agrimanager Autorize | E65: Churn | F65: jun/26 | G65: 2 | H65: =SUMIFS(Base_Tratada!$H:$H,Base_Tratada!$A:$A,$A65,Base_Tratada!$G:$G,$D65) -> 0 | I65: =-H65 -> 0 | J65: =IFERROR(I65/$I$67,0) -> 0 | L65: Sem impacto (R$ 0,00) | M65: Sim | N65: Cancelamento de Agrimanager Autorize com cobrança de R$ 131,11 e estorno de igual valor na mesma competência — resultado líquido zero. A perda real do cliente está na linha 34. | O65: Sem impacto financeiro
A66: VALQUIRIA MARCELINO FERREIRA ABREU IE: 13.429.008-9 | B66: 30016155 | C66: 30004756 | D66: Aliare Cloud - PR | E66: Churn | F66: mai/26 | G66: 1 | H66: =SUMIFS(Base_Tratada!$H:$H,Base_Tratada!$A:$A,$A66,Base_Tratada!$G:$G,$D66) -> 0 | I66: =-H66 -> 0 | J66: =IFERROR(I66/$I$67,0) -> 0 | L66: Sem impacto (R$ 0,00) | M66: Sim | N66: Aliare Cloud sem MRR no contrato 30004756, cancelado junto com o Agrimanager ERP (linha 17). Mesmo cliente e mesma competência, produto diferente — não é duplicidade de registro. | O66: Baixa aderência do agm. Sem impacto financeiro.
A67: TOTAL | G67: =SUM(G5:G66) -> 89 | H67: =SUM(H5:H66) -> -108562.33 | I67: =SUM(I5:I66) -> 108562.33 | J67: =SUM(J5:J66) -> 1
A69: ATENÇÃO — leia antes de usar estes números:
A70: 1) A soma da coluna Variação é feita COM SINAL. Existem 8 linhas POSITIVAS dentro de eventos de Churn: são estornos de linhas de desconto/crédito negativas que existiam no faturamento anterior. Somar em módulo inflaria a perda em R$ 20.076,54 (+18,5%) — valor errado.
A71: 2) Cliente + produto que teve evento em mais de um mês foi colapsado em 1 linha (SERIOS AGROPECUARIA e SERRA BONITA SEMENTES). A coluna Competência(s) preserva os meses. Para leitura mensal, use a aba Análises.
A72: 3) 3 linhas têm variação R$ 0,00 (Rentax, Adriano Xavier Pivetta, Valquiria/Aliare Cloud): são eventos registrados sem impacto financeiro no mês.
A73: 4) Fonte: Produtor__Rural_-_Lista_YTD_06-2026.xlsx, aba Planilha1, 13.856 linhas, competências jan a jun/2026. Filtro aplicado: 89 linhas.
A75: 5) Colunas K, L e M foram preenchidas a partir da coluna de observação livre do arquivo "Churn_e_Down_-_Julho_2026.xlsx" (aba Planilha1). O texto original de cada linha está preservado como comentário na célula da coluna M.
A76: 6) Critério de "Procede?": Sim = evento real de churn/downsell. Não = evento não se confirma (contrato ativo, revertido pela CSM, renovação, migração interna ou erro de venda). Sim (ressalva) = evento real, mas com competência divergente (cancelamento originado em 2025). A validar = a observação de julho não permite concluir.
A77: 7) Critério de "Trato por CSM?": Sim = há registro explícito de tratativa do CS. Não = a observação afirma que não passou pelo CS. Sem informação = a observação nada diz sobre o CS. Não localizado = houve busca (HubSpot, Service Desk, e-mail) e nada foi encontrado.
A78: 8) LACUNAS — 2 linhas deste consolidado não existem no arquivo de julho: ADRIANO XAVIER PIVETTA (Agrimanager Autorize, Downsell, mar/26) e VALQUIRIA MARCELINO FERREIRA ABREU (Aliare Cloud - PR, Churn, mai/26). Ambas com variação R$ 0,00 e reclassificadas como "Sem impacto (R$ 0,00)" — ver nota 12.
A79: 9) LACUNAS — 2 linhas existem no arquivo de julho mas com a observação em branco: RODRIGO KONAGESKI (Vistra BI, fev/26) e AGRO 100 (Agrimanager ERP, mar/26). ROGERIO EZEQUIEL FERRARI (Agrimanager Autorize, mar/26) está em julho, também sem observação, e nem consta neste consolidado.
A80: 10) DIVERGÊNCIAS DE BASE — julho totaliza R$ 109.147,10 contra R$ 108.562,33 aqui. A diferença de R$ 584,77 vem de ROGERIO EZEQUIEL FERRARI (R$ 193,33, ausente aqui) e de MARCOS CESAR JORDAO (R$ 798,68 em julho contra R$ 407,24 aqui — diferença de R$ 391,44, correspondente à linha de Ajuste entre mai/26 e jun/26).
A81: 11) Coluna N — categoria raiz do cancelamento, extraída do arquivo "relatorio-churn-2026-08-20.xlsx". Vocabulário controlado de 10 valores para permitir contagem e soma por categoria. A classificação usa o campo "Histórico motivo cancelamento" como árbitro quando o motivo declarado pelo cliente diverge do motivo interno. O detalhe de cada caso está no comentário da célula. "Sem relatório de churn" = o cliente não consta no relatório.
A82: 12) EVENTOS SEM IMPACTO FINANCEIRO — 3 linhas movimentam R$ 0,00 e foram marcadas como "Sem impacto (R$ 0,00)" na coluna K: VALQUIRIA (Aliare Cloud, linha 66), ADRIANO XAVIER PIVETTA (Autorize, linha 64) e LUCAS BOLOGNINI (Autorize, linha 65). Não são duplicidades: a aba segue a regra de 1 linha por cliente x produto, e nos três casos trata-se de um segundo produto do mesmo contrato, sem MRR próprio. Para contagem de eventos de churn/downsell com efeito financeiro, filtrar a coluna K excluindo este valor: 59 eventos, R$ 108.562,33.

Sheet Analises
A1: ANALISES DE CHURN E DOWNSELL — Vertical Produtores Agricolas — YTD jan a jun/2026
A2: Todos os numeros abaixo sao calculados por formula a partir das abas Base_Tratada e Dados_Origem. Nada esta digitado a mao.
A4: 1. RESUMO EXECUTIVO
A5: Indicador | B5: Valor | C5: Leitura
A6: Perda bruta total (Churn + Downsell) | B6: =SUMIFS(Base_Tratada!$H$5:$H$93,Base_Tratada!$F$5:$F$93,"Churn")+SUMIFS(Base_Tratada!$H$5:$H$93,Base_Tratada!$F$5:$F$93,"Downsell") -> -108562.33 | C6: Soma com sinal da coluna Variacao nas 89 linhas filtradas.
A7: dos quais Churn | B7: =SUMIFS(Base_Tratada!$H$5:$H$93,Base_Tratada!$F$5:$F$93,"Churn") -> -54930.404 | C7: 50,6% da perda. Cliente/produto encerrado.
A8: dos quais Downsell | B8: =SUMIFS(Base_Tratada!$H$5:$H$93,Base_Tratada!$F$5:$F$93,"Downsell") -> -53631.922 | C8: 49,4% da perda. Reducao de escopo com o cliente ativo.
A9: Clientes distintos afetados | B9: =SUMPRODUCT((Base_Tratada!$A$5:$A$93<>"")/COUNTIF(Base_Tratada!$A$5:$A$93,Base_Tratada!$A$5:$A$93&"")) -> 58 | C9: 12,0% da base de ~484 clientes ativos foi tocada em 6 meses.
A10: Eventos unicos (cliente x produto x mes) | B10: =SUM(Base_Tratada!$K$5:$K$93) -> 64 | C10: A aba Consolidado tem 62 linhas porque dois pares tiveram evento em 2 meses.
A11: MRR medio mensal da base | B11: =AVERAGE(Dados_Origem!$I$5:$I$10) -> 1325505 | C11: Media das 6 competencias.
A12: Taxa de churn bruta mensal | B12: =-B6/6/B11 -> 0.013650435 | C12: Perda media mensal sobre o MRR medio.
A13: Taxa de churn bruta anualizada | B13: =1-(1-B12)^12 -> 0.15204992 | C13: Perda bruta anualizada da base. Referencia SaaS PME: 10% a 15% ao ano.
A14: NRR estimado no semestre | B14: =(Dados_Origem!$I$5+B6+Dados_Origem!$C$11+Dados_Origem!$D$11)/Dados_Origem!$I$5 -> 0.94506517 | C14: MRR de jan mais perdas, upsell e reajuste. Nao conta novos logos.
A15: Ticket medio jan/26 | B15: =Dados_Origem!$I$5/Dados_Origem!$J$5 -> 2821.0861 | C15: MRR dividido por clientes ativos.
A16: Ticket medio jun/26 | B16: =Dados_Origem!$I$10/Dados_Origem!$J$10 -> 2685.5939 | C16: Queda de 4,8% em 6 meses.
A17: Concentracao: top 3 linhas cliente x produto | B17: =(LARGE(Consolidado!$I$5:$I$66,1)+LARGE(Consolidado!$I$5:$I$66,2)+LARGE(Consolidado!$I$5:$I$66,3))/SUM(Consolidado!$I$5:$I$66) -> 0.33904736 | C17: Por cliente (somando produtos) o top 3 chega a 35,7% e o top 10 a 60,0%.
A19: 2. VALOR DE CHURN E DOWNSELL POR MES
A20: Mes | B20: Churn (R$) | C20: Downsell (R$) | D20: Total (R$) | E20: MRR base do mes | F20: % do MRR | G20: Eventos de Churn | H20: Eventos de Downsell
A21: jan/26 | B21: =SUMIFS(Base_Tratada!$H$5:$H$93,Base_Tratada!$E$5:$E$93,"2026-01",Base_Tratada!$F$5:$F$93,"Churn") -> -5119.17 | C21: =SUMIFS(Base_Tratada!$H$5:$H$93,Base_Tratada!$E$5:$E$93,"2026-01",Base_Tratada!$F$5:$F$93,"Downsell") -> -1693.5217 | D21: =B21+C21 -> -6812.6917 | E21: =Dados_Origem!$I$5 -> 1325910.5 | F21: =-D21/E21 -> 0.0051381235 | G21: =SUMIFS(Base_Tratada!$K$5:$K$93,Base_Tratada!$E$5:$E$93,"2026-01",Base_Tratada!$F$5:$F$93,"Churn") -> 5 | H21: =SUMIFS(Base_Tratada!$K$5:$K$93,Base_Tratada!$E$5:$E$93,"2026-01",Base_Tratada!$F$5:$F$93,"Downsell") -> 2
A22: fev/26 | B22: =SUMIFS(Base_Tratada!$H$5:$H$93,Base_Tratada!$E$5:$E$93,"2026-02",Base_Tratada!$F$5:$F$93,"Churn") -> -13233.29 | C22: =SUMIFS(Base_Tratada!$H$5:$H$93,Base_Tratada!$E$5:$E$93,"2026-02",Base_Tratada!$F$5:$F$93,"Downsell") -> -22881.82 | D22: =B22+C22 -> -36115.11 | E22: =Dados_Origem!$I$6 -> 1320291.6 | F22: =-D22/E22 -> 0.027353889 | G22: =SUMIFS(Base_Tratada!$K$5:$K$93,Base_Tratada!$E$5:$E$93,"2026-02",Base_Tratada!$F$5:$F$93,"Churn") -> 9 | H22: =SUMIFS(Base_Tratada!$K$5:$K$93,Base_Tratada!$E$5:$E$93,"2026-02",Base_Tratada!$F$5:$F$93,"Downsell") -> 8
A23: mar/26 | B23: =SUMIFS(Base_Tratada!$H$5:$H$93,Base_Tratada!$E$5:$E$93,"2026-03",Base_Tratada!$F$5:$F$93,"Churn") -> -4069.8698 | C23: =SUMIFS(Base_Tratada!$H$5:$H$93,Base_Tratada!$E$5:$E$93,"2026-03",Base_Tratada!$F$5:$F$93,"Downsell") -> -561.54 | D23: =B23+C23 -> -4631.4098 | E23: =Dados_Origem!$I$7 -> 1337681.5 | F23: =-D23/E23 -> 0.0034622664 | G23: =SUMIFS(Base_Tratada!$K$5:$K$93,Base_Tratada!$E$5:$E$93,"2026-03",Base_Tratada!$F$5:$F$93,"Churn") -> 4 | H23: =SUMIFS(Base_Tratada!$K$5:$K$93,Base_Tratada!$E$5:$E$93,"2026-03",Base_Tratada!$F$5:$F$93,"Downsell") -> 2
A24: abr/26 | B24: =SUMIFS(Base_Tratada!$H$5:$H$93,Base_Tratada!$E$5:$E$93,"2026-04",Base_Tratada!$F$5:$F$93,"Churn") -> -157.28 | C24: =SUMIFS(Base_Tratada!$H$5:$H$93,Base_Tratada!$E$5:$E$93,"2026-04",Base_Tratada!$F$5:$F$93,"Downsell") -> 0 | D24: =B24+C24 -> -157.28 | E24: =Dados_Origem!$I$8 -> 1340358.8 | F24: =-D24/E24 -> 0.00011734172 | G24: =SUMIFS(Base_Tratada!$K$5:$K$93,Base_Tratada!$E$5:$E$93,"2026-04",Base_Tratada!$F$5:$F$93,"Churn") -> 1 | H24: =SUMIFS(Base_Tratada!$K$5:$K$93,Base_Tratada!$E$5:$E$93,"2026-04",Base_Tratada!$F$5:$F$93,"Downsell") -> 0
A25: mai/26 | B25: =SUMIFS(Base_Tratada!$H$5:$H$93,Base_Tratada!$E$5:$E$93,"2026-05",Base_Tratada!$F$5:$F$93,"Churn") -> -13849.484 | C25: =SUMIFS(Base_Tratada!$H$5:$H$93,Base_Tratada!$E$5:$E$93,"2026-05",Base_Tratada!$F$5:$F$93,"Downsell") -> -12235.12 | D25: =B25+C25 -> -26084.604 | E25: =Dados_Origem!$I$9 -> 1328960.4 | F25: =-D25/E25 -> 0.019627827 | G25: =SUMIFS(Base_Tratada!$K$5:$K$93,Base_Tratada!$E$5:$E$93,"2026-05",Base_Tratada!$F$5:$F$93,"Churn") -> 8 | H25: =SUMIFS(Base_Tratada!$K$5:$K$93,Base_Tratada!$E$5:$E$93,"2026-05",Base_Tratada!$F$5:$F$93,"Downsell") -> 6
A26: jun/26 | B26: =SUMIFS(Base_Tratada!$H$5:$H$93,Base_Tratada!$E$5:$E$93,"2026-06",Base_Tratada!$F$5:$F$93,"Churn") -> -18501.31 | C26: =SUMIFS(Base_Tratada!$H$5:$H$93,Base_Tratada!$E$5:$E$93,"2026-06",Base_Tratada!$F$5:$F$93,"Downsell") -> -16259.92 | D26: =B26+C26 -> -34761.23 | E26: =Dados_Origem!$I$10 -> 1299827.5 | F26: =-D26/E26 -> 0.026742957 | G26: =SUMIFS(Base_Tratada!$K$5:$K$93,Base_Tratada!$E$5:$E$93,"2026-06",Base_Tratada!$F$5:$F$93,"Churn") -> 14 | H26: =SUMIFS(Base_Tratada!$K$5:$K$93,Base_Tratada!$E$5:$E$93,"2026-06",Base_Tratada!$F$5:$F$93,"Downsell") -> 5
A27: TOTAL | B27: =SUM(B21:B26) -> -54930.404 | C27: =SUM(C21:C26) -> -53631.922 | D27: =SUM(D21:D26) -> -108562.33 | E27: =AVERAGE(E21:E26) -> 1325505 | F27: =-D27/E27/6 -> 0.013650435 | G27: =SUM(G21:G26) -> 41 | H27: =SUM(H21:H26) -> 23
A29: 3. QUANTIDADE DE EVENTOS POR MES x PRODUTO (evento = cliente x produto x mes)
A30: 3.1 CHURN — quantidade de eventos
A31: Produto | B31: jan/26 | C31: fev/26 | D31: mar/26 | E31: abr/26 | F31: mai/26 | G31: jun/26 | H31: Total
A32: Agrimanager Algodoeira | B32: =SUMIFS(Base_Tratada!$K$5:$K$93,Base_Tratada!$E$5:$E$93,"2026-01",Base_Tratada!$F$5:$F$93,"Churn",Base_Tratada!$G$5:$G$93,$A32) -> 0 | C32: =SUMIFS(Base_Tratada!$K$5:$K$93,Base_Tratada!$E$5:$E$93,"2026-02",Base_Tratada!$F$5:$F$93,"Churn",Base_Tratada!$G$5:$G$93,$A32) -> 0 | D32: =SUMIFS(Base_Tratada!$K$5:$K$93,Base_Tratada!$E$5:$E$93,"2026-03",Base_Tratada!$F$5:$F$93,"Churn",Base_Tratada!$G$5:$G$93,$A32) -> 1 | E32: =SUMIFS(Base_Tratada!$K$5:$K$93,Base_Tratada!$E$5:$E$93,"2026-04",Base_Tratada!$F$5:$F$93,"Churn",Base_Tratada!$G$5:$G$93,$A32) -> 0 | F32: =SUMIFS(Base_Tratada!$K$5:$K$93,Base_Tratada!$E$5:$E$93,"2026-05",Base_Tratada!$F$5:$F$93,"Churn",Base_Tratada!$G$5:$G$93,$A32) -> 0 | G32: =SUMIFS(Base_Tratada!$K$5:$K$93,Base_Tratada!$E$5:$E$93,"2026-06",Base_Tratada!$F$5:$F$93,"Churn",Base_Tratada!$G$5:$G$93,$A32) -> 0 | H32: =SUM(B32:G32) -> 1
A33: Agrimanager Autorize | B33: =SUMIFS(Base_Tratada!$K$5:$K$93,Base_Tratada!$E$5:$E$93,"2026-01",Base_Tratada!$F$5:$F$93,"Churn",Base_Tratada!$G$5:$G$93,$A33) -> 0 | C33: =SUMIFS(Base_Tratada!$K$5:$K$93,Base_Tratada!$E$5:$E$93,"2026-02",Base_Tratada!$F$5:$F$93,"Churn",Base_Tratada!$G$5:$G$93,$A33) -> 0 | D33: =SUMIFS(Base_Tratada!$K$5:$K$93,Base_Tratada!$E$5:$E$93,"2026-03",Base_Tratada!$F$5:$F$93,"Churn",Base_Tratada!$G$5:$G$93,$A33) -> 0 | E33: =SUMIFS(Base_Tratada!$K$5:$K$93,Base_Tratada!$E$5:$E$93,"2026-04",Base_Tratada!$F$5:$F$93,"Churn",Base_Tratada!$G$5:$G$93,$A33) -> 1 | F33: =SUMIFS(Base_Tratada!$K$5:$K$93,Base_Tratada!$E$5:$E$93,"2026-05",Base_Tratada!$F$5:$F$93,"Churn",Base_Tratada!$G$5:$G$93,$A33) -> 0 | G33: =SUMIFS(Base_Tratada!$K$5:$K$93,Base_Tratada!$E$5:$E$93,"2026-06",Base_Tratada!$F$5:$F$93,"Churn",Base_Tratada!$G$5:$G$93,$A33) -> 1 | H33: =SUM(B33:G33) -> 2
A34: Agrimanager ERP | B34: =SUMIFS(Base_Tratada!$K$5:$K$93,Base_Tratada!$E$5:$E$93,"2026-01",Base_Tratada!$F$5:$F$93,"Churn",Base_Tratada!$G$5:$G$93,$A34) -> 0 | C34: =SUMIFS(Base_Tratada!$K$5:$K$93,Base_Tratada!$E$5:$E$93,"2026-02",Base_Tratada!$F$5:$F$93,"Churn",Base_Tratada!$G$5:$G$93,$A34) -> 2 | D34: =SUMIFS(Base_Tratada!$K$5:$K$93,Base_Tratada!$E$5:$E$93,"2026-03",Base_Tratada!$F$5:$F$93,"Churn",Base_Tratada!$G$5:$G$93,$A34) -> 1 | E34: =SUMIFS(Base_Tratada!$K$5:$K$93,Base_Tratada!$E$5:$E$93,"2026-04",Base_Tratada!$F$5:$F$93,"Churn",Base_Tratada!$G$5:$G$93,$A34) -> 0 | F34: =SUMIFS(Base_Tratada!$K$5:$K$93,Base_Tratada!$E$5:$E$93,"2026-05",Base_Tratada!$F$5:$F$93,"Churn",Base_Tratada!$G$5:$G$93,$A34) -> 2 | G34: =SUMIFS(Base_Tratada!$K$5:$K$93,Base_Tratada!$E$5:$E$93,"2026-06",Base_Tratada!$F$5:$F$93,"Churn",Base_Tratada!$G$5:$G$93,$A34) -> 4 | H34: =SUM(B34:G34) -> 9
A35: Aliare Cloud - PR | B35: =SUMIFS(Base_Tratada!$K$5:$K$93,Base_Tratada!$E$5:$E$93,"2026-01",Base_Tratada!$F$5:$F$93,"Churn",Base_Tratada!$G$5:$G$93,$A35) -> 1 | C35: =SUMIFS(Base_Tratada!$K$5:$K$93,Base_Tratada!$E$5:$E$93,"2026-02",Base_Tratada!$F$5:$F$93,"Churn",Base_Tratada!$G$5:$G$93,$A35) -> 0 | D35: =SUMIFS(Base_Tratada!$K$5:$K$93,Base_Tratada!$E$5:$E$93,"2026-03",Base_Tratada!$F$5:$F$93,"Churn",Base_Tratada!$G$5:$G$93,$A35) -> 0 | E35: =SUMIFS(Base_Tratada!$K$5:$K$93,Base_Tratada!$E$5:$E$93,"2026-04",Base_Tratada!$F$5:$F$93,"Churn",Base_Tratada!$G$5:$G$93,$A35) -> 0 | F35: =SUMIFS(Base_Tratada!$K$5:$K$93,Base_Tratada!$E$5:$E$93,"2026-05",Base_Tratada!$F$5:$F$93,"Churn",Base_Tratada!$G$5:$G$93,$A35) -> 2 | G35: =SUMIFS(Base_Tratada!$K$5:$K$93,Base_Tratada!$E$5:$E$93,"2026-06",Base_Tratada!$F$5:$F$93,"Churn",Base_Tratada!$G$5:$G$93,$A35) -> 1 | H35: =SUM(B35:G35) -> 4
A36: My Farm ERP | B36: =SUMIFS(Base_Tratada!$K$5:$K$93,Base_Tratada!$E$5:$E$93,"2026-01",Base_Tratada!$F$5:$F$93,"Churn",Base_Tratada!$G$5:$G$93,$A36) -> 4 | C36: =SUMIFS(Base_Tratada!$K$5:$K$93,Base_Tratada!$E$5:$E$93,"2026-02",Base_Tratada!$F$5:$F$93,"Churn",Base_Tratada!$G$5:$G$93,$A36) -> 4 | D36: =SUMIFS(Base_Tratada!$K$5:$K$93,Base_Tratada!$E$5:$E$93,"2026-03",Base_Tratada!$F$5:$F$93,"Churn",Base_Tratada!$G$5:$G$93,$A36) -> 1 | E36: =SUMIFS(Base_Tratada!$K$5:$K$93,Base_Tratada!$E$5:$E$93,"2026-04",Base_Tratada!$F$5:$F$93,"Churn",Base_Tratada!$G$5:$G$93,$A36) -> 0 | F36: =SUMIFS(Base_Tratada!$K$5:$K$93,Base_Tratada!$E$5:$E$93,"2026-05",Base_Tratada!$F$5:$F$93,"Churn",Base_Tratada!$G$5:$G$93,$A36) -> 4 | G36: =SUMIFS(Base_Tratada!$K$5:$K$93,Base_Tratada!$E$5:$E$93,"2026-06",Base_Tratada!$F$5:$F$93,"Churn",Base_Tratada!$G$5:$G$93,$A36) -> 8 | H36: =SUM(B36:G36) -> 21
A37: Vistra BI - PR | B37: =SUMIFS(Base_Tratada!$K$5:$K$93,Base_Tratada!$E$5:$E$93,"2026-01",Base_Tratada!$F$5:$F$93,"Churn",Base_Tratada!$G$5:$G$93,$A37) -> 0 | C37: =SUMIFS(Base_Tratada!$K$5:$K$93,Base_Tratada!$E$5:$E$93,"2026-02",Base_Tratada!$F$5:$F$93,"Churn",Base_Tratada!$G$5:$G$93,$A37) -> 3 | D37: =SUMIFS(Base_Tratada!$K$5:$K$93,Base_Tratada!$E$5:$E$93,"2026-03",Base_Tratada!$F$5:$F$93,"Churn",Base_Tratada!$G$5:$G$93,$A37) -> 1 | E37: =SUMIFS(Base_Tratada!$K$5:$K$93,Base_Tratada!$E$5:$E$93,"2026-04",Base_Tratada!$F$5:$F$93,"Churn",Base_Tratada!$G$5:$G$93,$A37) -> 0 | F37: =SUMIFS(Base_Tratada!$K$5:$K$93,Base_Tratada!$E$5:$E$93,"2026-05",Base_Tratada!$F$5:$F$93,"Churn",Base_Tratada!$G$5:$G$93,$A37) -> 0 | G37: =SUMIFS(Base_Tratada!$K$5:$K$93,Base_Tratada!$E$5:$E$93,"2026-06",Base_Tratada!$F$5:$F$93,"Churn",Base_Tratada!$G$5:$G$93,$A37) -> 0 | H37: =SUM(B37:G37) -> 4
A38: TOTAL | B38: =SUM(B32:B37) -> 5 | C38: =SUM(C32:C37) -> 9 | D38: =SUM(D32:D37) -> 4 | E38: =SUM(E32:E37) -> 1 | F38: =SUM(F32:F37) -> 8 | G38: =SUM(G32:G37) -> 14 | H38: =SUM(H32:H37) -> 41
A39: 3.2 DOWNSELL — quantidade de eventos
A40: Produto | B40: jan/26 | C40: fev/26 | D40: mar/26 | E40: abr/26 | F40: mai/26 | G40: jun/26 | H40: Total
A41: Agrimanager Algodoeira | B41: =SUMIFS(Base_Tratada!$K$5:$K$93,Base_Tratada!$E$5:$E$93,"2026-01",Base_Tratada!$F$5:$F$93,"Downsell",Base_Tratada!$G$5:$G$93,$A41) -> 0 | C41: =SUMIFS(Base_Tratada!$K$5:$K$93,Base_Tratada!$E$5:$E$93,"2026-02",Base_Tratada!$F$5:$F$93,"Downsell",Base_Tratada!$G$5:$G$93,$A41) -> 0 | D41: =SUMIFS(Base_Tratada!$K$5:$K$93,Base_Tratada!$E$5:$E$93,"2026-03",Base_Tratada!$F$5:$F$93,"Downsell",Base_Tratada!$G$5:$G$93,$A41) -> 0 | E41: =SUMIFS(Base_Tratada!$K$5:$K$93,Base_Tratada!$E$5:$E$93,"2026-04",Base_Tratada!$F$5:$F$93,"Downsell",Base_Tratada!$G$5:$G$93,$A41) -> 0 | F41: =SUMIFS(Base_Tratada!$K$5:$K$93,Base_Tratada!$E$5:$E$93,"2026-05",Base_Tratada!$F$5:$F$93,"Downsell",Base_Tratada!$G$5:$G$93,$A41) -> 0 | G41: =SUMIFS(Base_Tratada!$K$5:$K$93,Base_Tratada!$E$5:$E$93,"2026-06",Base_Tratada!$F$5:$F$93,"Downsell",Base_Tratada!$G$5:$G$93,$A41) -> 0 | H41: =SUM(B41:G41) -> 0
A42: Agrimanager Autorize | B42: =SUMIFS(Base_Tratada!$K$5:$K$93,Base_Tratada!$E$5:$E$93,"2026-01",Base_Tratada!$F$5:$F$93,"Downsell",Base_Tratada!$G$5:$G$93,$A42) -> 0 | C42: =SUMIFS(Base_Tratada!$K$5:$K$93,Base_Tratada!$E$5:$E$93,"2026-02",Base_Tratada!$F$5:$F$93,"Downsell",Base_Tratada!$G$5:$G$93,$A42) -> 0 | D42: =SUMIFS(Base_Tratada!$K$5:$K$93,Base_Tratada!$E$5:$E$93,"2026-03",Base_Tratada!$F$5:$F$93,"Downsell",Base_Tratada!$G$5:$G$93,$A42) -> 1 | E42: =SUMIFS(Base_Tratada!$K$5:$K$93,Base_Tratada!$E$5:$E$93,"2026-04",Base_Tratada!$F$5:$F$93,"Downsell",Base_Tratada!$G$5:$G$93,$A42) -> 0 | F42: =SUMIFS(Base_Tratada!$K$5:$K$93,Base_Tratada!$E$5:$E$93,"2026-05",Base_Tratada!$F$5:$F$93,"Downsell",Base_Tratada!$G$5:$G$93,$A42) -> 0 | G42: =SUMIFS(Base_Tratada!$K$5:$K$93,Base_Tratada!$E$5:$E$93,"2026-06",Base_Tratada!$F$5:$F$93,"Downsell",Base_Tratada!$G$5:$G$93,$A42) -> 2 | H42: =SUM(B42:G42) -> 3
A43: Agrimanager ERP | B43: =SUMIFS(Base_Tratada!$K$5:$K$93,Base_Tratada!$E$5:$E$93,"2026-01",Base_Tratada!$F$5:$F$93,"Downsell",Base_Tratada!$G$5:$G$93,$A43) -> 1 | C43: =SUMIFS(Base_Tratada!$K$5:$K$93,Base_Tratada!$E$5:$E$93,"2026-02",Base_Tratada!$F$5:$F$93,"Downsell",Base_Tratada!$G$5:$G$93,$A43) -> 3 | D43: =SUMIFS(Base_Tratada!$K$5:$K$93,Base_Tratada!$E$5:$E$93,"2026-03",Base_Tratada!$F$5:$F$93,"Downsell",Base_Tratada!$G$5:$G$93,$A43) -> 1 | E43: =SUMIFS(Base_Tratada!$K$5:$K$93,Base_Tratada!$E$5:$E$93,"2026-04",Base_Tratada!$F$5:$F$93,"Downsell",Base_Tratada!$G$5:$G$93,$A43) -> 0 | F43: =SUMIFS(Base_Tratada!$K$5:$K$93,Base_Tratada!$E$5:$E$93,"2026-05",Base_Tratada!$F$5:$F$93,"Downsell",Base_Tratada!$G$5:$G$93,$A43) -> 3 | G43: =SUMIFS(Base_Tratada!$K$5:$K$93,Base_Tratada!$E$5:$E$93,"2026-06",Base_Tratada!$F$5:$F$93,"Downsell",Base_Tratada!$G$5:$G$93,$A43) -> 3 | H43: =SUM(B43:G43) -> 11
A44: Aliare Cloud - PR | B44: =SUMIFS(Base_Tratada!$K$5:$K$93,Base_Tratada!$E$5:$E$93,"2026-01",Base_Tratada!$F$5:$F$93,"Downsell",Base_Tratada!$G$5:$G$93,$A44) -> 0 | C44: =SUMIFS(Base_Tratada!$K$5:$K$93,Base_Tratada!$E$5:$E$93,"2026-02",Base_Tratada!$F$5:$F$93,"Downsell",Base_Tratada!$G$5:$G$93,$A44) -> 0 | D44: =SUMIFS(Base_Tratada!$K$5:$K$93,Base_Tratada!$E$5:$E$93,"2026-03",Base_Tratada!$F$5:$F$93,"Downsell",Base_Tratada!$G$5:$G$93,$A44) -> 0 | E44: =SUMIFS(Base_Tratada!$K$5:$K$93,Base_Tratada!$E$5:$E$93,"2026-04",Base_Tratada!$F$5:$F$93,"Downsell",Base_Tratada!$G$5:$G$93,$A44) -> 0 | F44: =SUMIFS(Base_Tratada!$K$5:$K$93,Base_Tratada!$E$5:$E$93,"2026-05",Base_Tratada!$F$5:$F$93,"Downsell",Base_Tratada!$G$5:$G$93,$A44) -> 0 | G44: =SUMIFS(Base_Tratada!$K$5:$K$93,Base_Tratada!$E$5:$E$93,"2026-06",Base_Tratada!$F$5:$F$93,"Downsell",Base_Tratada!$G$5:$G$93,$A44) -> 0 | H44: =SUM(B44:G44) -> 0
A45: My Farm ERP | B45: =SUMIFS(Base_Tratada!$K$5:$K$93,Base_Tratada!$E$5:$E$93,"2026-01",Base_Tratada!$F$5:$F$93,"Downsell",Base_Tratada!$G$5:$G$93,$A45) -> 1 | C45: =SUMIFS(Base_Tratada!$K$5:$K$93,Base_Tratada!$E$5:$E$93,"2026-02",Base_Tratada!$F$5:$F$93,"Downsell",Base_Tratada!$G$5:$G$93,$A45) -> 0 | D45: =SUMIFS(Base_Tratada!$K$5:$K$93,Base_Tratada!$E$5:$E$93,"2026-03",Base_Tratada!$F$5:$F$93,"Downsell",Base_Tratada!$G$5:$G$93,$A45) -> 0 | E45: =SUMIFS(Base_Tratada!$K$5:$K$93,Base_Tratada!$E$5:$E$93,"2026-04",Base_Tratada!$F$5:$F$93,"Downsell",Base_Tratada!$G$5:$G$93,$A45) -> 0 | F45: =SUMIFS(Base_Tratada!$K$5:$K$93,Base_Tratada!$E$5:$E$93,"2026-05",Base_Tratada!$F$5:$F$93,"Downsell",Base_Tratada!$G$5:$G$93,$A45) -> 3 | G45: =SUMIFS(Base_Tratada!$K$5:$K$93,Base_Tratada!$E$5:$E$93,"2026-06",Base_Tratada!$F$5:$F$93,"Downsell",Base_Tratada!$G$5:$G$93,$A45) -> 0 | H45: =SUM(B45:G45) -> 4
A46: Vistra BI - PR | B46: =SUMIFS(Base_Tratada!$K$5:$K$93,Base_Tratada!$E$5:$E$93,"2026-01",Base_Tratada!$F$5:$F$93,"Downsell",Base_Tratada!$G$5:$G$93,$A46) -> 0 | C46: =SUMIFS(Base_Tratada!$K$5:$K$93,Base_Tratada!$E$5:$E$93,"2026-02",Base_Tratada!$F$5:$F$93,"Downsell",Base_Tratada!$G$5:$G$93,$A46) -> 5 | D46: =SUMIFS(Base_Tratada!$K$5:$K$93,Base_Tratada!$E$5:$E$93,"2026-03",Base_Tratada!$F$5:$F$93,"Downsell",Base_Tratada!$G$5:$G$93,$A46) -> 0 | E46: =SUMIFS(Base_Tratada!$K$5:$K$93,Base_Tratada!$E$5:$E$93,"2026-04",Base_Tratada!$F$5:$F$93,"Downsell",Base_Tratada!$G$5:$G$93,$A46) -> 0 | F46: =SUMIFS(Base_Tratada!$K$5:$K$93,Base_Tratada!$E$5:$E$93,"2026-05",Base_Tratada!$F$5:$F$93,"Downsell",Base_Tratada!$G$5:$G$93,$A46) -> 0 | G46: =SUMIFS(Base_Tratada!$K$5:$K$93,Base_Tratada!$E$5:$E$93,"2026-06",Base_Tratada!$F$5:$F$93,"Downsell",Base_Tratada!$G$5:$G$93,$A46) -> 0 | H46: =SUM(B46:G46) -> 5
A47: TOTAL | B47: =SUM(B41:B46) -> 2 | C47: =SUM(C41:C46) -> 8 | D47: =SUM(D41:D46) -> 2 | E47: =SUM(E41:E46) -> 0 | F47: =SUM(F41:F46) -> 6 | G47: =SUM(G41:G46) -> 5 | H47: =SUM(H41:H46) -> 23
A49: 4. VALOR PERDIDO (R$) POR MES x PRODUTO — Churn + Downsell somados
A50: Produto | B50: jan/26 | C50: fev/26 | D50: mar/26 | E50: abr/26 | F50: mai/26 | G50: jun/26 | H50: Total YTD | I50: MRR medio mensal | J50: Taxa mensal
A51: Agrimanager Algodoeira | B51: =SUMIFS(Base_Tratada!$H$5:$H$93,Base_Tratada!$E$5:$E$93,"2026-01",Base_Tratada!$G$5:$G$93,$A51) -> 0 | C51: =SUMIFS(Base_Tratada!$H$5:$H$93,Base_Tratada!$E$5:$E$93,"2026-02",Base_Tratada!$G$5:$G$93,$A51) -> 0 | D51: =SUMIFS(Base_Tratada!$H$5:$H$93,Base_Tratada!$E$5:$E$93,"2026-03",Base_Tratada!$G$5:$G$93,$A51) -> -1926.9898 | E51: =SUMIFS(Base_Tratada!$H$5:$H$93,Base_Tratada!$E$5:$E$93,"2026-04",Base_Tratada!$G$5:$G$93,$A51) -> 0 | F51: =SUMIFS(Base_Tratada!$H$5:$H$93,Base_Tratada!$E$5:$E$93,"2026-05",Base_Tratada!$G$5:$G$93,$A51) -> 0 | G51: =SUMIFS(Base_Tratada!$H$5:$H$93,Base_Tratada!$E$5:$E$93,"2026-06",Base_Tratada!$G$5:$G$93,$A51) -> 0 | H51: =SUM(B51:G51) -> -1926.9898 | I51: 8729.68 | J51: =IFERROR(-H51/6/I51,0) -> 0.036790005
A52: Agrimanager Autorize | B52: =SUMIFS(Base_Tratada!$H$5:$H$93,Base_Tratada!$E$5:$E$93,"2026-01",Base_Tratada!$G$5:$G$93,$A52) -> 0 | C52: =SUMIFS(Base_Tratada!$H$5:$H$93,Base_Tratada!$E$5:$E$93,"2026-02",Base_Tratada!$G$5:$G$93,$A52) -> 0 | D52: =SUMIFS(Base_Tratada!$H$5:$H$93,Base_Tratada!$E$5:$E$93,"2026-03",Base_Tratada!$G$5:$G$93,$A52) -> 0 | E52: =SUMIFS(Base_Tratada!$H$5:$H$93,Base_Tratada!$E$5:$E$93,"2026-04",Base_Tratada!$G$5:$G$93,$A52) -> -157.28 | F52: =SUMIFS(Base_Tratada!$H$5:$H$93,Base_Tratada!$E$5:$E$93,"2026-05",Base_Tratada!$G$5:$G$93,$A52) -> 0 | G52: =SUMIFS(Base_Tratada!$H$5:$H$93,Base_Tratada!$E$5:$E$93,"2026-06",Base_Tratada!$G$5:$G$93,$A52) -> -558.69 | H52: =SUM(B52:G52) -> -715.97 | I52: 3654.65 | J52: =IFERROR(-H52/6/I52,0) -> 0.032651097
A53: Agrimanager ERP | B53: =SUMIFS(Base_Tratada!$H$5:$H$93,Base_Tratada!$E$5:$E$93,"2026-01",Base_Tratada!$G$5:$G$93,$A53) -> -1657.47 | C53: =SUMIFS(Base_Tratada!$H$5:$H$93,Base_Tratada!$E$5:$E$93,"2026-02",Base_Tratada!$G$5:$G$93,$A53) -> -24097.77 | D53: =SUMIFS(Base_Tratada!$H$5:$H$93,Base_Tratada!$E$5:$E$93,"2026-03",Base_Tratada!$G$5:$G$93,$A53) -> -1936.7 | E53: =SUMIFS(Base_Tratada!$H$5:$H$93,Base_Tratada!$E$5:$E$93,"2026-04",Base_Tratada!$G$5:$G$93,$A53) -> 0 | F53: =SUMIFS(Base_Tratada!$H$5:$H$93,Base_Tratada!$E$5:$E$93,"2026-05",Base_Tratada!$G$5:$G$93,$A53) -> -13280.21 | G53: =SUMIFS(Base_Tratada!$H$5:$H$93,Base_Tratada!$E$5:$E$93,"2026-06",Base_Tratada!$G$5:$G$93,$A53) -> -25146.31 | H53: =SUM(B53:G53) -> -66118.46 | I53: 1024373.7 | J53: =IFERROR(-H53/6/I53,0) -> 0.010757543
A54: Aliare Cloud - PR | B54: =SUMIFS(Base_Tratada!$H$5:$H$93,Base_Tratada!$E$5:$E$93,"2026-01",Base_Tratada!$G$5:$G$93,$A54) -> -1875.06 | C54: =SUMIFS(Base_Tratada!$H$5:$H$93,Base_Tratada!$E$5:$E$93,"2026-02",Base_Tratada!$G$5:$G$93,$A54) -> 0 | D54: =SUMIFS(Base_Tratada!$H$5:$H$93,Base_Tratada!$E$5:$E$93,"2026-03",Base_Tratada!$G$5:$G$93,$A54) -> 0 | E54: =SUMIFS(Base_Tratada!$H$5:$H$93,Base_Tratada!$E$5:$E$93,"2026-04",Base_Tratada!$G$5:$G$93,$A54) -> 0 | F54: =SUMIFS(Base_Tratada!$H$5:$H$93,Base_Tratada!$E$5:$E$93,"2026-05",Base_Tratada!$G$5:$G$93,$A54) -> -3046.65 | G54: =SUMIFS(Base_Tratada!$H$5:$H$93,Base_Tratada!$E$5:$E$93,"2026-06",Base_Tratada!$G$5:$G$93,$A54) -> -1650.36 | H54: =SUM(B54:G54) -> -6572.07 | I54: 65030.85 | J54: =IFERROR(-H54/6/I54,0) -> 0.016843467
A55: My Farm ERP | B55: =SUMIFS(Base_Tratada!$H$5:$H$93,Base_Tratada!$E$5:$E$93,"2026-01",Base_Tratada!$G$5:$G$93,$A55) -> -3280.1617 | C55: =SUMIFS(Base_Tratada!$H$5:$H$93,Base_Tratada!$E$5:$E$93,"2026-02",Base_Tratada!$G$5:$G$93,$A55) -> -2995.67 | D55: =SUMIFS(Base_Tratada!$H$5:$H$93,Base_Tratada!$E$5:$E$93,"2026-03",Base_Tratada!$G$5:$G$93,$A55) -> -320 | E55: =SUMIFS(Base_Tratada!$H$5:$H$93,Base_Tratada!$E$5:$E$93,"2026-04",Base_Tratada!$G$5:$G$93,$A55) -> 0 | F55: =SUMIFS(Base_Tratada!$H$5:$H$93,Base_Tratada!$E$5:$E$93,"2026-05",Base_Tratada!$G$5:$G$93,$A55) -> -9757.7442 | G55: =SUMIFS(Base_Tratada!$H$5:$H$93,Base_Tratada!$E$5:$E$93,"2026-06",Base_Tratada!$G$5:$G$93,$A55) -> -7405.87 | H55: =SUM(B55:G55) -> -23759.446 | I55: 211773.11 | J55: =IFERROR(-H55/6/I55,0) -> 0.018698822
A56: Vistra BI - PR | B56: =SUMIFS(Base_Tratada!$H$5:$H$93,Base_Tratada!$E$5:$E$93,"2026-01",Base_Tratada!$G$5:$G$93,$A56) -> 0 | C56: =SUMIFS(Base_Tratada!$H$5:$H$93,Base_Tratada!$E$5:$E$93,"2026-02",Base_Tratada!$G$5:$G$93,$A56) -> -9021.67 | D56: =SUMIFS(Base_Tratada!$H$5:$H$93,Base_Tratada!$E$5:$E$93,"2026-03",Base_Tratada!$G$5:$G$93,$A56) -> -447.72 | E56: =SUMIFS(Base_Tratada!$H$5:$H$93,Base_Tratada!$E$5:$E$93,"2026-04",Base_Tratada!$G$5:$G$93,$A56) -> 0 | F56: =SUMIFS(Base_Tratada!$H$5:$H$93,Base_Tratada!$E$5:$E$93,"2026-05",Base_Tratada!$G$5:$G$93,$A56) -> 0 | G56: =SUMIFS(Base_Tratada!$H$5:$H$93,Base_Tratada!$E$5:$E$93,"2026-06",Base_Tratada!$G$5:$G$93,$A56) -> 0 | H56: =SUM(B56:G56) -> -9469.39 | I56: 11943.07 | J56: =IFERROR(-H56/6/I56,0) -> 0.13214623
A57: TOTAL | B57: =SUM(B51:B56) -> -6812.6917 | C57: =SUM(C51:C56) -> -36115.11 | D57: =SUM(D51:D56) -> -4631.4098 | E57: =SUM(E51:E56) -> -157.28 | F57: =SUM(F51:F56) -> -26084.604 | G57: =SUM(G51:G56) -> -34761.23 | H57: =SUM(H51:H56) -> -108562.33 | I57: =SUM(I51:I56) -> 1325505 | J57: =-H57/6/I57 -> 0.013650436
I58: MRR medio mensal por produto: input extraido do arquivo original (media das 6 competencias).
A60: 5. RANKING DE PERDA — onde a receita realmente saiu (top 15 de 62 linhas)
A61: # | B61: Cliente | C61: Produto | D61: Status | E61: Perda (R$) | F61: % acumulado
A62: 1 | B62: SERIOS AGROPECUARIA LTDA | C62: Agrimanager ERP | D62: Downsell | E62: =SUMIFS(Base_Tratada!$H$5:$H$93,Base_Tratada!$A$5:$A$93,$B62,Base_Tratada!$G$5:$G$93,$C62)*-1 -> 16573.14 | F62: =SUM($E$62:$E62)/SUM(Consolidado!$I$5:$I$66) -> 0.15266014
A63: 2 | B63: CLODOVEU FRANCIOSI IE 133535746 | C63: Agrimanager ERP | D63: Downsell | E63: =SUMIFS(Base_Tratada!$H$5:$H$93,Base_Tratada!$A$5:$A$93,$B63,Base_Tratada!$G$5:$G$93,$C63)*-1 -> 13701.65 | F63: =SUM($E$62:$E63)/SUM(Consolidado!$I$5:$I$66) -> 0.27887013
A64: 3 | B64: SERRA BONITA SEMENTES S.A. | C64: Agrimanager ERP | D64: Downsell | E64: =SUMIFS(Base_Tratada!$H$5:$H$93,Base_Tratada!$A$5:$A$93,$B64,Base_Tratada!$G$5:$G$93,$C64)*-1 -> 6532.98 | F64: =SUM($E$62:$E64)/SUM(Consolidado!$I$5:$I$66) -> 0.33904736
A65: 4 | B65: LEONARDO LUIZ OSS | C65: My Farm ERP | D65: Downsell | E65: =SUMIFS(Base_Tratada!$H$5:$H$93,Base_Tratada!$A$5:$A$93,$B65,Base_Tratada!$G$5:$G$93,$C65)*-1 -> 4195.79 | F65: =SUM($E$62:$E65)/SUM(Consolidado!$I$5:$I$66) -> 0.37769604
A66: 5 | B66: 3SB PRODUTOS AGRICOLAS S.A. | C66: Agrimanager ERP | D66: Churn | E66: =SUMIFS(Base_Tratada!$H$5:$H$93,Base_Tratada!$A$5:$A$93,$B66,Base_Tratada!$G$5:$G$93,$C66)*-1 -> 4170.46 | F66: =SUM($E$62:$E66)/SUM(Consolidado!$I$5:$I$66) -> 0.41611139
A67: 6 | B67: BRUNO SANCHES TORO | C67: Agrimanager ERP | D67: Churn | E67: =SUMIFS(Base_Tratada!$H$5:$H$93,Base_Tratada!$A$5:$A$93,$B67,Base_Tratada!$G$5:$G$93,$C67)*-1 -> 4010.69 | F67: =SUM($E$62:$E67)/SUM(Consolidado!$I$5:$I$66) -> 0.45305505
A68: 7 | B68: CLAUDIO AUGUSTO DINIZ - I.E. 13.235.367-9 | C68: Agrimanager ERP | D68: Churn | E68: =SUMIFS(Base_Tratada!$H$5:$H$93,Base_Tratada!$A$5:$A$93,$B68,Base_Tratada!$G$5:$G$93,$C68)*-1 -> 3408.4 | F68: =SUM($E$62:$E68)/SUM(Consolidado!$I$5:$I$66) -> 0.48445084
A69: 8 | B69: RICARDO SILVA ROCHA IE: 11.196.197-1 | C69: Agrimanager ERP | D69: Churn | E69: =SUMIFS(Base_Tratada!$H$5:$H$93,Base_Tratada!$A$5:$A$93,$B69,Base_Tratada!$G$5:$G$93,$C69)*-1 -> 3117.15 | F69: =SUM($E$62:$E69)/SUM(Consolidado!$I$5:$I$66) -> 0.51316384
A70: 9 | B70: NATALINO BIGOLIN IE:13.606.182-6 | C70: Aliare Cloud - PR | D70: Churn | E70: =SUMIFS(Base_Tratada!$H$5:$H$93,Base_Tratada!$A$5:$A$93,$B70,Base_Tratada!$G$5:$G$93,$C70)*-1 -> 3046.65 | F70: =SUM($E$62:$E70)/SUM(Consolidado!$I$5:$I$66) -> 0.54122744
A71: 10 | B71: LUIS HENRIQUE PAZINI E OUTRO - IE - 133440532 | C71: My Farm ERP | D71: Churn | E71: =SUMIFS(Base_Tratada!$H$5:$H$93,Base_Tratada!$A$5:$A$93,$B71,Base_Tratada!$G$5:$G$93,$C71)*-1 -> 2775.55 | F71: =SUM($E$62:$E71)/SUM(Consolidado!$I$5:$I$66) -> 0.56679386
A72: 11 | B72: ZORZETTO ASSES. E CONSULTORIA AGRONOMICA LTDA. | C72: Agrimanager ERP | D72: Churn | E72: =SUMIFS(Base_Tratada!$H$5:$H$93,Base_Tratada!$A$5:$A$93,$B72,Base_Tratada!$G$5:$G$93,$C72)*-1 -> 2243.46 | F72: =SUM($E$62:$E72)/SUM(Consolidado!$I$5:$I$66) -> 0.58745904
A73: 12 | B73: OCTAVIANO RAYMUNDO CAMARGO SILVA IE:212.059.354.118 | C73: Agrimanager ERP | D73: Churn | E73: =SUMIFS(Base_Tratada!$H$5:$H$93,Base_Tratada!$A$5:$A$93,$B73,Base_Tratada!$G$5:$G$93,$C73)*-1 -> 2150.61 | F73: =SUM($E$62:$E73)/SUM(Consolidado!$I$5:$I$66) -> 0.60726895
... A76: 15 | B76: SEMENTES TRES PINHEIROS SEEDS LTDA | C76: Aliare Cloud - PR | D76: Churn | E76: =SUMIFS(Base_Tratada!$H$5:$H$93,Base_Tratada!$A$5:$A$93,$B76,Base_Tratada!$G$5:$G$93,$C76)*-1 -> 1875.06 | F76: =SUM($E$62:$E76)/SUM(Consolidado!$I$5:$I$66) -> 0.66173407
A79: 6. MOVIMENTACAO COMPLETA DO MRR — o churn no contexto do saldo do mes
A80: Mes | B80: Novos logos | C80: Upsell | D80: Reajuste | E80: Ajustes | F80: Downsell | G80: Churn | H80: Saldo liquido | I80: MRR base
A81: jan/26 | B81: =Dados_Origem!$B$5 -> 4815.29 | C81: =Dados_Origem!$C$5 -> 3301.64 | D81: =Dados_Origem!$D$5 -> 225.325 | E81: =Dados_Origem!$E$5 -> -4985.29 | F81: =Dados_Origem!$G$5 -> -1693.5217 | G81: =Dados_Origem!$H$5 -> -5119.17 | H81: =SUM(B81:G81) -> -3455.7267 | I81: =Dados_Origem!$I$5 -> 1325910.5
A82: fev/26 | B82: =Dados_Origem!$B$6 -> 13662.66 | C82: =Dados_Origem!$C$6 -> 10796.99 | D82: =Dados_Origem!$D$6 -> 1889.3692 | E82: =Dados_Origem!$E$6 -> 0 | F82: =Dados_Origem!$G$6 -> -22881.82 | G82: =Dados_Origem!$H$6 -> -13233.29 | H82: =SUM(B82:G82) -> -9766.0908 | I82: =Dados_Origem!$I$6 -> 1320291.6
A83: mar/26 | B83: =Dados_Origem!$B$7 -> 14361.57 | C83: =Dados_Origem!$C$7 -> 7665.44 | D83: =Dados_Origem!$D$7 -> 813.3025 | E83: =Dados_Origem!$E$7 -> -818.96 | F83: =Dados_Origem!$G$7 -> -561.54 | G83: =Dados_Origem!$H$7 -> -4069.8698 | H83: =SUM(B83:G83) -> 17389.943 | I83: =Dados_Origem!$I$7 -> 1337681.5
A84: abr/26 | B84: =Dados_Origem!$B$8 -> 2279.96 | C84: =Dados_Origem!$C$8 -> 837.9 | D84: =Dados_Origem!$D$8 -> -339.75833 | E84: =Dados_Origem!$E$8 -> 56.41 | F84: =Dados_Origem!$G$8 -> 0 | G84: =Dados_Origem!$H$8 -> -157.28 | H84: =SUM(B84:G84) -> 2677.2317 | I84: =Dados_Origem!$I$8 -> 1340358.8
A85: mai/26 | B85: =Dados_Origem!$B$9 -> 6849.4 | C85: =Dados_Origem!$C$9 -> 504.4 | D85: =Dados_Origem!$D$9 -> 6940.9252 | E85: =Dados_Origem!$E$9 -> 391.44 | F85: =Dados_Origem!$G$9 -> -12235.12 | G85: =Dados_Origem!$H$9 -> -13849.484 | H85: =SUM(B85:G85) -> -11398.439 | I85: =Dados_Origem!$I$9 -> 1328960.4
A86: jun/26 | B86: =Dados_Origem!$B$10 -> 2931.66 | C86: =Dados_Origem!$C$10 -> 3088.12 | D86: =Dados_Origem!$D$10 -> 0 | E86: =Dados_Origem!$E$10 -> -391.44 | F86: =Dados_Origem!$G$10 -> -16259.92 | G86: =Dados_Origem!$H$10 -> -18501.31 | H86: =SUM(B86:G86) -> -29132.89 | I86: =Dados_Origem!$I$10 -> 1299827.5
A87: TOTAL YTD | B87: =SUM(B81:B86) -> 44900.54 | C87: =SUM(C81:C86) -> 26194.49 | D87: =SUM(D81:D86) -> 9529.1635 | E87: =SUM(E81:E86) -> -5747.84 | F87: =SUM(F81:F86) -> -53631.922 | G87: =SUM(G81:G86) -> -54930.404 | H87: =SUM(H81:H86) -> -33685.972 | I87: =Dados_Origem!$I$10 -> 1299827.5
A88: Saldo liquido YTD de -R$ 33.686 contra uma queda observada de MRR de -R$ 26.083 (jan vs jun). A diferenca de R$ 7.603 vem das linhas com valor vazio em jan/26 e mai/26, tratadas como zero. Ver ressalva 4.
A90: 7. O QUE OS NUMEROS DIZEM — leitura critica
A91: A base cresce em logos e encolhe em receita.
A92: De jan a jun a carteira foi de 470 para 484 clientes (+3,0%) e o MRR caiu de R$ 1.325.910 para R$ 1.299.827 (-2,0%). O ticket medio caiu de R$ 2.821 para R$ 2.686 (-4,8%). Vender mais logos nao esta compensando a erosao da base instalada.
A94: Metade da perda nao e cancelamento, e reducao de escopo.
A95: Downsell responde por R$ 53.632 contra R$ 54.930 de churn. Downsell e um evento em conta VIVA, com CSM ativo. Se metade da perda acontece dentro de contas que voce ainda atende, o problema esta em gestao de valor no pos-venda, nao em retencao de contrato.
A97: Dos 25 clientes com CHURN registrado ate maio, 7 continuaram faturando depois.
A98: Ou seja, 28% do que esta rotulado como churn e na verdade cancelamento de MODULO dentro de conta ativa. Isso significa que sua taxa de churn de logo esta superestimada e sua taxa de downsell esta subestimada. Nos 16 downsells ate maio, 100% seguiram faturando, o que confirma que a classificacao tem ruido.
A100: Vistra BI nao tem churn cronico. Tem UM evento em fevereiro.
A101: A taxa mensal de 13,2% engana. Dos R$ 9.469 perdidos no produto, R$ 9.022 (95%) sairam em fev/26, em 8 contas de uma vez (5 downsells e 3 churns), e depois de mar/26 o produto nao teve mais nenhum evento. Isso nao e erosao organica, e uma decisao unica: mudanca de contrato, fim de bundle promocional ou reprecificacao. Descobrir o que aconteceu em fevereiro vale mais do que qualquer plano de retencao para o produto.
A103: O churn de VOLUME e o churn de VALOR estao em produtos diferentes.
A104: My Farm ERP concentra 21 dos 41 eventos de churn (51%) mas so 21,9% do valor perdido. Agrimanager ERP tem 9 eventos de churn e 60,9% do valor. Sao dois problemas distintos: no My Farm voce perde muitos clientes pequenos, o que pede processo e automacao; no Agrimanager voce perde poucas contas grandes, o que pede plano de conta nominal. Tratar os dois com o mesmo playbook nao vai funcionar.
... A125: 7) Fonte unica: Produtor__Rural_-_Lista_YTD_06-2026.xlsx, aba Planilha1, 13.856 linhas, vertical PRODUTORES AGRICOLAS, competencias 01/2026 a 06/2026. Nenhum valor foi digitado a mao nas abas de calculo; tudo referencia Base_Tratada ou Dados_Origem.

Sheet Base_Tratada
A1: BASE TRATADA — 89 linhas originais com STATUS = Churn ou Downsell
A2: Linhas exatamente como na origem, sem alteração de valores. Colunas E, J e K são derivadas para permitir as fórmulas das outras abas.
A4: Cliente | B4: Cód. Cliente | C4: Contrato | D4: Competência | E4: Mês | F4: Status | G4: Produto | H4: Variação (R$) | I4: Valor faturado (R$) | J4: Tipo de linha | K4: Evento único
A5: 3SB PRODUTOS AGRICOLAS S.A. | B5: 30007727 | C5: 30000677 | D5: 46054 | E5: 2026-02 | F5: Churn | G5: Agrimanager ERP | H5: -3861.97 | I5: 0 | J5: Perda de receita (-) | K5: 1
A6: 3SB PRODUTOS AGRICOLAS S.A. | B6: 30007727 | C6: 30000677 | D6: 46054 | E6: 2026-02 | F6: Churn | G6: Agrimanager ERP | H6: -386.1 | I6: 0 | J6: Perda de receita (-) | K6: 0
A7: 3SB PRODUTOS AGRICOLAS S.A. | B7: 30007727 | C7: 30000677 | D7: 46054 | E7: 2026-02 | F7: Churn | G7: Agrimanager ERP | H7: 4248.07 | I7: 0 | J7: Estorno de linha negativa (+) | K7: 0
A8: 3SB PRODUTOS AGRICOLAS S.A. | B8: 30007727 | C8: 30000677 | D8: 46054 | E8: 2026-02 | F8: Churn | G8: Agrimanager ERP | H8: -3849.64 | I8: 0 | J8: Perda de receita (-) | K8: 0
A9: 3SB PRODUTOS AGRICOLAS S.A. | B9: 30007727 | C9: 30000677 | D9: 46054 | E9: 2026-02 | F9: Churn | G9: Agrimanager ERP | H9: -320.82 | I9: 0 | J9: Perda de receita (-) | K9: 0
A10: ACASSIO TELES DE CASTRO | B10: 30017239 | C10: 30005439 | D10: 46023 | E10: 2026-01 | F10: Churn | G10: My Farm ERP | H10: -1200 | I10: 0 | J10: Perda de receita (-) | K10: 1
A11: ADEMIR JOSE COMPARIM IE-28.523.221-5 | B11: 30012242 | C11: 30002927 | D11: 46023 | E11: 2026-01 | F11: Churn | G11: My Farm ERP | H11: -840.51 | I11: 0 | J11: Perda de receita (-) | K11: 1
A12: ADRIANO XAVIER PIVETTA E OUTROS I.E 13.438.585-3 | B12: 30011394 | C12: 30002303 | D12: 46082 | E12: 2026-03 | F12: Downsell | G12: Agrimanager Autorize | H12: 0 | I12: 0 | J12: Evento sem impacto financeiro | K12: 1
A13: AGRO 100 COMERCIO DE PRODUTOS AGRICOLAS LTDA - EM RECUPERACAO | B13: 10001146 | C13: 10000135 | D13: 46082 | E13: 2026-03 | F13: Churn | G13: Agrimanager ERP | H13: -1375.16 | I13: 0 | J13: Perda de receita (-) | K13: 1
A14: ANDRE LUIZ COELHO GUILHERME | B14: 30016960 | C14: 30005242 | D14: 46143 | E14: 2026-05 | F14: Churn | G14: My Farm ERP | H14: -1073.29 | I14: 0 | J14: Perda de receita (-) | K14: 1
A15: ANTONIO MIGUEL WEBER DOS SANTOS I.E. 13.294.586-0 | B15: 30010080 | C15: 30001646 | D15: 46113 | E15: 2026-04 | F15: Churn | G15: Agrimanager Autorize | H15: -157.28 | I15: -157.28 | J15: Perda de receita (-) | K15: 1
A16: BRUNO RODRIGUES CAPPELLESSO | B16: 30011293 | C16: 30002239 | D16: 46023 | E16: 2026-01 | F16: Downsell | G16: My Farm ERP | H16: -36.051667 | I16: -36.051667 | J16: Perda de receita (-) | K16: 1
A17: BRUNO SANCHES TORO | B17: 30015024 | C17: 30004006 | D17: 46174 | E17: 2026-06 | F17: Churn | G17: Agrimanager ERP | H17: -2326.2 | J17: Perda de receita (-) | K17: 1
A18: BRUNO SANCHES TORO | B18: 30015024 | C18: 30004006 | D18: 46174 | E18: 2026-06 | F18: Churn | G18: Agrimanager ERP | H18: -932.27 | J18: Perda de receita (-) | K18: 0
A19: BRUNO SANCHES TORO | B19: 30015024 | C19: 30004006 | D19: 46174 | E19: 2026-06 | F19: Churn | G19: Agrimanager ERP | H19: -752.22 | J19: Perda de receita (-) | K19: 0
A20: BRUNO SANCHES TORO | B20: 30015024 | C20: 30004006 | D20: 46174 | E20: 2026-06 | F20: Churn | G20: Aliare Cloud - PR | H20: -887.6 | J20: Perda de receita (-) | K20: 1
A21: BRUNO SANCHES TORO | B21: 30015024 | C21: 30004006 | D21: 46174 | E21: 2026-06 | F21: Churn | G21: Aliare Cloud - PR | H21: -355.72 | J21: Perda de receita (-) | K21: 0
A22: BRUNO SANCHES TORO | B22: 30015024 | C22: 30004006 | D22: 46174 | E22: 2026-06 | F22: Churn | G22: Aliare Cloud - PR | H22: -407.04 | J22: Perda de receita (-) | K22: 0
A23: CAPIVARY AGROPASTORIL LTDA | B23: 30010978 | C23: 30002051 | D23: 46023 | E23: 2026-01 | F23: Downsell | G23: Agrimanager ERP | H23: -1657.47 | I23: -1657.47 | J23: Perda de receita (-) | K23: 1
A24: CARLOS ALBERTO MORESCO | B24: 20000027 | C24: 30001343 | D24: 46054 | E24: 2026-02 | F24: Churn | G24: Vistra BI - PR | H24: -1655.56 | I24: -1655.56 | J24: Perda de receita (-) | K24: 1
A25: CARLOS FERNANDO DA SILVEIRA BUENO | B25: 30017285 | C25: 30005453 | D25: 46023 | E25: 2026-01 | F25: Churn | G25: My Farm ERP | H25: -583.33 | I25: 0 | J25: Perda de receita (-) | K25: 1
A26: CLAUDIO AUGUSTO DINIZ - I.E. 13.235.367-9 | B26: 30009772 | C26: 30001556 | D26: 46143 | E26: 2026-05 | F26: Churn | G26: Agrimanager ERP | H26: -1950.8 | I26: 0 | J26: Perda de receita (-) | K26: 1
A27: CLAUDIO AUGUSTO DINIZ - I.E. 13.235.367-9 | B27: 30009772 | C27: 30001556 | D27: 46143 | E27: 2026-05 | F27: Churn | G27: Agrimanager ERP | H27: -1457.6 | I27: 0 | J27: Perda de receita (-) | K27: 0
A28: CLODOVEU FRANCIOSI IE 133535746 | B28: 30006916 | C28: 30001424 | D28: 46082 | E28: 2026-03 | F28: Churn | G28: Agrimanager Algodoeira | H28: -1926.9898 | I28: -1926.9898 | J28: Perda de receita (-) | K28: 1
A29: CLODOVEU FRANCIOSI IE 133535746 | B29: 30006916 | C29: 30001424 | D29: 46174 | E29: 2026-06 | F29: Downsell | G29: Agrimanager ERP | H29: -13701.65 | I29: -13701.65 | J29: Perda de receita (-) | K29: 1
A30: CORNELIO ADRIANO SANDERS E OUTROS | B30: 20000043 | C30: 30000717 | D30: 46174 | E30: 2026-06 | F30: Downsell | G30: Agrimanager ERP | H30: -514.72 | I30: -514.72 | J30: Perda de receita (-) | K30: 1
A31: DONA EMA AGROPECUARIA E INDUSTRIAL LTDA | B31: 30013184 | C31: 30000891 | D31: 46054 | E31: 2026-02 | F31: Downsell | G31: Agrimanager ERP | H31: -884.96 | I31: -884.96 | J31: Perda de receita (-) | K31: 1
A32: EDIANA EDITH BOERI IE: 126447373 | B32: 30013092 | C32: 30003274 | D32: 46143 | E32: 2026-05 | F32: Downsell | G32: My Farm ERP | H32: -65.3 | I32: -65.3 | J32: Perda de receita (-) | K32: 1
A33: EDUARDO ZORZI - I.E. 13.322.258-6 | B33: 30010781 | C33: 30001903 | D33: 46054 | E33: 2026-02 | F33: Downsell | G33: Vistra BI - PR | H33: -865.52 | I33: -865.52 | J33: Perda de receita (-) | K33: 1
A34: ELIANA GASPARINI TESTA IE 111876893 | B34: 30018091 | C34: 30005902 | D34: 46054 | E34: 2026-02 | F34: Churn | G34: My Farm ERP | H34: -480 | I34: 0 | J34: Perda de receita (-) | K34: 1
A35: EVANDRO VILELA BARROS IE 11.331.859-6 | B35: 30014925 | C35: 30003941 | D35: 46143 | E35: 2026-05 | F35: Churn | G35: My Farm ERP | H35: -827.41 | I35: 0 | J35: Perda de receita (-) | K35: 1
A36: FABIANO BERGOLI ZAMBERLAN IE:120114927-1 | B36: 30017436 | C36: 30005541 | D36: 46174 | E36: 2026-06 | F36: Churn | G36: My Farm ERP | H36: -963.73 | J36: Perda de receita (-) | K36: 1
A37: FERNANDO CAVALHEIRO MACHADO I.E.29.439.136-3 | B37: 30008736 | C37: 30005481 | D37: 46054 | E37: 2026-02 | F37: Downsell | G37: Vistra BI - PR | H37: -1352.1 | I37: -1352.1 | J37: Perda de receita (-) | K37: 1
A38: FLAVIO FAEDO IE 11.508.239-5 | B38: 130 | C38: 30002569 | D38: 46054 | E38: 2026-02 | F38: Churn | G38: My Farm ERP | H38: -1201.82 | I38: 0 | J38: Perda de receita (-) | K38: 1
A39: GERALDO AUGUSTO MARTINS TEIXEIRA IE 37260520019 | B39: 30015743 | C39: 30005853 | D39: 46082 | E39: 2026-03 | F39: Churn | G39: My Farm ERP | H39: -320 | I39: 0 | J39: Perda de receita (-) | K39: 1
A40: GUILHERME DE ARAUJO PREDIGER | C40: 30007398 | D40: 46174 | E40: 2026-06 | F40: Churn | G40: My Farm ERP | H40: -621.26 | J40: Perda de receita (-) | K40: 1
A41: JORGE AUGUSTO BARRAGANA BRAZEIRO | B41: 30016118 | C41: 30004747 | D41: 46082 | E41: 2026-03 | F41: Churn | G41: Vistra BI - PR | H41: -447.72 | I41: 0 | J41: Perda de receita (-) | K41: 1
A42: JORGE AUGUSTO BARRAGANA BRAZEIRO | B42: 30016118 | C42: 30004747 | D42: 46082 | E42: 2026-03 | F42: Churn | G42: Vistra BI - PR | H42: 447.72 | I42: 0 | J42: Estorno de linha negativa (+) | K42: 0
A43: JORGE AUGUSTO BARRAGANA BRAZEIRO | B43: 30016118 | C43: 30004747 | D43: 46082 | E43: 2026-03 | F43: Churn | G43: Vistra BI - PR | H43: -447.72 | I43: 0 | J43: Perda de receita (-) | K43: 0
A44: LEANDRO CAIAFFA ORCAY | B44: 30016337 | C44: 30004869 | D44: 46143 | E44: 2026-05 | F44: Downsell | G44: My Farm ERP | H44: -113.26 | I44: -113.26 | J44: Perda de receita (-) | K44: 1
A45: LEANDRO CAIAFFA ORCAY | B45: 30016337 | C45: 30004869 | D45: 46143 | E45: 2026-05 | F45: Downsell | G45: My Farm ERP | H45: -99.77 | I45: -99.77 | J45: Perda de receita (-) | K45: 0
A46: LEINNER LIMA BORGES IE 11.468.592-4 | B46: 30012511 | C46: 30003044 | D46: 46054 | E46: 2026-02 | F46: Churn | G46: My Farm ERP | H46: -302.91 | I46: 0 | J46: Perda de receita (-) | K46: 1
A47: LEONARDO LUIZ OSS | B47: 30016958 | C47: 30005248 | D47: 46143 | E47: 2026-05 | F47: Downsell | G47: My Farm ERP | H47: -4195.79 | I47: -4195.79 | J47: Perda de receita (-) | K47: 1
A48: LUCAS BOLOGNINI STRACCI | B48: 30016543 | C48: 30001182 | D48: 46174 | E48: 2026-06 | F48: Churn | G48: Agrimanager Autorize | H48: -131.11 | J48: Perda de receita (-) | K48: 1
A49: LUCAS BOLOGNINI STRACCI | B49: 30016543 | C49: 30001182 | D49: 46174 | E49: 2026-06 | F49: Churn | G49: Agrimanager Autorize | H49: 131.11 | J49: Estorno de linha negativa (+) | K49: 0
A50: LUCAS BOLOGNINI STRACCI | B50: 30016543 | C50: 30001182 | D50: 46174 | E50: 2026-06 | F50: Churn | G50: Agrimanager ERP | H50: -4466.62 | J50: Perda de receita (-) | K50: 1
A51: LUCAS BOLOGNINI STRACCI | B51: 30016543 | C51: 30001182 | D51: 46174 | E51: 2026-06 | F51: Churn | G51: Agrimanager ERP | H51: -610.74 | J51: Perda de receita (-) | K51: 0
A52: LUCAS BOLOGNINI STRACCI | B52: 30016543 | C52: 30001182 | D52: 46174 | E52: 2026-06 | F52: Churn | G52: Agrimanager ERP | H52: 556.62 | J52: Estorno de linha negativa (+) | K52: 0
A53: LUCAS BOLOGNINI STRACCI | B53: 30016543 | C53: 30001182 | D53: 46174 | E53: 2026-06 | F53: Churn | G53: Agrimanager ERP | H53: 464.76 | J53: Estorno de linha negativa (+) | K53: 0
A54: LUCAS BOLOGNINI STRACCI | B54: 30016543 | C54: 30001182 | D54: 46174 | E54: 2026-06 | F54: Churn | G54: Agrimanager ERP | H54: -251.07 | J54: Perda de receita (-) | K54: 0
A55: LUCAS BOLOGNINI STRACCI | B55: 30016543 | C55: 30001182 | D55: 46174 | E55: 2026-06 | F55: Churn | G55: Agrimanager ERP | H55: -267.92 | J55: Perda de receita (-) | K55: 0
A56: LUCAS BOLOGNINI STRACCI | B56: 30016543 | C56: 30001182 | D56: 46174 | E56: 2026-06 | F56: Churn | G56: Agrimanager ERP | H56: -273.65 | J56: Perda de receita (-) | K56: 0
A57: LUCAS BOLOGNINI STRACCI | B57: 30016543 | C57: 30001182 | D57: 46174 | E57: 2026-06 | F57: Churn | G57: Agrimanager ERP | H57: 2551.66 | J57: Estorno de linha negativa (+) | K57: 0
A58: LUCAS BOLOGNINI STRACCI | B58: 30016543 | C58: 30001182 | D58: 46174 | E58: 2026-06 | F58: Churn | G58: Agrimanager ERP | H58: 1256.64 | J58: Estorno de linha negativa (+) | K58: 0
A59: LUIS HENRIQUE PAZINI E OUTRO - IE - 133440532 | B59: 30018439 | C59: 30006041 | D59: 46143 | E59: 2026-05 | F59: Churn | G59: My Farm ERP | H59: -2775.55 | I59: 0 | J59: Perda de receita (-) | K59: 1
A60: MARCELO ANDRE KONAGESKI | B60: 30008217 | C60: 30001240 | D60: 46143 | E60: 2026-05 | F60: Downsell | G60: Agrimanager ERP | H60: -580.08 | I60: -580.08 | J60: Perda de receita (-) | K60: 1
A61: MARCONDES AGROPECUARIA LTDA | B61: 30010824 | C61: 30001946 | D61: 46054 | E61: 2026-02 | F61: Downsell | G61: Vistra BI - PR | H61: -1865.58 | I61: -1865.58 | J61: Perda de receita (-) | K61: 1
A62: MARCOS CESAR JORDAO | B62: 30004467 | C62: 30000770 | D62: 46174 | E62: 2026-06 | F62: Downsell | G62: Agrimanager Autorize | H62: -407.24 | I62: -407.24 | J62: Perda de receita (-) | K62: 1
A63: MARCOS JOSE MELOZZI E OUTROS-I.E.13.576.600-1 | B63: 30010335 | C63: 30001726 | D63: 46174 | E63: 2026-06 | F63: Downsell | G63: Agrimanager Autorize | H63: -151.45 | I63: -151.45 | J63: Perda de receita (-) | K63: 1
A64: MARIO PINTO DA SILVA | B64: 30020666 | C64: 30007174 | D64: 46174 | E64: 2026-06 | F64: Churn | G64: My Farm ERP | H64: -1327.99 | J64: Perda de receita (-) | K64: 1
A65: MATEUS EDUARDO GONCALVES VIANA | B65: 30005462 | C65: 30000900 | D65: 46082 | E65: 2026-03 | F65: Downsell | G65: Agrimanager ERP | H65: -561.54 | I65: -561.54 | J65: Perda de receita (-) | K65: 1
A66: MBB AGRO LTDA | B66: 30016791 | C66: 30005763 | D66: 46054 | E66: 2026-02 | F66: Churn | G66: Vistra BI - PR | H66: -517.19 | I66: -517.19 | J66: Perda de receita (-) | K66: 1
A67: NATALINO BIGOLIN IE:13.606.182-6 | B67: 30006687 | C67: 30004170 | D67: 46143 | E67: 2026-05 | F67: Churn | G67: Aliare Cloud - PR | H67: -3046.65 | I67: 0 | J67: Perda de receita (-) | K67: 1
A68: OCTAVIANO RAYMUNDO CAMARGO SILVA IE:212.059.354.118 | B68: 30016194 | C68: 30004772 | D68: 46174 | E68: 2026-06 | F68: Churn | G68: Agrimanager ERP | H68: -2150.61 | J68: Perda de receita (-) | K68: 1
A69: OSVALDO HANISCH - I.E. 057.547.903 | B69: 10002290 | C69: 30001671 | D69: 46174 | E69: 2026-06 | F69: Downsell | G69: Agrimanager ERP | H69: -1484.86 | I69: -1484.86 | J69: Perda de receita (-) | K69: 1
A70: PAULO EMILIO PALUDO - IE 13.345.834-2 | B70: 30014318 | C70: 30003760 | D70: 46143 | E70: 2026-05 | F70: Churn | G70: My Farm ERP | H70: -607.37417 | I70: 0 | J70: Perda de receita (-) | K70: 1
A71: PAULO RICARDO SANTIN | B71: 30017209 | C71: 30005426 | D71: 46174 | E71: 2026-06 | F71: Churn | G71: My Farm ERP | H71: -937.62 | J71: Perda de receita (-) | K71: 1
A72: PEDRO ALCEU BACH | B72: 30019380 | C72: 30006286 | D72: 46174 | E72: 2026-06 | F72: Churn | G72: My Farm ERP | H72: -1070 | J72: Perda de receita (-) | K72: 1
A73: RENTAX AGROSOLUCOES E SERVICOS ADMINISTRATIVOS LTDA | B73: 30016676 | C73: 30005063 | D73: 46023 | E73: 2026-01 | F73: Churn | G73: My Farm ERP | H73: 0 | I73: 0 | J73: Evento sem impacto financeiro | K73: 1
A74: RENTAX AGROSOLUCOES E SERVICOS ADMINISTRATIVOS LTDA | B74: 30016676 | C74: 30005063 | D74: 46023 | E74: 2026-01 | F74: Churn | G74: My Farm ERP | H74: -620.27 | I74: 0 | J74: Perda de receita (-) | K74: 0
A75: RICARDO SILVA ROCHA IE: 11.196.197-1 | B75: 30013024 | C75: 30003254 | D75: 46054 | E75: 2026-02 | F75: Churn | G75: Agrimanager ERP | H75: -3498.84 | I75: 0 | J75: Perda de receita (-) | K75: 1
A76: RICARDO SILVA ROCHA IE: 11.196.197-1 | B76: 30013024 | C76: 30003254 | D76: 46054 | E76: 2026-02 | F76: Churn | G76: Agrimanager ERP | H76: 381.69 | I76: 0 | J76: Estorno de linha negativa (+) | K76: 0
A77: RODRIGO KONAGESKI I.E.13.252.476-7 | B77: 30011301 | C77: 30002242 | D77: 46054 | E77: 2026-02 | F77: Churn | G77: Vistra BI - PR | H77: -777.26 | I77: 0 | J77: Perda de receita (-) | K77: 1
A78: ROQUE CASSOL | B78: 30017104 | C78: 30005345 | D78: 46054 | E78: 2026-02 | F78: Churn | G78: My Farm ERP | H78: -1010.94 | I78: 0 | J78: Perda de receita (-) | K78: 1
A79: S EPP AGRICOLA LTDA | B79: 30015247 | C79: 30001307 | D79: 46054 | E79: 2026-02 | F79: Downsell | G79: Vistra BI - PR | H79: -1178.13 | I79: -1178.13 | J79: Perda de receita (-) | K79: 1
A80: SEMENTES TRES PINHEIROS SEEDS LTDA | B80: 30010348 | C80: 30004593 | D80: 46023 | E80: 2026-01 | F80: Churn | G80: Aliare Cloud - PR | H80: -1875.06 | I80: 0 | J80: Perda de receita (-) | K80: 1
A81: SERIOS AGROPECUARIA LTDA | B81: 30008363 | C81: 30001083 | D81: 46054 | E81: 2026-02 | F81: Downsell | G81: Agrimanager ERP | H81: -1037.7 | I81: -1037.7 | J81: Perda de receita (-) | K81: 1
A82: SERIOS AGROPECUARIA LTDA | B82: 30008363 | C82: 30001083 | D82: 46054 | E82: 2026-02 | F82: Downsell | G82: Agrimanager ERP | H82: -14561.04 | I82: -14561.04 | J82: Perda de receita (-) | K82: 0
A83: SERIOS AGROPECUARIA LTDA | B83: 30008363 | C83: 30001083 | D83: 46143 | E83: 2026-05 | F83: Downsell | G83: Agrimanager ERP | H83: -974.4 | I83: -974.4 | J83: Perda de receita (-) | K83: 1
A84: SERRA BONITA SEMENTES S.A. | B84: 30005436 | C84: 30000899 | D84: 46054 | E84: 2026-02 | F84: Downsell | G84: Agrimanager ERP | H84: -326.46 | I84: -326.46 | J84: Perda de receita (-) | K84: 1
... A86: TANIA POTRICH DE ROCCO E OUTROS IE 13.234.919-1 | B86: 30017565 | C86: 30005685 | D86: 46054 | E86: 2026-02 | F86: Downsell | G86: Vistra BI - PR | H86: -810.33 | I86: -810.33 | J86: Perda de receita (-) | K86: 1
A87: THIAGO DE ALMEIDA | B87: 30011397 | C87: 30002281 | D87: 46174 | E87: 2026-06 | F87: Churn | G87: My Farm ERP | H87: -1067.58 | J87: Perda de receita (-) | K87: 1
A88: VALDIR FREIER IE 00132823500 | B88: 30011963 | C88: 30002645 | D88: 46174 | E88: 2026-06 | F88: Churn | G88: My Farm ERP | H88: -772.9 | J88: Perda de receita (-) | K88: 1
A89: VALQUIRIA MARCELINO FERREIRA ABREU IE: 13.429.008-9 | B89: 30016155 | C89: 30004756 | D89: 46143 | E89: 2026-05 | F89: Churn | G89: Agrimanager ERP | H89: -2110.81 | I89: 0 | J89: Perda de receita (-) | K89: 1
A90: VALQUIRIA MARCELINO FERREIRA ABREU IE: 13.429.008-9 | B90: 30016155 | C90: 30004756 | D90: 46143 | E90: 2026-05 | F90: Churn | G90: Aliare Cloud - PR | H90: 0 | I90: 0 | J90: Evento sem impacto financeiro | K90: 1
A91: WAGNER EDUARDO BALDIN PEREIRA | B91: 30017869 | C91: 30005764 | D91: 46174 | E91: 2026-06 | F91: Churn | G91: My Farm ERP | H91: -644.79 | J91: Perda de receita (-) | K91: 1
A92: ZORZETTO ASSES. E CONSULTORIA AGRONOMICA LTDA. | B92: 30010916 | C92: 30002254 | D92: 46174 | E92: 2026-06 | F92: Churn | G92: Agrimanager ERP | H92: -1223.46 | J92: Perda de receita (-) | K92: 1
A93: ZORZETTO ASSES. E CONSULTORIA AGRONOMICA LTDA. | B93: 30010916 | C93: 30002254 | D93: 46174 | E93: 2026-06 | F93: Churn | G93: Agrimanager ERP | H93: -1020 | J93: Perda de receita (-) | K93: 0

Sheet Dados_Origem
A1: DADOS DE ORIGEM — movimentação completa do MRR e base faturada
A2: Valores em AZUL são inputs extraídos direto do arquivo original (soma da coluna Variacao por competência x STATUS, e soma da coluna valor por competência). Não são calculados aqui.
A4: Mês | B4: NewMRR | C4: Upsell | D4: Reajuste | E4: Ajustes | F4: Sem alteração | G4: Downsell | H4: Churn | I4: MRR base faturado | J4: Clientes na base
A5: jan/26 | B5: 4815.29 | C5: 3301.64 | D5: 225.325 | E5: -4985.29 | F5: 0.18166667 | G5: -1693.5217 | H5: -5119.17 | I5: 1325910.5 | J5: 470
A6: fev/26 | B6: 13662.66 | C6: 10796.99 | D6: 1889.3692 | E6: 0 | F6: 0.16 | G6: -22881.82 | H6: -13233.29 | I6: 1320291.6 | J6: 479
A7: mar/26 | B7: 14361.57 | C7: 7665.44 | D7: 813.3025 | E7: -818.96 | F7: -2.5579538e-13 | G7: -561.54 | H7: -4069.8698 | I7: 1337681.5 | J7: 486
A8: abr/26 | B8: 2279.96 | C8: 837.9 | D8: -339.75833 | E8: 56.41 | F8: 0.02 | G8: 0 | H8: -157.28 | I8: 1340358.8 | J8: 484
A9: mai/26 | B9: 6849.4 | C9: 504.4 | D9: 6940.9252 | E9: 391.44 | F9: 0 | G9: -12235.12 | H9: -13849.484 | I9: 1328960.4 | J9: 487
A10: jun/26 | B10: 2931.66 | C10: 3088.12 | D10: 0 | E10: -391.44 | F10: 0 | G10: -16259.92 | H10: -18501.31 | I10: 1299827.5 | J10: 484
A11: TOTAL YTD | B11: =SUM(B5:B10) -> 44900.54 | C11: =SUM(C5:C10) -> 26194.49 | D11: =SUM(D5:D10) -> 9529.1635 | E11: =SUM(E5:E10) -> -5747.84 | F11: =SUM(F5:F10) -> 0.36166667 | G11: =SUM(G5:G10) -> -53631.922 | H11: =SUM(H5:H10) -> -54930.404 | I11: =SUM(I5:I10) -> 7953030.2
A12: Fonte: Produtor__Rural_-_Lista_YTD_06-2026.xlsx (aba Planilha1). MRR base = soma da coluna "valor" na competência; linhas com valor vazio contam como zero (jan/26 tem 493 linhas vazias, mai/26 tem 276 — ver Notas).
