Workbook

Sheet Resumo
A1: Análise de Churn
A2: Janeiro a junho de 2026. Churn confirmado, downsell e indicadores da base.
A4: Indicador | B4: Valor | C4: Base de cálculo
A5: Perda por churn | B5: =SUM(Churn!F2:F40) -> 89646.72 | C5: Soma da aba Churn
A6: Eventos de churn | B6: =COUNTA(Churn!A2:A40) -> 39 | C6: Linhas da aba Churn (cliente x produto)
A7: Clientes com churn | B7: =SUMPRODUCT(1/COUNTIF(Churn!A2:A40,Churn!A2:A40)) -> 37 | C7: Clientes distintos na aba Churn
A8: Perda por downsell | B8: =SUM(Downsell!F2:F10) -> 9365.8 | C8: Soma da aba Downsell
A9: Eventos de downsell | B9: =COUNTA(Downsell!A2:A10) -> 9 | C9: Linhas da aba Downsell
A10: Clientes com downsell | B10: =SUMPRODUCT(1/COUNTIF(Downsell!A2:A10,Downsell!A2:A10)) -> 9 | C10: Clientes distintos na aba Downsell
A11: Churn mais downsell | B11: =B5+B8 -> 99012.52 | C11: Soma dos dois
A12: Taxa de churn anualizada | B12: ='Mês a mês'!F10 -> 0.13526425 | C12: Perda do semestre sobre o MRR médio, vezes 2 (aba Mês a mês)
A13: Referência de mercado (SaaS de médio porte) | B13: entre 10% e 15% ao ano | C13: Referência usada na aba Mês a mês
A14: Logo churn anualizado | B14: =B7/'Movimentação MRR'!J9*2 -> 0.15363322 | C14: Clientes com churn sobre a base média de clientes, vezes 2
A15: Concentração nos 10 maiores clientes | B15: =SUMPRODUCT(LARGE('Por cliente'!B2:B38,{1,2,3,4,5,6,7,8,9,10}))/B5 -> 0.69373358 | C15: Dez maiores clientes por perda (aba Por cliente) sobre a perda por churn
A16: Ticket médio em janeiro | B16: ='Movimentação MRR'!I2/'Movimentação MRR'!J2 -> 2821.0861 | C16: MRR base sobre clientes na base
A17: Ticket médio em junho | B17: ='Movimentação MRR'!I7/'Movimentação MRR'!J7 -> 2685.5939 | C17: MRR base sobre clientes na base
A18: Queda no ticket médio | B18: =1-B17/B16 -> 0.048028366 | C18: Janeiro contra junho
A19: MRR base em janeiro | B19: ='Movimentação MRR'!I2 -> 1325910.5 | C19: Aba Movimentação MRR
A20: MRR base em junho | B20: ='Movimentação MRR'!I7 -> 1299827.5 | C20: Aba Movimentação MRR
A21: Queda no MRR da base | B21: =1-B20/B19 -> 0.019671764 | C21: Janeiro contra junho
A22: Clientes na base em janeiro | B22: ='Movimentação MRR'!J2 -> 470 | C22: Aba Movimentação MRR
A23: Clientes na base em junho | B23: ='Movimentação MRR'!J7 -> 484 | C23: Aba Movimentação MRR
A25: Fonte: planilha de origem (Churn Tratado), aba Consolidado para os eventos confirmados de churn e downsell; aba Dados_Origem para MRR e clientes na base. Todos os valores desta aba são fórmulas sobre as demais abas.

Sheet Churn
A1: Cliente | B1: Produto | C1: Mês | D1: Motivo | E1: Grupo do motivo | F1: Perda (R$)
A2: Serios Agropecuária | B2: Agrimanager ERP | C2: Fev + Mai | D2: Troca de ERP | E2: Troca de ERP | F2: 16573.14
A3: Clodoveu Franciosi | B3: Agrimanager ERP | C3: Jun | D3: Troca de ERP | E3: Troca de ERP | F3: 13701.65
A4: Serra Bonita Sementes | B4: Agrimanager ERP | C4: Fev + Mai | D4: Venda da empresa | E4: Encerramento ou venda do negócio | F4: 6532.98
A5: 3SB Produtos Agrícolas | B5: Agrimanager ERP | C5: Fev | D5: Falta de flexibilidade e automação do AGM | E5: Produto | F5: 4170.46
A6: Bruno Sanches Toro | B6: Agrimanager ERP | C6: Jun | D6: Gap funcional do produto | E6: Produto | F6: 4010.69
A7: Claudio Augusto Diniz | B7: Agrimanager ERP | C7: Mai | D7: Baixa adoção / não uso | E7: Capacidade operacional do cliente | F7: 3408.4
A8: Natalino Bigolin | B8: Aliare Cloud | C8: Mai | D8: Gap funcional do produto | E8: Produto | F8: 3046.65
A9: Luis Henrique Pazini e outro | B9: My Farm ERP | C9: Mai | D9: Instabilidade do myFarm | E9: Produto | F9: 2775.55
A10: Zorzetto Assessoria e Consultoria Agronômica | B10: Agrimanager ERP | C10: Jun | D10: Troca de ERP | E10: Troca de ERP | F10: 2243.46
A11: Octaviano Raymundo Camargo Silva | B11: Agrimanager ERP | C11: Jun | D11: Falta de mão de obra | E11: Capacidade operacional do cliente | F11: 2150.61
A12: Valquiria Marcelino Ferreira Abreu | B12: Agrimanager ERP | C12: Mai | D12: Troca de ERP | E12: Troca de ERP | F12: 2110.81
A13: Clodoveu Franciosi | B13: Agrimanager Algodoeira | C13: Mar | D13: Troca de ERP | E13: Troca de ERP | F13: 1926.99
... A40: Leinner Lima Borges | B40: My Farm ERP | C40: Fev | D40: Instabilidade do myFarm | E40: Produto | F40: 302.91
A41: Total | F41: =SUM(F2:F40) -> 89646.72

Sheet Downsell
A1: Cliente | B1: Produto | C1: Mês | D1: Motivo | E1: Grupo do motivo | F1: Redução (R$)
A2: Leonardo Luiz Oss | B2: My Farm ERP | C2: Mai | D2: Internalização do serviço de BPO | E2: Internalização do serviço de BPO | F2: 4195.79
A3: Osvaldo Hanisch | B3: Agrimanager ERP | C3: Jun | D3: Reestruturação do quadro de colaboradores | E3: Redução de equipe no cliente | F3: 1484.86
A4: Dona Ema Agropecuária e Industrial | B4: Agrimanager ERP | C4: Fev | D4: Redução de custos | E4: Redução de custos | F4: 884.96
A5: Eduardo Zorzi | B5: Vistra BI | C5: Fev | D5: Baixa adoção / não uso | E5: Baixa adoção / não uso | F5: 865.52
A6: Marcelo Andre Konageski | B6: Agrimanager ERP | C6: Mai | D6: Redução de colaboradores | E6: Redução de equipe no cliente | F6: 580.08
A7: Mateus Eduardo Gonçalves Viana | B7: Agrimanager ERP | C7: Mar | D7: Redução de colaboradores | E7: Redução de equipe no cliente | F7: 561.54
A8: Cornelio Adriano Sanders e outros | B8: Agrimanager ERP | C8: Jun | D8: Redução de custos | E8: Redução de custos | F8: 514.72
A9: Leandro Caiaffa Orcay | B9: My Farm ERP | C9: Mai | D9: Renovação sem reajuste do INPC | E9: Renovação sem reajuste do INPC | F9: 213.03
A10: Ediana Edith Boeri | B10: My Farm ERP | C10: Mai | D10: Redução de custos | E10: Redução de custos | F10: 65.3
A11: Total | F11: =SUM(F2:F10) -> 9365.8
A13: Reduções de licenças ou de serviços em clientes que seguem ativos. Clientes que ficaram com uma ou duas licenças por módulo estão na aba Churn.

Sheet Motivo x Produto
A1: Perda por churn: grupo do motivo por produto
A3: Grupo do motivo | B3: Agrimanager ERP | C3: My Farm ERP | D3: Aliare Cloud | E3: Vistra BI | F3: Agrimanager Algodoeira | G3: Total (R$) | H3: Eventos | I3: % do total
A4: Troca de ERP | B4: =SUMIFS(Churn!$F:$F,Churn!$E:$E,$A4,Churn!$B:$B,B$3) -> 35669.38 | C4: =SUMIFS(Churn!$F:$F,Churn!$E:$E,$A4,Churn!$B:$B,C$3) -> 827.41 | D4: =SUMIFS(Churn!$F:$F,Churn!$E:$E,$A4,Churn!$B:$B,D$3) -> 1875.06 | E4: =SUMIFS(Churn!$F:$F,Churn!$E:$E,$A4,Churn!$B:$B,E$3) -> 0 | F4: =SUMIFS(Churn!$F:$F,Churn!$E:$E,$A4,Churn!$B:$B,F$3) -> 1926.99 | G4: =SUM(B4:F4) -> 40298.84 | H4: =COUNTIF(Churn!$E:$E,$A4) -> 8 | I4: =G4/$G$11 -> 0.44952944
A5: Produto | B5: =SUMIFS(Churn!$F:$F,Churn!$E:$E,$A5,Churn!$B:$B,B$3) -> 8181.15 | C5: =SUMIFS(Churn!$F:$F,Churn!$E:$E,$A5,Churn!$B:$B,C$3) -> 8706.9 | D5: =SUMIFS(Churn!$F:$F,Churn!$E:$E,$A5,Churn!$B:$B,D$3) -> 3046.65 | E5: =SUMIFS(Churn!$F:$F,Churn!$E:$E,$A5,Churn!$B:$B,E$3) -> 1865.58 | F5: =SUMIFS(Churn!$F:$F,Churn!$E:$E,$A5,Churn!$B:$B,F$3) -> 0 | G5: =SUM(B5:F5) -> 21800.28 | H5: =COUNTIF(Churn!$E:$E,$A5) -> 13 | I5: =G5/$G$11 -> 0.2431799
A6: Capacidade operacional do cliente | B6: =SUMIFS(Churn!$F:$F,Churn!$E:$E,$A6,Churn!$B:$B,B$3) -> 7216.48 | C6: =SUMIFS(Churn!$F:$F,Churn!$E:$E,$A6,Churn!$B:$B,C$3) -> 6082.73 | D6: =SUMIFS(Churn!$F:$F,Churn!$E:$E,$A6,Churn!$B:$B,D$3) -> 0 | E6: =SUMIFS(Churn!$F:$F,Churn!$E:$E,$A6,Churn!$B:$B,E$3) -> 777.26 | F6: =SUMIFS(Churn!$F:$F,Churn!$E:$E,$A6,Churn!$B:$B,F$3) -> 0 | G6: =SUM(B6:F6) -> 14076.47 | H6: =COUNTIF(Churn!$E:$E,$A6) -> 10 | I6: =G6/$G$11 -> 0.15702158
A7: Encerramento ou venda do negócio | B7: =SUMIFS(Churn!$F:$F,Churn!$E:$E,$A7,Churn!$B:$B,B$3) -> 6532.98 | C7: =SUMIFS(Churn!$F:$F,Churn!$E:$E,$A7,Churn!$B:$B,C$3) -> 1265.06 | D7: =SUMIFS(Churn!$F:$F,Churn!$E:$E,$A7,Churn!$B:$B,D$3) -> 0 | E7: =SUMIFS(Churn!$F:$F,Churn!$E:$E,$A7,Churn!$B:$B,E$3) -> 0 | F7: =SUMIFS(Churn!$F:$F,Churn!$E:$E,$A7,Churn!$B:$B,F$3) -> 0 | G7: =SUM(B7:F7) -> 7798.04 | H7: =COUNTIF(Churn!$E:$E,$A7) -> 3 | I7: =G7/$G$11 -> 0.086986339
A8: Financeiro do cliente | B8: =SUMIFS(Churn!$F:$F,Churn!$E:$E,$A8,Churn!$B:$B,B$3) -> 0 | C8: =SUMIFS(Churn!$F:$F,Churn!$E:$E,$A8,Churn!$B:$B,C$3) -> 772.9 | D8: =SUMIFS(Churn!$F:$F,Churn!$E:$E,$A8,Churn!$B:$B,D$3) -> 1650.36 | E8: =SUMIFS(Churn!$F:$F,Churn!$E:$E,$A8,Churn!$B:$B,E$3) -> 1655.56 | F8: =SUMIFS(Churn!$F:$F,Churn!$E:$E,$A8,Churn!$B:$B,F$3) -> 0 | G8: =SUM(B8:F8) -> 4078.82 | H8: =COUNTIF(Churn!$E:$E,$A8) -> 3 | I8: =G8/$G$11 -> 0.04549882
A9: Migração para solução própria | B9: =SUMIFS(Churn!$F:$F,Churn!$E:$E,$A9,Churn!$B:$B,B$3) -> 0 | C9: =SUMIFS(Churn!$F:$F,Churn!$E:$E,$A9,Churn!$B:$B,C$3) -> 1010.94 | D9: =SUMIFS(Churn!$F:$F,Churn!$E:$E,$A9,Churn!$B:$B,D$3) -> 0 | E9: =SUMIFS(Churn!$F:$F,Churn!$E:$E,$A9,Churn!$B:$B,E$3) -> 0 | F9: =SUMIFS(Churn!$F:$F,Churn!$E:$E,$A9,Churn!$B:$B,F$3) -> 0 | G9: =SUM(B9:F9) -> 1010.94 | H9: =COUNTIF(Churn!$E:$E,$A9) -> 1 | I9: =G9/$G$11 -> 0.011276932
A10: Sem informação | B10: =SUMIFS(Churn!$F:$F,Churn!$E:$E,$A10,Churn!$B:$B,B$3) -> 0 | C10: =SUMIFS(Churn!$F:$F,Churn!$E:$E,$A10,Churn!$B:$B,C$3) -> 583.33 | D10: =SUMIFS(Churn!$F:$F,Churn!$E:$E,$A10,Churn!$B:$B,D$3) -> 0 | E10: =SUMIFS(Churn!$F:$F,Churn!$E:$E,$A10,Churn!$B:$B,E$3) -> 0 | F10: =SUMIFS(Churn!$F:$F,Churn!$E:$E,$A10,Churn!$B:$B,F$3) -> 0 | G10: =SUM(B10:F10) -> 583.33 | H10: =COUNTIF(Churn!$E:$E,$A10) -> 1 | I10: =G10/$G$11 -> 0.0065069865
A11: Total | B11: =SUM(B4:B10) -> 57599.99 | C11: =SUM(C4:C10) -> 19249.27 | D11: =SUM(D4:D10) -> 6572.07 | E11: =SUM(E4:E10) -> 4298.4 | F11: =SUM(F4:F10) -> 1926.99 | G11: =SUM(G4:G10) -> 89646.72 | H11: =SUM(H4:H10) -> 39 | I11: =SUM(I4:I10) -> 1
A12: % do total por produto | B12: =B11/$G$11 -> 0.642522 | C12: =C11/$G$11 -> 0.21472364 | D12: =D11/$G$11 -> 0.073310769 | E12: =E11/$G$11 -> 0.047948213 | F12: =F11/$G$11 -> 0.021495377 | G12: =G11/$G$11 -> 1
A14: Somas por fórmula a partir da aba Churn (SUMIFS por grupo do motivo e produto).

Sheet Mês a mês
A1: Churn e downsell por mês, contra a referência de mercado
A3: Mês | B3: Perda por churn (R$) | C3: Downsell (R$) | D3: MRR base do mês (R$) | E3: Churn sobre o MRR | F3: Taxa anualizada | G3: Situação
A4: Jan | B4: 6776.64 | C4: =SUMIFS(Downsell!$F:$F,Downsell!$C:$C,A4) -> 0 | D4: 1325910.5 | E4: =B4/D4 -> 0.0051109333 | F4: =E4*12 -> 0.0613312 | G4: =IF(F4>0.15,"Acima do esperado","Dentro do esperado") -> Dentro do esperado
A5: Fev | B5: 27389.73 | C5: =SUMIFS(Downsell!$F:$F,Downsell!$C:$C,A5) -> 1750.48 | D5: 1320291.6 | E5: =B5/D5 -> 0.020745213 | F5: =E5*12 -> 0.24894255 | G5: =IF(F5>0.15,"Acima do esperado","Dentro do esperado") -> Acima do esperado
A6: Mar | B6: 2246.99 | C6: =SUMIFS(Downsell!$F:$F,Downsell!$C:$C,A6) -> 561.54 | D6: 1337681.5 | E6: =B6/D6 -> 0.0016797645 | F6: =E6*12 -> 0.020157174 | G6: =IF(F6>0.15,"Acima do esperado","Dentro do esperado") -> Dentro do esperado
A7: Abr | B7: 0 | C7: =SUMIFS(Downsell!$F:$F,Downsell!$C:$C,A7) -> 0 | D7: 1340358.8 | E7: =B7/D7 -> 0 | F7: =E7*12 -> 0 | G7: =IF(F7>0.15,"Acima do esperado","Dentro do esperado") -> Dentro do esperado
A8: Mai | B8: 21030.4 | C8: =SUMIFS(Downsell!$F:$F,Downsell!$C:$C,A8) -> 5054.2 | D8: 1328960.4 | E8: =B8/D8 -> 0.015824701 | F8: =E8*12 -> 0.18989641 | G8: =IF(F8>0.15,"Acima do esperado","Dentro do esperado") -> Acima do esperado
A9: Jun | B9: 32202.96 | C9: =SUMIFS(Downsell!$F:$F,Downsell!$C:$C,A9) -> 1999.58 | D9: 1299827.5 | E9: =B9/D9 -> 0.024774796 | F9: =E9*12 -> 0.29729755 | G9: =IF(F9>0.15,"Acima do esperado","Dentro do esperado") -> Acima do esperado
A10: Semestre | B10: =SUM(B4:B9) -> 89646.72 | C10: =SUM(C4:C9) -> 9365.8 | D10: =AVERAGE(D4:D9) -> 1325505 | E10: =B10/D10 -> 0.067632123 | F10: =E10*2 -> 0.13526425 | G10: =IF(F10>0.15,"Acima do esperado","Dentro do esperado") -> Dentro do esperado
A12: Referência de mercado para SaaS de médio porte: entre 10% e 15% de churn ao ano. A situação compara a taxa anualizada do mês com o teto de 15%. Na linha Semestre, a taxa é a perda do semestre sobre o MRR médio, vezes 2.
A13: Perda por churn alocada pela competência de faturamento. Serios Agropecuária e Serra Bonita Sementes tiveram eventos em fevereiro e maio e aparecem na aba Churn com os dois meses.
A14: MRR base do mês: planilha de origem (Churn Tratado), aba Dados_Origem.

Sheet Por cliente
A1: Cliente | B1: Perda por churn (R$) | C1: Eventos | D1: % acumulado
A2: Serios Agropecuária | B2: =SUMIF(Churn!$A:$A,A2,Churn!$F:$F) -> 16573.14 | C2: =COUNTIF(Churn!$A:$A,A2) -> 1 | D2: =SUM($B$2:B2)/$B$39 -> 0.18487168
A3: Clodoveu Franciosi | B3: =SUMIF(Churn!$A:$A,A3,Churn!$F:$F) -> 15628.64 | C3: =COUNTIF(Churn!$A:$A,A3) -> 2 | D3: =SUM($B$2:B3)/$B$39 -> 0.35920756
A4: Serra Bonita Sementes | B4: =SUMIF(Churn!$A:$A,A4,Churn!$F:$F) -> 6532.98 | C4: =COUNTIF(Churn!$A:$A,A4) -> 1 | D4: =SUM($B$2:B4)/$B$39 -> 0.43208229
A5: Bruno Sanches Toro | B5: =SUMIF(Churn!$A:$A,A5,Churn!$F:$F) -> 5661.05 | C5: =COUNTIF(Churn!$A:$A,A5) -> 2 | D5: =SUM($B$2:B5)/$B$39 -> 0.49523072
A6: 3SB Produtos Agrícolas | B6: =SUMIF(Churn!$A:$A,A6,Churn!$F:$F) -> 4170.46 | C6: =COUNTIF(Churn!$A:$A,A6) -> 1 | D6: =SUM($B$2:B6)/$B$39 -> 0.54175178
A7: Claudio Augusto Diniz | B7: =SUMIF(Churn!$A:$A,A7,Churn!$F:$F) -> 3408.4 | C7: =COUNTIF(Churn!$A:$A,A7) -> 1 | D7: =SUM($B$2:B7)/$B$39 -> 0.57977213
A8: Natalino Bigolin | B8: =SUMIF(Churn!$A:$A,A8,Churn!$F:$F) -> 3046.65 | C8: =COUNTIF(Churn!$A:$A,A8) -> 1 | D8: =SUM($B$2:B8)/$B$39 -> 0.6137572
A9: Luis Henrique Pazini e outro | B9: =SUMIF(Churn!$A:$A,A9,Churn!$F:$F) -> 2775.55 | C9: =COUNTIF(Churn!$A:$A,A9) -> 1 | D9: =SUM($B$2:B9)/$B$39 -> 0.64471818
A10: Zorzetto Assessoria e Consultoria Agronômica | B10: =SUMIF(Churn!$A:$A,A10,Churn!$F:$F) -> 2243.46 | C10: =COUNTIF(Churn!$A:$A,A10) -> 1 | D10: =SUM($B$2:B10)/$B$39 -> 0.66974375
A11: Octaviano Raymundo Camargo Silva | B11: =SUMIF(Churn!$A:$A,A11,Churn!$F:$F) -> 2150.61 | C11: =COUNTIF(Churn!$A:$A,A11) -> 1 | D11: =SUM($B$2:B11)/$B$39 -> 0.69373358
A12: Valquiria Marcelino Ferreira Abreu | B12: =SUMIF(Churn!$A:$A,A12,Churn!$F:$F) -> 2110.81 | C12: =COUNTIF(Churn!$A:$A,A12) -> 1 | D12: =SUM($B$2:B12)/$B$39 -> 0.71727945
A13: Sementes Três Pinheiros Seeds | B13: =SUMIF(Churn!$A:$A,A13,Churn!$F:$F) -> 1875.06 | C13: =COUNTIF(Churn!$A:$A,A13) -> 1 | D13: =SUM($B$2:B13)/$B$39 -> 0.73819555
... A38: Leinner Lima Borges | B38: =SUMIF(Churn!$A:$A,A38,Churn!$F:$F) -> 302.91 | C38: =COUNTIF(Churn!$A:$A,A38) -> 1 | D38: =SUM($B$2:B38)/$B$39 -> 1
A39: Total | B39: =SUM(B2:B38) -> 89646.72 | C39: =SUM(C2:C38) -> 39
A41: Clientes em ordem decrescente de perda. Somas por fórmula a partir da aba Churn.

Sheet Movimentação MRR
A1: Mês | B1: Novos clientes (R$) | C1: Upsell (R$) | D1: Reajuste (R$) | E1: Ajustes (R$) | F1: Downsell (R$) | G1: Churn (R$) | H1: Saldo líquido (R$) | I1: MRR base (R$) | J1: Clientes na base
A2: Jan | B2: 4815.29 | C2: 3301.64 | D2: 225.325 | E2: -4985.29 | F2: -1693.5217 | G2: -5119.17 | H2: =SUM(B2:G2) -> -3455.7267 | I2: 1325910.5 | J2: 470
A3: Fev | B3: 13662.66 | C3: 10796.99 | D3: 1889.3692 | E3: 0 | F3: -22881.82 | G3: -13233.29 | H3: =SUM(B3:G3) -> -9766.0908 | I3: 1320291.6 | J3: 479
A4: Mar | B4: 14361.57 | C4: 7665.44 | D4: 813.3025 | E4: -818.96 | F4: -561.54 | G4: -4069.8698 | H4: =SUM(B4:G4) -> 17389.943 | I4: 1337681.5 | J4: 486
A5: Abr | B5: 2279.96 | C5: 837.9 | D5: -339.75833 | E5: 56.41 | F5: 0 | G5: -157.28 | H5: =SUM(B5:G5) -> 2677.2317 | I5: 1340358.8 | J5: 484
A6: Mai | B6: 6849.4 | C6: 504.4 | D6: 6940.9252 | E6: 391.44 | F6: -12235.12 | G6: -13849.484 | H6: =SUM(B6:G6) -> -11398.439 | I6: 1328960.4 | J6: 487
A7: Jun | B7: 2931.66 | C7: 3088.12 | D7: 0 | E7: -391.44 | F7: -16259.92 | G7: -18501.31 | H7: =SUM(B7:G7) -> -29132.89 | I7: 1299827.5 | J7: 484
A8: Semestre | B8: =SUM(B2:B7) -> 44900.54 | C8: =SUM(C2:C7) -> 26194.49 | D8: =SUM(D2:D7) -> 9529.1635 | E8: =SUM(E2:E7) -> -5747.84 | F8: =SUM(F2:F7) -> -53631.922 | G8: =SUM(G2:G7) -> -54930.404 | H8: =SUM(H2:H7) -> -33685.972
A9: Média do semestre | I9: =AVERAGE(I2:I7) -> 1325505 | J9: =AVERAGE(J2:J7) -> 481.66667
A11: Valores da planilha de origem (Churn Tratado), aba Dados_Origem. As colunas Downsell e Churn refletem toda a movimentação registrada no faturamento, incluindo ajustes de contrato e correções, por isso diferem das abas Churn e Downsell deste arquivo.

Sheet Plano de ação
A1: Frente | B1: Ação | C1: Descrição | D1: Status | E1: Indicador acompanhado | F1: Responsável
A2: AgriManager, presencial | B2: Seis viagens a clientes ao longo do ano | C2: Visitas presenciais para entender a operação de cada cliente, mapear oportunidades e antecipar risco de saída. Goiás (região de Formosa; região de Rio Verde e Mineiros), Mato Grosso (Sapezal e região; Sorriso e região), Maranhão (Balsas) e Bahia (região de Luís Eduardo Magalhães). | D2: Realizado | E2: Clientes visitados, oportunidades geradas e pendências por cliente | F2: Gestão com o time de CS
A3: Telemetria de produto | B3: Reengajar quem não está acessando | C3: A telemetria passou a mostrar quem usa e quem não usa. Cliente sem acesso recebe contato do CS, conexão com consultor e horas de treinamento bonificadas para voltar a operar. | D3: Em andamento | E3: Clientes sem acesso, por semana | F3: Time de CS, com os dados de telemetria
A4: Telemetria de produto | B4: Pílulas de conhecimento no momento certo da safra | C4: Vídeos curtos sobre planejamento de safra, cadastro de talhões, atividades de campo e lançamento de colheita, disparados em massa pelo CS e no aviso de entrada do MyFarm. | D4: A iniciar | E4: Clientes que passam a usar as telas depois do disparo | F4: Consultores gravam, CS dispara, produto avalia o aviso dentro do MyFarm
A5: Produto e desenvolvimento | B5: Clientes em risco tratados junto com produto | C5: Levantar os clientes com a dor mais latente (chamados de erro frequentes, sinais de cancelamento), trazer para perto e dar prioridade na fila de desenvolvimento. | D5: A iniciar | E5: Lista de clientes em risco e prazo de resposta de produto para cada um | F5: Operações com o time de produto
A6: MyFarm | B6: Contato ativo com toda a base MyFarm desde 2025 | C6: Cada cliente que entrou de 2025 para cá recebe contato para entender se usa a ferramenta e se precisa de ajuda. Consultores de projeto sem agenda entram nesse esforço. | D6: Em andamento | E6: Clientes contatados por semana e quantos voltaram a usar | F6: CS e equipe de projetos
A7: AgriManager, remoto | B7: Revisitar quem já foi visitado e cobrir o restante por agenda remota | C7: Retomar cada cliente das viagens: o que ficou pendente, quais oportunidades surgiram, provas de conceito incluídas, e como está hoje. Para os demais, agendas remotas marcadas pelo CS e conduzidas pela gestão, apresentando a vertical de produtor rural. | D7: A iniciar | E7: Clientes revisitados e agendas remotas realizadas | F7: CS marca, gestão conduz
